Workbook

Sheet Budget
A1: to | B1: trip | C1: date - | D1: destination | E1: ticket | F1: visa | G1: currency commission | H1: acc | I1: misc | J1: transport inc airport | K1: food | L1: extra kg | M1: cargo | N1: airport duty | O1: stock | P1: personal | Q1: 2 MONTHS RENTAL | R1: 2 MONTHS SALARIES | S1: TOTAL COST | T1: TOTAL overheads | U1: total recommende sales value | V1: total actual sales value | W1: profit | X1: profit in USD
B3: istanbul | C3: 30 may-10 june 2021 | D3: istanbul | E3: 930 | F3: 230 | H3: 200 | J3: 10 | K3: 50 | M3: =886+1723+1000 -> 3609 | O3: 9148 | P3: 500 | Q3: 400 | R3: 400 | S3: =SUM(E3:R3) -> 15477
B7: istanbul november 2021 trip
B8: 0 | G8: =844*0.04+75 -> 108.76 | H8: =25*6 -> 150 | I8: =3*15+10 -> 55 | J8: 50 | K8: 20 | L8: 250 | M8: 1200 | N8: 360 | O8: 6556 | P8: 0 | Q8: 400 | R8: 600 | S8: =SUM(B8:R8) -> 9749.76
B10: istanbul kapura Dec | I10: =+O10*0.06 -> 210.3 | M10: =70*17+50+20*17+50 -> 1630 | O10: =1992+1048+465 -> 3505 | Q10: 200 | R10: 700 | S10: =SUM(G10:R10) -> 6245.3
B13: istanbul april2022 | E13: 850 | H13: =135+60 -> 195 | I13: 55 | J13: 50 | K13: 20 | L13: =4*110+75*3 -> 665 | M13: =80*17.5+50 -> 1450 | N13: =720+15+40 -> 775 | O13: =+'stock purchase 2023'!#REF! -> #REF! | P13: =100+15+35+20+17+18+15+10+35 -> 265 | Q13: 300 | R13: 375 | S13: =SUM(E13:R13) -> #REF!
B16: istanbulsept 2022 | C16: 10 -22 sept | D16: istanbul | E16: =1220+135 -> 1355 | F16: 220 | G16: =3000*0.05 -> 150 | H16: =40+30*5+80 -> 270 | I16: 50 | J16: 50 | K16: 50 | L16: =3*120+4*75 -> 660 | M16: 0 | N16: =600+30+40 -> 670 | O16: 6911 | P16: =66+10+200+40+50 -> 366 | Q16: 500 | R16: 375 | S16: =SUM(E16:R16) -> 11627 | T16: =+E16+F16+G16+H16+I16+J16+K16+L16+M16+N16+P16+Q16+R16 -> 4716
B17: via Germany | C17: 17-20 sept | D17: germany | E17: 370
B19: ISTANBUL | C19: 19-27 NOV | D19: ISTANBUL | E19: 800 | H19: 250 | I19: 16 | J19: 50 | K19: 50 | L19: 200 | N19: 480 | O19: 4607 | P19: 250 | Q19: 500 | R19: 400 | S19: =SUM(E19:R19) -> 7603 | T19: =+S19-O19 -> 2996 | U19: =+'stock purchase 2023'!#REF! -> #REF! | V19: =+'stock purchase 2023'!#REF! -> #REF! | W19: =+V19-S19 -> #REF!
B23: istanbul March 2023 | C23: 5-12 mar | D23: istanbul | E23: 1235 | H23: 240 | I23: 100 | J23: 50 | K23: 50 | L23: =500+225 -> 725 | N23: 840 | O23: 8267 | P23: 50 | Q23: =+(2200+500) -> 2700 | R23: 1000 | S23: =SUM(E23:R23) -> 15257 | T23: =+S23-O23 -> 6990
B24: via Germany | C24: 28 feb-4 march | D24: germany | E24: 100 | H24: 180 | I24: 50 | J24: 40 | K24: 40 | S24: =SUM(E24:R24) -> 410 | T24: =+S24 -> 410
T25: =SUM(T23:T24) -> 7400
B26: istanbul | C26: 7-13 march | D26: istanbul | E26: 951 | H26: 240 | I26: 100 | J26: =50+30 -> 80 | K26: =50+20 -> 70 | L26: =500+75*9 -> 1175 | N26: =8*120+90 -> 1050 | O26: 9682 | P26: 400 | Q26: =2200+500 -> 2700 | R26: =+(400+400+200) -> 1000 | S26: =SUM(E26:R26) -> 17448 | T26: =+S26-O26 -> 7766
L28: =+E26+H26+I26+J26+K26+L26+N26 -> 3666 | M28: =+L26+N26 -> 2225 | N28: =32*8 -> 256
L29: =+L28/N28 -> 14.320312 | N29: =+M28/N28 -> 8.6914062
B30: ISTANBUL MAY 2023
B34: ISTANBUL | C34: 2-9 JULY 2023 | D34: istanbul | E34: 1080 | H34: 200 | I34: 50 | J34: =40+40+5+7 -> 92 | K34: 20 | L34: =130+300 -> 430 | M34: =15*16.5+25 -> 272.5 | N34: 480 | O34: 6066 | P34: 200 | Q34: =950*2+250*2 -> 2400 | R34: =+(175*2+100*2)+240 -> 790 | S34: =SUM(E34:R34) -> 12080.5 | T34: =+S34-O34 -> 6014.5
B37: istanbul sept/oct | C37: 25-29 15-18 | D37: istanbul | E37: 930 | F37: 400 | H37: =8*45 -> 360 | I37: =60+100+35+35 -> 230 | J37: =50+30+40+10 -> 130 | K37: 50 | L37: =2*120+3*75 -> 465 | M37: =502+25*16.5+25*16.5 -> 1327 | N37: =4*120 -> 480 | O37: 6440 | P37: 100 | Q37: =950*2+250*2 -> 2400 | R37: =+(175*2+120*2)+240 -> 830 | S37: =SUM(E37:R37) -> 14142 | T37: =+S37-O37 -> 7702
B38: new york | C38: 30-14 oct | D38: new york/ florida | E38: 900 | F38: 160 | H38: =593+180 -> 773 | J38: =42+42+27+60+17+14+8 -> 210 | K38: 180 | L38: =30+40 -> 70 | N38: 120 | O38: 1327 | P38: =54+25+35+29+20+53 -> 216 | S38: =SUM(E38:R38) -> 3956 | T38: =+S38-O38 -> 2629
B39: total | E39: =SUM(E37:E38) -> 1830 | F39: =SUM(F37:F38) -> 560 | G39: =SUM(G37:G38) -> 0 | H39: =SUM(H37:H38) -> 1133 | I39: =SUM(I37:I38) -> 230 | J39: =SUM(J37:J38) -> 340 | K39: =SUM(K37:K38) -> 230 | L39: =SUM(L37:L38) -> 535 | ... P39: =SUM(P37:P38) -> 316 | S39: =SUM(S37:S38) -> 18098 | T39: =SUM(T37:T38) -> 10331
B41: BABY WEAR | C41: 25-29 15-18 | D41: istanbul | E41: 300 | F41: 50 | G41: 0 | H41: 0 | I41: 100 | J41: 20 | K41: 20 | L41: 200 | M41: 439 | N41: 120 | O41: 2400 | Q41: 500 | R41: 300 | S41: =SUM(E41:R41) -> 4449 | T41: =+S41-O41 -> 2049
B44: istanbul | C44: 13-20nov | D44: istanbul | E44: 800 | H44: =6*45 -> 270 | I44: 50 | J44: 30 | K44: 50 | M44: 902 | O44: 3687 | P44: 30 | Q44: 500 | R44: =350+240+360 -> 950 | S44: =SUM(E44:R44) -> 7269 | T44: =+S44-O44 -> 3582
B45: BABY WEAR | E45: 300 | H45: =2*35 -> 70 | I45: 150 | K45: 20 | M45: =568-8*15.5+600 -> 1044 | O45: 1215 | P45: 20 | Q45: 500 | R45: 420 | S45: =SUM(E45:R45) -> 3739 | T45: =+S45-O45 -> 2524
B47: baby wear omer | C47: cargo | M47: 400 | O47: 532 | Q47: 500 | R47: 400 | S47: =SUM(E47:R47) -> 1832 | T47: =+S47-O47 -> 1300
B83: NOTES
B84: MARCH TRIP - | C84: FIND MANY CLEARANCE SALES, good opportunity for big margins
C85: buy outfits & dresses for occassions then
C86: buy winter items and leave for may, can also do kapura
C87: if i buy winter things on layby i should not do a trip in June coz this coincides with layby final payments, cargo costs and duty.
C88: unless the trip is for going to collect the items on layby
C89: JACKETS ARE NOT PROFITABLE IF BOUGHT FOR MORE THAN $15 EACH
C90: winter items are bulky and heavy. Resulting in high cargo charges. Better to buy winter items all through out the year.
E93: jan-dec 208m
E105: SALES ANALYSIS 2016-2021
E106: month | F106: 2016 | G106: 2017 | H106: 2018 | I106: 2019 | J106: 2020 | K106: 2021
E107: jan | F107: 3811 | I107: 2814 | J107: 4180
E108: feb | F108: 4126 | I108: 2883 | J108: 3413
E109: mar | F109: 5742 | I109: 6262 | J109: 6532
E110: apr | F110: 12651 | I110: 2162 | J110: 128
E111: may | F111: 5651 | I111: 6517 | J111: 3594
E112: jun | F112: 8161 | I112: 1498 | J112: 3961
E113: jul | F113: 6484 | I113: 6873 | J113: 5060
E114: aug | F114: 8230 | I114: 5505 | J114: 3150
E115: sept | I115: 7189 | J115: 5083
E116: oct | I116: 6691 | J116: 3875
E117: nov | I117: 6841 | J117: 4706
E118: dec | I118: 7148 | J118: 6947
B126: sales graph since inception
C127: month | D127: sales | E127: expenses | F127: stock
C128: 42248 | D128: 6540 | E128: 4941
C129: 42278 | D129: 11157 | E129: 5768
C130: 42309 | D130: 6993 | E130: 2988 | F130: 4682
C131: 42339 | D131: 9405 | E131: 7452
C132: 42370 | D132: 3811 | E132: 4168 | F132: 2074
C133: 42401 | D133: 4126 | E133: 3225
C134: 42430 | D134: 5742 | E134: 3971 | F134: 10401
C135: 42461 | D135: 12651 | E135: 4337 | F135: 1250
C136: 42491
C137: 42522
C138: 42552
C141: total | D141: =SUM(D128:D140) -> 60425
B144: MARCH CASH BUDGET
D145: Rent | E145: 200 | G145: fron daily sales | I145: 100 | J145: per week for rent
D146: round table | E146: 90 | I146: 50 | J146: per week for client refund
D147: visa insurance | E147: 38 | I147: 20 | J147: per week tete connie
D148: visa application | E148: 200 | I148: 150 | J148: per week savings
D149: kudzi refund | E149: 90
D150: china dresses | E150: 300 | I150: =SUM(I145:I149) -> 320
D151: turkey cargo | E151: 150
D152: carpenter shop shelving | E152: 70
D153: shop licence | E153: 300
D154: vida track suit | E154: 41
E158: =SUM(E145:E157) -> 1479
D159: seke
D160: fence | E160: 130
D161: poles | E161: 70

Sheet STOCK TAKE
A1: to
B2: STOCK TAKE OCTOBER 2020
B4: LABEL | C4: DESCRIPTION | D4: PURCHASE PRICE | E4: SALE PRICE | J4: LABEL | K4: DESCRIPTION | L4: PURCHASE PRICE | M4: SALE PRICE
B6: MISSING STOCK | J6: MISSING STOCK
A7: 1 | B7: Le mirage | C7: burnt orage/white 2 piece | D7: 25 | I7: 1 | J7: adalyn | K7: navy dress w pleated back
A8: 2 | B8: le mirage | C8: navy 2 pc w printed skirt | D8: 25 | J8: versace | K8: grey 2 piece track suit from avondale
A9: 3 | B9: ell shirt dress | C9: shirt dress | D9: 9 | J9: nesly | K9: coffee suit
B10: tights | C10: tights | D10: 5 | K10: nesly coffee suit
B11: oreya | C11: maroon sude wedge shoe | D11: 8 | J11: TANGO EZGI | K11: PINK TOP/FLOWERY SKIRT
D12: =SUM(D7:D11) -> 72
B13: eastgate sales
A14: 1 | B14: yuxi fashion | C14: red wrap over dress | D14: 10 | E14: 45
C15: green dress cotton multi colour
B17: SALES ANALYSIS BY CATGORY
B18: STOCK | C18: OPENING QNTY | D18: CLOSING QNTY | E18: SALES QNTY | F18: % SALE | K18: stock not on stock sheet
B19: DRESS OUTFITS | J19: 1 | K19: mardi | L19: green/beige floral flared dress repeat - | M19: 28 | N19: 110
B20: 2 PIECE OUTFITS
B21: DRESSES | C21: 669 | D21: 355 | E21: =+C21-D21 -> 314 | F21: =+E21/C21*100 -> 46.935725 | K21: oreya white t shirt w front glitter
B22: SKIRTS | C22: 106 | D22: 83 | E22: =+C22-D22 -> 23 | F22: =+E22/C22*100 -> 21.698113 | K22: FI & BI | L22: black jeggin 46 | M22: sold but not on stocksheet
B23: TOPS | C23: 155 | D23: 86 | E23: =+C23-D23 -> 69 | F23: =+E23/C23*100 -> 44.516129
B24: TROUSERS | C24: 59 | D24: 34 | E24: =+C24-D24 -> 25 | F24: =+E24/C24*100 -> 42.372881
B25: WOOLEN TOPS | C25: 99 | D25: 41 | E25: =+C25-D25 -> 58 | F25: =+E25/C25*100 -> 58.585859
B26: JACKETS | C26: 31 | D26: 22 | E26: =+C26-D26 -> 9 | F26: =+E26/C26*100 -> 29.032258
B27: JERSEY | C27: 59 | D27: 26 | E27: =+C27-D27 -> 33 | F27: =+E27/C27*100 -> 55.932203
B28: TRACK SUITS | C28: 59 | D28: 34 | E28: =+C28-D28 -> 25 | F28: =+E28/C28*100 -> 42.372881
B29: SHOES | C29: 200 | D29: 111 | E29: =+C29-D29 -> 89 | F29: =+E29/C29*100 -> 44.5
B30: CLUTCH | C30: 12 | D30: 6 | E30: =+C30-D30 -> 6 | F30: =+E30/C30*100 -> 50
B31: COSERT | C31: 10 | D31: 4 | E31: =+C31-D31 -> 6 | F31: =+E31/C31*100 -> 60
B32: HANDBAGS | C32: 25 | D32: 9 | E32: =+C32-D32 -> 16 | F32: =+E32/C32*100 -> 64
B33: PANTY | C33: 103 | D33: 49 | E33: =+C33-D33 -> 54 | F33: =+E33/C33*100 -> 52.427184
B34: GYPSY SOCKS | C34: 40 | D34: 36 | E34: =+C34-D34 -> 4 | F34: =+E34/C34*100 -> 10
B45: OCTOBER STOCK TAKE 2022
C46: over | D46: under
B47: OVERS
B48: rouge grey knit dress 2 pc w hood
B50: UNDER
A51: channel | B51: navy | E51: balance with the one addedback jan 2022 stock take
B52: SKIRTS
A53: escarell | B53: black knit | E53: To check amount actually bought
A54: escarell | B54: black knit | E54: To check amount actually bought
B56: TROUSERS
A57: la gazelle | B57: 8 | C57: 36 | D57: trousers
A58: la curuse | B58: 14 | C58: 52 | D58: denim trousers
B59: SHIRTS & TOPS
A60: oreya | B60: white sleeveless long t shirt | C60: M
B61: WOOLEN TOPS
A62: oreya | B62: light throw blue with glitter front
A63: oreya | B63: polo neck burgundy
A64: oreya | B64: polo neck burgundy
A65: oreya | B65: twin set black | C65: L
A66: oreya | B66: t shirt jacket black
B68: JERSEYS
A69: oreya | B69: navy / maroon short jersey
A70: oreya | B70: jersey maroon with fur neck & sleeves 2020
B72: TRACK SUITS
A73: versace | B73: versarche grey trouser set
A74: bavinchi | B74: NAVY 3 PIECE | C74: 4xl
B76: SHOES
A77: ALTIN YAK | B77: maroon wedge
A78: ALTIN YAK | B78: black wedge w elastic top
B79: HANDBAGS
B80: LV black handbag w single handle
B82: ladies ankle socks black
A84: scarfs | B84: all colours

Sheet cashflow
A1: to | B1: CASHFLOW -2018 | C1: Jan | D1: Feb | E1: Mar | F1: Apr | G1: May | H1: Jun | I1: Jul | J1: Aug | K1: Sep | L1: Oct | M1: Nov | N1: Dec | P1: %
B2: INFLOWS
B3: SALES
B4: Cash sales | C4: =+'daily sales'!B139 -> 3230
B5: pos purchases
C6: =SUM(C4:C5) -> 3230
B8: LOANS
B9: stanbic bank loan
B10: loans personal
B11: loans other
B14: refunds
B17: Total | C17: =+C6+C12+C14 -> 3230
B19: MONTHLY EXPENSES
B20: stock purchases | C20: =+cashbook!#REF!+cashbook!#REF!+cashbook!#REF!+cashbook!#REF!+cashbook!#REF! -> #REF! | S20: 145
B22: operating expenses | C22: =SUM(C23:C58) -> 1903 | S22: 255
B23: parking | C23: 10 | S23: 75
B24: fuel | C24: 20 | S24: 50
B25: salaries
B26: Pauline | S26: 155
B27: Tatenda | S27: 323
B28: allowance self | C28: 321 | S28: 195
B29: staff transport allowance | S29: 62
B30: Pauline | C30: =87+18 -> 105
B31: Tatenda
B32: staff commission
B33: Pauline | C33: 21
B34: Tatenda | C34: 21
B35: rentals | C35: 250 | S35: 30
B36: rates | S36: =SUM(S20:S35) -> 1290
B37: electricity
B38: cleaning & packaging materials & shop utilities | C38: 10
B39: stationery
B40: car running expenses | R40: =346-24-13 -> 309
B41: miscellaneous
B42: airtime | C42: 50
B43: Business refreshments
B44: small asset procurement
B45: big asset procurement | C45: 600
B46: sales discount
B47: refunds
B48: money transfer charges
B49: membership fees
B50: licence fees and registrations | C50: 410
B51: gym subs & training
B52: bank fees & charges
B53: pos bank comission 2.5%
B54: zimra QPD
B55: medical | C55: 85
B56: donations
B57: company fees
B59: stock procurement costs | C59: =SUM(C60:C74) -> 1352
B60: visa
B61: ticket | C61: =1259+93 -> 1352
B62: extra kgs - bags packed to 32kg
B63: Luggage exess bags
B64: accomodation
B65: transport
B66: food
B67: cargo
B68: duty
B69: travel incidentals
B70: transportation charge for goods from a/port
B71: airport fees
B72: T & S
B73: loss on change of ticket
B74: PASSPORT APPLICATION
B75: EDUCATION | C75: =SUM(C76:C79) -> 0
B76: school fees.
B77: monthly allowance
B78: other
B80: LOAN REPAYMENT: | C80: =SUM(C81:C86) -> 0
B81: loan sharewealth
B82: loan ruwa ladies
B83: stanbic business loan
B84: loans others
B85: other loans
B87: TOTAL EXPENDITURE | C87: =+C80+C75+C59+C22+C20 -> #REF!
B90: TOTAL INCOME | C90: =+C17 -> 3230
B91: TOTAL EXPENSES | C91: =+C87 -> #REF!
B93: SURPLUS/DEFICIT | C93: =+C90-C91 -> #REF!
B96: INVESTMENTS
B97: Allan Gray
B98: home improvement/ construction
B99: $600 round
B100: $10 daily savings
B101: $20 daily savings
B102: school fees fund
B103: TOTAL
B115: NOTES
B116: sharewealth bricks loan to be classsified as home improvements
B117: major expenditure in 2020 included the construction and roofing of the house extension/cottage. Plumbing works and construction of the storm water drain,
B121: sales schedule
... B132: july

Sheet cashbook
A1: to | C1: cash USD | D1: debit card | E1: Cash bond ecocash | F1: cash /DEBIT convert to USD | G1: TOTAL | J1: expenditure | K1: cash | L1: personal
I2: 45292 | J2: 1K ROUND | K2: 1000
I3: week 1-2 | J3: FSBS club round | K3: 300
J4: teamwork | K4: 300
J5: sharewealth | K5: 1000
J6: shop licence | K6: =3865400/10800 -> 357.90741
J7: transport x2 weeks | K7: =15+15+12 -> 42
J8: personal round table | L8: 70
J9: simukai support jan | K9: 75
I10: week 3 | J10: transport tatenda | K10: 18
I11: 15-20 jan | J11: fire extinguisher service | K11: 20
J12: shop supplies | K12: 5
J13: personal, | L13: =240000/11000+10 -> 31.818182
I14: 22-27 jan | J14: transport tatenda | K14: 18
J15: plastic packaging | K15: 20
J16: personal | L16: =20+28+10+20 -> 78
I17: 29-31 jan | J17: transport tatenda | K17: 18
J18: transport Pau | K18: 18
J25: FEBRUARY
I26: week 1 | J26: Salary Tatenda | K26: 175
J27: Salary Pau | K27: 175
J28: transport allowance pau | K28: 15
J29: transport allowance tatenda | K29: 15
I30: week 2 | J30: transport allowance pau | K30: 15
J31: transport allowance tatenda | K31: 15
J32: advertising online casper | K32: 60
J33: 1 k round | K33: 1000
J34: baby shop goodwill | K34: 1000
J35: baby shop original stock | K35: 780
J36: staff december commisions | K36: 110
J37: turkey ticket (kudzai loan) | K37: =731+190 -> 921
J38: shop utilities - plastic packaging | K38: 20
J39: personal fsbs jan subs | L39: 80
J40: round table jan | K40: 70
J41: personal, | L41: =10+30+20 -> 60
I42: week 3 | J42: transport allowance pau | K42: 15
J43: transport allowance tatenda on sick leave) | K43: 6
J44: RENTALS | K44: 230
J45: personal | L45: =14+10 -> 24
I46: week 4 | J46: transport allowance pau | K46: 15
J47: transport allowance tatenda | K47: 15
J48: cargo temel | K48: 215
J49: TOTAL | K49: =SUM(K26:K48) -> 4867 | L49: =SUM(L26:L48) -> 164
J51: MARCH
I52: WEEK 1 | J52: Salary Tatenda | K52: 175
J53: Salary Pau | K53: 175
J54: transport allowance pau | K54: 15
J55: transport allowance tatenda | K55: 15
J56: 1 k round | K56: 1000
J57: baby shop goodwill | K57: 1000
J58: PERSONAL | L58: 10
J59: personal tithe | L59: 50
J60: personal fsbs round | L60: 300
J61: roundtable | K61: 270
I62: week2 | J62: turkey travel
J63: stock
J64: food
J65: transprt
J66: personal
J67: transport allowance pau | K67: 15
J68: transport allowance tatenda | K68: 15
I69: week 3 & 4 | J69: transport allowance pau | K69: =15+20 -> 35
J70: transport allowance tatenda | K70: 15
J71: rent - OPC FEB | K71: 20
J72: REnt - OPC mar | K72: 20
J73: plastic packaging | K73: 20
J74: personal (client bedspread) | L74: 100
J75: cargo temel | K75: 934
J76: stock pur ideal | K76: 848
J77: sending charges | K77: =+K76*0.045 -> 38.16
J78: staff lunches | K78: 15
J79: kudzi repayment | K79: 20
J80: staff lunches | K80: 10
J81: personal | L81: 15
J85: APRIL
I86: WEEK 1 | J86: Salary Pau | K86: 200
J87: salary tatenda | K87: 175
J88: transport pau | K88: 15
J89: personal | K89: 30
J90: cargo - ideal shop consignment | K90: 242
J91: 1k round | K91: 1000
J92: teamwork | K92: 300
J93: baby shop - stock pymnt to pamela 1140-500 | K93: 500
J94: personal | L94: 30
I95: week 2 | J95: transport pau | K95: 20
J96: personal | L96: 30
J97: sharewealth loan repayment nov '23 turkey trip | K97: 450
J98: loan interest ruwa round table - march turkey stock | K98: 250
J99: kudzai loan repayment - march turkey stock | K99: 200
J100: personal | L100: =150+30 -> 180
I101: week 3 | J101: maud loan - march turkey stock | K101: 80
I102: 14-20 | J102: personal midziyo round | L102: 100
J103: shop utilities brooms& mops | K103: 16
J104: shop rental march EB and Collectables | K104: =230+240 -> 470
J105: cargo - nesly shop stock | K105: 364
J106: march rental exotic blossom | K106: =230+20 -> 250
J107: march rental collectibles | K107: =240+20 -> 260
I108: week 4 | J108: transport pau | K108: 15
I109: 21- 26 | J109: transport tatenda | K109: 15
J110: personal | L110: =15+5+40 -> 60
...

Sheet cash budget
A3: =+'daily sales'!#REF!+'daily sales'!#REF! -> #REF! | E3: =1014+2900+594 -> 4508
E5: 900
A6: =SUM(A3:A5) -> #REF! | E6: =SUM(E2:E5) -> 5408
M8: nov
B9: 15
A13: 10
A14: 120 | B14: 80
A15: 375 | B15: 250 | C15: 245 | E15: =150+260 -> 410 | F15: 550
A16: 465 | C16: 465 | E16: 458 | F16: 450
A17: 30 | B17: 15
A22: 20
A23: 55 | C23: 70
A24: 550
A25: 165
A29: =400+40+40 -> 480
A30: 740.6 | F30: 1345
B31: 200 | F31: 200
F33: =30*4 -> 120
F34: 50
F35: 50
F37: 300
F40: 200
E43: 1820
A46: 75
A49: 500 | B49: =500+376 -> 876 | E49: 798 | F49: 249
A50: 263 | C50: 358 | E50: 1525 | F50: 300
A52: 543 | C52: 543 | E52: 543 | F52: 543
A55: 500 | C55: 500 | E55: 225 | F55: 225
A56: 103 | C56: 103 | E56: 103 | F56: 103
C57: 129
A59: =SUM(A9:A58) -> 4994.6 | B59: =SUM(B9:B58) -> 1436 | C59: =SUM(C9:C58) -> 2413 | D59: =SUM(D9:D58) -> 0 | E59: =SUM(E9:E58) -> 5882 | F59: =SUM(F9:F58) -> 4685
A62: =+A6-A59 -> #REF!
A211: week 1 expenditure | B211: Jan week 4 | C211: feb week 1 | D211: feb week 2 | E211: feb week 3 | F211: feb week 4
A212: daily round
A213: 1000 round | C213: 1000
A214: round table
A215: weekly 25 round | C215: 200 | D215: 200 | E215: 200 | F215: 200
A216: fsbs | C216: 300
A217: teamwork | C217: 300
A218: rentals | F218: 250
A219: salaries | C219: 350
A220: medical | C220: 115
A221: stock | B221: 120 | D221: 338.88889 | E221: =54+24 -> 78
A222: kudzai loan repayment | E222: =400+50 -> 450
A223: 49 cork road rentals | C223: 1100
A224: 49 cork road fittings | D224: 115 | E224: 40 | F224: 300
A225: chickens | B225: =70+35+34+34 -> 173 | C225: =70+35+13+11+34 -> 163 | D225: =34-7 -> 27
A226: education | C226: 50
A227: TOTAL | B227: =SUM(B212:B225) -> 293 | C227: =SUM(C212:C225) -> 3528 | D227: =SUM(D212:D225) -> 680.88889 | E227: =SUM(E212:E225) -> 768 | F227: =SUM(F212:F225) -> 750
I229: GERMANY/ TURKEY BUDGET
A230: income | B230: Jan | C230: Feb | D230: Mar | E230: Apr | F230: May | I230: German accomodation | K230: =60*3 -> 180
I231: german transport | K231: 50
A232: sales income | C232: 2100 | E232: =880+50 -> 930 | I232: food and entertainment | K232: 100
A233: savings | E233: 4800 | I233: turkey transport | K233: 20
A234: 1000 round | C234: 3000 | D234: 4000 | E234: -1000 | I234: turkey food and entertainment | K234: 30
I235: accomodation | K235: =6*50 -> 300
A236: ruwa roundtable | C236: 1200 | E236: -50
I237: extra bags emirates | K237: 500
A238: sharewealth | C238: 3000 | I238: upload to 32kg *3 | K238: 225
I239: airport
A240: sister sister | D240: 1200 | E240: -300
A241: 25 per day | B241: 600 | D241: 600 | E241: -400 | I241: stock | K241: 8300
A242: teamwork | D242: 900 | E242: -300
I243: kapura | K243: 300
A244: Viano Loan | C244: =500+200 -> 700 | D244: 370
A245: rentals | E245: -1350 | K245: =SUM(K230:K244) -> 10005
A246: salaries | E246: -450
A247: air ticcket | E247: -950 | G247: =+E240+E241+E242+E234 -> -2000
A248: stock purchase | E248: -5000 | G248: -870
A249: travel costs(emirates 5 bags xcess baggage airport) | E249: =-(500+525+840) -> -1865 | G249: =SUM(G247:G248) -> -2870
A250: house construction + solar | E250: =-386-270-600 -> -1256
I251: kapura | J251: total | K251: paid | L251: balance
A252: TOTAL | B252: =SUM(B231:B251) -> 600 | C252: =SUM(C231:C251) -> 10000 | D252: =SUM(D231:D251) -> 7070 | E252: =SUM(E231:E251) -> -7191 | F252: =SUM(F231:F251) -> 0 | I252: nesley | K252: 50 | L252: =+J252-K252 -> -50
I253: ideal | J253: 612 | L253: =+J253-K253 -> 612
I254: ariens | J254: 580 | K254: 100 | L254: =+J254-K254 -> 480
B255: PAULINE | C255: TATENDA SNR | D255: TATENDA JNR | I255: handbags | J255: 250 | K255: 50 | L255: =+J255-K255 -> 200
A256: SALARIES | B256: 175 | C256: 175 | D256: 90 | I256: nude | J256: 500 | L256: =+J256-K256 -> 500
A257: TRANSPORT ALL | B257: 60 | C257: 60 | D257: 60 | I257: TOTAL | J257: =SUM(J252:J256) -> 1942 | K257: =SUM(K252:K256) -> 200 | L257: =SUM(L252:L256) -> 1742
A258: COMMISSION
A259: TOTAL | B259: =SUM(B256:B258) -> 235 | C259: =SUM(C256:C258) -> 235 | D259: =SUM(D256:D258) -> 150
B262: MON | C262: TUE | D262: WED | E262: THUR | F262: FRI | G262: SAT | I262: DEBT
A263: TRAVEL PLAZA | B263: PAU | C263: PAU | D263: PAU | E263: T.S | F263: PAU | G263: PAU
A264: AVONDALE | B264: TS | C264: TS | D264: TS | E264: TJ | F264: TS | G264: TJ
A266: PAU | B266: PAU | C266: PAU | D266: PAU | E266: PAU | G266: PAU
A267: TATENDA SNR | B267: TS | C267: TS | D267: TS | E267: TS | F267: TS
A268: TATENDA JNR | C268: TJ | D268: TJ | E268: TJ | F268: TJ | G268: TJ
F270: date | G270: debit | H270: credit sale | I270: other credit
A271: DEBT SCHEDULE | F271: 44985
A272: sharewealth | B272: 3300 | C272: 3300 | F272: 44986 | G272: -350 | H272: =885-130 -> 755
A273: zvinoera | B273: 1500 | C273: 1500 | F273: 44987 | H273: 0
A274: viano | B274: 1070 | F274: 44988 | H274: =+'daily sales'!#REF! -> #REF!
A275: kudzai | B275: 1350 | F275: 44989 | H275: =+'daily sales'!#REF! -> #REF!
A276: ruwa roundtable | B276: 2225 | C276: 1800 | F276: 44990 | H276: 0
A277: obligations | F277: 44991 | G277: -30 | H277: =+'daily sales'!#REF! -> #REF!
A278: salaries | B278: 450 | F278: 44992 | H278: =+'daily sales'!#REF! -> #REF!
A279: rentals | B279: 1350 | F279: 44993 | H279: =+'daily sales'!#REF! -> #REF!
B280: =SUM(B272:B279) -> 11245 | F280: 44994 | H280: =+'daily sales'!#REF! -> #REF!
A281: income | F281: 44995 | H281: 0
A282: 1000 round | B282: 4000 | F282: 44996 | H282: =+'daily sales'!#REF! -> #REF!
A283: teamwork | B283: 1200 | F283: 44997 | H283: 0
...

Sheet o stock
A1: SHOP | B1: LABEL | C1: Q | D1: size | E1: Item | F1: purchase price / unit $ | G1: total purchase price | H1: total cost | I1: Indirect Cost / unit | J1: Total Unit Cost | K1: Multiplier | L1: recommended | M1: Actual Price | N1: SALE | O1: S/T DEC '23 | P1: status | Q1: date | R1: sales
A2: DRESS OUTFITS
E3: OUTFITS & SUITS
A4: femeny | B4: jf lefone | C4: 1 | E4: white dress & jacket | F4: 33 | G4: 5920.5 | H4: 13960 | I4: =+F4/G4*H4 -> 77.810996 | J4: =+F4+I4 -> 110.811 | K4: 0.3 | L4: =+J4*K4+J4 -> 144.05429 | M4: 150
B5: dancing queen | C5: 2 | D5: 48 | E5: silver & black 2 piece | F5: 45 | G5: 5920.5 | H5: 13960 | I5: =+F5/G5*H5 -> 106.1059 | J5: =+F5+I5 -> 151.1059 | K5: 0.3 | L5: =+J5*K5+J5 -> 196.43767 | M5: 100 | N5: 80 | P5: nyamakupi | Q5: 45351 | R5: =+N5*15000 -> 1200000
B6: dancing queen | C6: 3 | D6: 48 | E6: silver & black 2 piece | F6: 45 | G6: 5920.5 | H6: 13960 | I6: =+F6/G6*H6 -> 106.1059 | J6: =+F6+I6 -> 151.1059 | K6: 0.3 | L6: =+J6*K6+J6 -> 196.43767 | M6: 100
B7: hatunga | C7: 4 | D7: 38 | E7: gold 2 piece with front glitter | L7: =+J7*K7+J7 -> 0 | P7: from eastgate
B8: fascino | C8: 5 | D8: 44 | E8: fascino cream/gold 2pc | F8: 55 | G8: 5500 | H8: 11950 | I8: =+F8/G8*H8 -> 119.5 | K8: 0.3 | L8: =+J8*K8+J8 -> 0 | M8: 220
B9: mavellino | C9: 6 | D9: 42 | E9: striped blue dress suit | F9: 55 | G9: 5690 | H9: 9443 | I9: =+F9/G9*H9 -> 91.276801 | J9: =+F9+I9 -> 146.2768 | K9: 0.3 | M9: 180
B10: march 2019 stock | L10: =+J10*K10+J10 -> 0
B11: hatunga | C11: 7 | D11: 42 | E11: navy/pink 3 piece | F11: 50 | G11: 4794 | H11: 7939 | I11: =+F11/G11*H11 -> 82.801418 | J11: =+F11+I11 -> 132.80142 | K11: 0.3 | L11: =+J11*K11+J11 -> 172.64184 | M11: 200
B12: hatunga | C12: 8 | D12: 44 | E12: navy/pink 3 piece | F12: 50 | G12: 4794 | H12: 7939 | I12: =+F12/G12*H12 -> 82.801418 | J12: =+F12+I12 -> 132.80142 | K12: 0.3 | L12: =+J12*K12+J12 -> 172.64184 | M12: 200 | P12: cash returned
E13: FEB 2020 STOCK | L13: =+J13*K13+J13 -> 0
A14: NIDA | B14: lavous | C14: 9 | D14: 48 | E14: scotch & yellow 2 piece | F14: 19 | G14: 5690 | H14: 9443 | I14: =+F14/G14*H14 -> 31.531986 | J14: =+F14+I14 -> 50.531986 | K14: 0.3 | L14: =+J14*K14+J14 -> 65.691582 | M14: 100
B15: antonella | C15: 10 | D15: 44 | E15: black 2 piece knit | F15: 20 | G15: 5690 | H15: 9443 | I15: =+F15/G15*H15 -> 33.191564 | J15: =+F15+I15 -> 53.191564 | K15: 0.3 | L15: =+J15*K15+J15 -> 69.149033 | M15: 95
B16: antonella | C16: 11 | D16: 44 | E16: black 2 piece knit | F16: 20 | G16: 5690 | H16: 9443 | I16: =+F16/G16*H16 -> 33.191564 | J16: =+F16+I16 -> 53.191564 | K16: 0.3 | L16: =+J16*K16+J16 -> 69.149033 | M16: 95
B17: antonella | C17: 12 | D17: 46 | E17: black 2 piece knit | F17: 20 | G17: 5690 | H17: 9443 | I17: =+F17/G17*H17 -> 33.191564 | J17: =+F17+I17 -> 53.191564 | K17: 0.3 | L17: =+J17*K17+J17 -> 69.149033 | M17: 95
B18: antonella | C18: 13 | D18: 46 | E18: black 2 piece knit | F18: 20 | G18: 5690 | H18: 9443 | I18: =+F18/G18*H18 -> 33.191564 | J18: =+F18+I18 -> 53.191564 | K18: 0.3 | L18: =+J18*K18+J18 -> 69.149033 | M18: 95 | N18: 60 | P18: nyamakupi | Q18: 45351 | R18: =+N18*10000 -> 600000
E19: JUNE 2020 STOCK | L19: =+J19*K19+J19 -> 0
B20: sincere | C20: 14 | D20: 48 | E20: 2 piece denim dress | F20: 28 | G20: 283 | H20: =+G20+314 -> 597 | I20: =+F20/G20*H20 -> 59.067138 | J20: =+F20+I20 -> 87.067138 | K20: 0.3 | L20: =+J20*K20+J20 -> 113.18728 | M20: 100
E21: december 2020 stock | L21: =+J21*K21+J21 -> 0
B22: pinema | C22: 15 | D22: 42 | E22: white trouser set | F22: 28 | G22: 272 | H22: =+G22+50+16 -> 338 | I22: =+F22/G22*H22 -> 34.794118 | J22: =+F22+I22 -> 62.794118 | K22: 0.3 | L22: =+J22*K22+J22 -> 81.632353 | M22: 110
B23: pinema | C23: 16 | D23: 44 | E23: white trouser set | F23: 28 | G23: 272 | H23: =+G23+50+16 -> 338 | I23: =+F23/G23*H23 -> 34.794118 | J23: =+F23+I23 -> 62.794118 | K23: 0.3 | L23: =+J23*K23+J23 -> 81.632353 | M23: 110
B24: pinema | C24: 17 | D24: 46 | E24: white trouser set | F24: 28 | G24: 272 | H24: =+G24+50+16 -> 338 | I24: =+F24/G24*H24 -> 34.794118 | J24: =+F24+I24 -> 62.794118 | K24: 0.3 | L24: =+J24*K24+J24 -> 81.632353 | M24: 110
B25: pinema | C25: 18 | D25: 48 | E25: white trouser set | F25: 28 | G25: 272 | H25: =+G25+50+16 -> 338 | I25: =+F25/G25*H25 -> 34.794118 | J25: =+F25+I25 -> 62.794118 | K25: 0.3 | L25: =+J25*K25+J25 -> 81.632353 | M25: 110
E26: dec 2021 stock | L26: =+J26*K26+J26 -> 0
A27: ideal | B27: ceber | C27: 19 | D27: 42 | E27: cream dress w gold jacket | F27: 41 | G27: 6556 | H27: 9750 | I27: =+F27/G27*H27 -> 60.97468 | J27: =+F27+I27 -> 101.97468 | K27: 0.3 | L27: =+J27*K27+J27 -> 132.56708 | M27: 150
A28: ideal | B28: ceber | C28: 20 | D28: 44 | E28: cream dress w gold jacket | F28: 41 | G28: 6556 | H28: 9750 | I28: =+F28/G28*H28 -> 60.97468 | J28: =+F28+I28 -> 101.97468 | K28: 0.3 | L28: =+J28*K28+J28 -> 132.56708 | M28: 150
A29: ideal | B29: ceber | C29: 21 | D29: 48 | E29: cream dress w gold jacket | F29: 41 | G29: 6556 | H29: 9750 | I29: =+F29/G29*H29 -> 60.97468 | J29: =+F29+I29 -> 101.97468 | K29: 0.3 | L29: =+J29*K29+J29 -> 132.56708 | M29: 150
A30: ideal | B30: gicca | C30: 22 | D30: 50 | E30: cream dress w gold jacket | F30: 41 | G30: 6556 | H30: 9750 | I30: =+F30/G30*H30 -> 60.97468 | J30: =+F30+I30 -> 101.97468 | K30: 0.3 | L30: =+J30*K30+J30 -> 132.56708 | M30: 150
A31: ideal | B31: gicca | C31: 23 | D31: 54 | E31: cream dress w gold jacket | F31: 41 | G31: 6556 | H31: 9750 | I31: =+F31/G31*H31 -> 60.97468 | J31: =+F31+I31 -> 101.97468 | K31: 0.3 | L31: =+J31*K31+J31 -> 132.56708 | M31: 150
A32: ideal | B32: gicca | C32: 24 | D32: 56 | E32: cream dress w gold jacket | F32: 41 | G32: 6556 | H32: 9750 | I32: =+F32/G32*H32 -> 60.97468 | J32: =+F32+I32 -> 101.97468 | K32: 0.3 | L32: =+J32*K32+J32 -> 132.56708 | M32: 150
E33: NOV Turkey trip
B34: Nesly | C34: 25 | D34: 44 | E34: charcoal stripe skirt suit | F34: 55 | G34: 8267 | H34: 7400 | I34: =+F34/G34*H34 -> 49.231886 | J34: =+F34+I34 -> 104.23189 | K34: 0.3 | L34: =+J34*1.3 -> 135.50145 | M34: 150
B35: Nesly | C35: 26 | D35: 44 | E35: navy skirt suit | F35: 55 | G35: 8267 | H35: 7400 | I35: =+F35/G35*H35 -> 49.231886 | J35: =+F35+I35 -> 104.23189 | K35: 0.3 | L35: =+J35*1.3 -> 135.50145 | M35: 150
B36: Nesly | C36: 27 | D36: 52 | E36: navy skirt suit | F36: 55 | G36: 8267 | H36: 7400 | I36: =+F36/G36*H36 -> 49.231886 | J36: =+F36+I36 -> 104.23189 | K36: 0.3 | L36: =+J36*1.3 -> 135.50145 | M36: 150
B37: murray & co | C37: 28 | D37: 38 | E37: black skirt suit | F37: 60 | G37: 8267 | H37: 7400 | I37: =+F37/G37*H37 -> 53.707512 | J37: =+F37+I37 -> 113.70751 | K37: 0.3 | L37: =+J37*1.3 -> 147.81977 | M37: 80
B38: TEMEL CARGO 29 MAR '23
B39: NESLY | C39: 29 | D39: 40 | E39: black w blue pinstripe | F39: 50 | G39: =+(700+612+375)*1.5 -> 2530.5 | H39: 631 | I39: =+F39/G39*H39 -> 12.467892 | J39: =+F39+I39 -> 62.467892 | K39: 0.4 | L39: =+J39*1.3 -> 81.208259 | M39: 150
B40: NESLY | C40: 30 | E40: black w blue pinstripe | F40: 50 | G40: =+(700+612+375)*1.5 -> 2530.5 | H40: 631 | I40: =+F40/G40*H40 -> 12.467892 | J40: =+F40+I40 -> 62.467892 | K40: 0.4 | L40: =+J40*1.3 -> 81.208259 | M40: 150
B41: NESLY | C41: 31 | D41: 44 | E41: black skirt and jacket suit | F41: 50 | G41: =+(700+612+375)*1.5 -> 2530.5 | H41: 631 | I41: =+F41/G41*H41 -> 12.467892 | J41: =+F41+I41 -> 62.467892 | K41: 0.4 | L41: =+J41*1.3 -> 81.208259 | M41: 150 | P41: cash | Q41: 45408 | R41: =+M41*36000 -> 5400000
B42: NESLY | C42: 32 | D42: 46 | E42: black skirt and jacket suit | F42: 50 | G42: =+(700+612+375)*1.5 -> 2530.5 | H42: 631 | I42: =+F42/G42*H42 -> 12.467892 | J42: =+F42+I42 -> 62.467892 | K42: 0.4 | L42: =+J42*1.3 -> 81.208259 | M42: 125 | P42: rev mtisi | Q42: 45337 | R42: =+M42*10000 -> 1250000
B43: NESLY | C43: 33 | D43: 50 | E43: black skirt and jacket suit | F43: 50 | G43: =+(700+612+375)*1.5 -> 2530.5 | H43: 631 | I43: =+F43/G43*H43 -> 12.467892 | J43: =+F43+I43 -> 62.467892 | K43: 0.4 | L43: =+J43*1.3 -> 81.208259 | M43: 150
B44: NESLY | C44: 34 | D44: 46 | E44: black skirt and jacket suit | F44: 50 | G44: =+(700+612+375)*1.5 -> 2530.5 | H44: 631 | I44: =+F44/G44*H44 -> 12.467892 | J44: =+F44+I44 -> 62.467892 | K44: 0.4 | L44: =+J44*1.3 -> 81.208259 | M44: 150 | P44: cash | Q44: 45500
E45: TURKEY MAY 2023
A46: nesly | B46: nesly | C46: 35 | D46: 38 | E46: coffee scotch small size | F46: 55 | G46: 9682 | H46: 7766 | I46: =+F46/G46*H46 -> 44.115885 | J46: =+F46+I46 -> 99.115885 | K46: 0.4 | L46: =+J46*1.4 -> 138.76224 | M46: 150
A47: nesly | B47: nesly | C47: 36 | D47: 46 | E47: stripe trouser suit | F47: 55 | G47: 9682 | H47: 7766 | I47: =+F47/G47*H47 -> 44.115885 | J47: =+F47+I47 -> 99.115885 | K47: 0.4 | L47: =+J47*1.4 -> 138.76224 | M47: 150
A48: nesly | B48: nesly | C48: 37 | D48: 50 | E48: stripe trouser suit | F48: 55 | G48: 9682 | H48: 7766 | I48: =+F48/G48*H48 -> 44.115885 | J48: =+F48+I48 -> 99.115885 | K48: 0.4 | L48: =+J48*1.4 -> 138.76224 | M48: 150
B49: TURKEY MAY 2023 | E49: TROUSER SET
A50: tango | B50: misi Misia | C50: 38 | D50: 44 | E50: black trouser w black/white top | F50: 33 | G50: 9682 | H50: 7766 | I50: =+F50/G50*H50 -> 26.469531 | J50: =+F50+I50 -> 59.469531 | K50: 0.4 | L50: =+J50*1.4 -> 83.257344 | M50: 125
A51: tango | B51: misi Misia | C51: 39 | D51: 48 | E51: black trouser w black/white top | F51: 33 | G51: 9682 | H51: 7766 | I51: =+F51/G51*H51 -> 26.469531 | J51: =+F51+I51 -> 59.469531 | K51: 0.4 | L51: =+J51*1.4 -> 83.257344 | M51: 125 | P51: ivy sithole | Q51: 45435 | R51: =+M54*14.5 -> 1812.5
A52: moons | B52: moons | C52: 40 | D52: 40 | E52: blue trouser set w blue white blouse | F52: 40 | G52: 9682 | H52: 7766 | I52: =+F52/G52*H52 -> 32.08428 | J52: =+F52+I52 -> 72.08428 | K52: 0.4 | L52: =+J52*1.4 -> 100.91799 | M52: 125
A53: moons | B53: moons | C53: 41 | D53: 44 | E53: blue trouser set w blue white blouse | F53: 40 | G53: 9682 | H53: 7766 | I53: =+F53/G53*H53 -> 32.08428 | J53: =+F53+I53 -> 72.08428 | K53: 0.4 | L53: =+J53*1.4 -> 100.91799 | M53: 125
A54: moons | B54: moons | C54: 42 | D54: 46 | E54: blue trouser set w blue white blouse | F54: 40 | G54: 9682 | H54: 7766 | I54: =+F54/G54*H54 -> 32.08428 | J54: =+F54+I54 -> 72.08428 | K54: 0.4 | L54: =+J54*1.4 -> 100.91799 | M54: 125
A55: moons | B55: moons | C55: 43 | D55: 48 | E55: blue trouser set w blue white blouse | F55: 40 | G55: 9682 | H55: 7766 | I55: =+F55/G55*H55 -> 32.08428 | J55: =+F55+I55 -> 72.08428 | K55: 0.4 | L55: =+J55*1.4 -> 100.91799 | M55: 125
E56: JULY 2023 STOCK
A57: NESLEY | B57: NESLEY | C57: 44 | D57: 38 | E57: black 2 piece suit | F57: 50 | G57: 6066 | H57: 6015 | I57: =+F57/G57*H57 -> 49.579624 | J57: =+F57+I57 -> 99.579624 | K57: 0.4 | L57: =+J57*1.4 -> 139.41147 | M57: 150
A58: NESLEY | B58: NESLEY | C58: 45 | D58: 40 | E58: black 2 piece suit | F58: 50 | G58: 6066 | H58: 6015 | I58: =+F58/G58*H58 -> 49.579624 | J58: =+F58+I58 -> 99.579624 | K58: 0.4 | L58: =+J58*1.4 -> 139.41147 | M58: 150
A59: NESLEY | B59: NESLEY | C59: 46 | D59: 44 | E59: black 2 piece suit | F59: 50 | G59: 6066 | H59: 6015 | I59: =+F59/G59*H59 -> 49.579624 | J59: =+F59+I59 -> 99.579624 | K59: 0.4 | L59: =+J59*1.4 -> 139.41147 | M59: 150
A60: NESLEY | B60: NESLEY | C60: 47 | D60: 46 | E60: black 2 piece suit | F60: 50 | G60: 6066 | H60: 6015 | I60: =+F60/G60*H60 -> 49.579624 | J60: =+F60+I60 -> 99.579624 | K60: 0.4 | L60: =+J60*1.4 -> 139.41147 | M60: 150
B61: 45352
A63: NESLY | B63: NESLY | C63: 49 | D63: 42 | E63: coffee scotch jacket & coffee pleated skirt | F63: 55 | G63: =825+725*0.045 -> 857.625 | H63: 370 | I63: =+F63/G63*H63 -> 23.728319 | J63: =+I63+F63 -> 78.728319 | K63: 0.4 | L63: =+J63*1.4 -> 110.21965 | M63: 150
A64: NESLY | B64: NESLY | C64: 50 | D64: 44 | E64: coffee scotch jacket & coffee pleated skirt | F64: 55 | G64: =825+725*0.045 -> 857.625 | H64: 370 | I64: =+F64/G64*H64 -> 23.728319 | J64: =+I64+F64 -> 78.728319 | K64: 0.4 | L64: =+J64*1.4 -> 110.21965 | M64: 150 | P64: masika | Q64: 45491
A65: NESLY | B65: NESLY | C65: 51 | D65: 46 | E65: coffee scotch jacket & coffee pleated skirt | F65: 55 | G65: =825+725*0.045 -> 857.625 | H65: 370 | I65: =+F65/G65*H65 -> 23.728319 | J65: =+I65+F65 -> 78.728319 | K65: 0.4 | L65: =+J65*1.4 -> 110.21965 | M65: 145 | P65: cash | Q65: 45457 | R65: =+M65*14.5 -> 2102.5
A66: NESLY | B66: NESLY | C66: 52 | D66: 48 | E66: coffee scotch jacket & coffee pleated skirt | F66: 55 | G66: =825+725*0.045 -> 857.625 | H66: 370 | I66: =+F66/G66*H66 -> 23.728319 | J66: =+I66+F66 -> 78.728319 | K66: 0.4 | L66: =+J66*1.4 -> 110.21965 | M66: 150
A67: NESLY | B67: NESLY | C67: 53 | D67: 50 | E67: coffee scotch jacket & coffee pleated skirt | F67: 55 | G67: =825+725*0.045 -> 857.625 | H67: 370 | I67: =+F67/G67*H67 -> 23.728319 | J67: =+I67+F67 -> 78.728319 | K67: 0.4 | L67: =+J67*1.4 -> 110.21965 | M67: 150 | P67: cash mupfumi | Q67: 45432 | R67: =+M67*14.5 -> 2175
A68: NESLY | B68: NESLY | C68: 54 | D68: 38 | E68: navy scotch jacket & navy pleated skirt | F68: 55 | G68: =825+725*0.045 -> 857.625 | H68: 370 | I68: =+F68/G68*H68 -> 23.728319 | J68: =+I68+F68 -> 78.728319 | K68: 0.4 | L68: =+J68*1.4 -> 110.21965 | M68: 150
A69: NESLY | B69: NESLY | C69: 55 | D69: 40 | E69: navy scotch jacket & navy pleated skirt | F69: 55 | G69: =825+725*0.045 -> 857.625 | H69: 370 | I69: =+F69/G69*H69 -> 23.728319 | J69: =+I69+F69 -> 78.728319 | K69: 0.4 | L69: =+J69*1.4 -> 110.21965 | M69: 150
A70: NESLY | B70: NESLY | C70: 56 | D70: 42 | E70: navy scotch jacket & navy pleated skirt | F70: 55 | G70: =825+725*0.045 -> 857.625 | H70: 370 | I70: =+F70/G70*H70 -> 23.728319 | J70: =+I70+F70 -> 78.728319 | K70: 0.4 | L70: =+J70*1.4 -> 110.21965 | M70: 150
A71: NESLY | B71: NESLY | C71: 57 | D71: 44 | E71: navy scotch jacket & navy pleated skirt | F71: 55 | G71: =825+725*0.045 -> 857.625 | H71: 370 | I71: =+F71/G71*H71 -> 23.728319 | J71: =+I71+F71 -> 78.728319 | K71: 0.4 | L71: =+J71*1.4 -> 110.21965 | M71: 150 | P71: cash | Q71: 45408 | R71: =+M71*36000 -> 5400000
A72: NESLY | B72: NESLY | C72: 58 | D72: 46 | E72: navy scotch jacket & navy pleated skirt | F72: 55 | G72: =825+725*0.045 -> 857.625 | H72: 370 | I72: =+F72/G72*H72 -> 23.728319 | J72: =+I72+F72 -> 78.728319 | K72: 0.4 | L72: =+J72*1.4 -> 110.21965 | M72: 145 | P72: cash | Q72: 45457 | R72: =+M72*14.5 -> 2102.5
A73: NESLY | B73: NESLY | C73: 59 | D73: 38 | E73: navy scotch jacket w rounded collar & navy pleated skirt | F73: 55 | G73: =825+725*0.045 -> 857.625 | H73: 370 | I73: =+F73/G73*H73 -> 23.728319 | J73: =+I73+F73 -> 78.728319 | K73: 0.4 | L73: =+J73*1.4 -> 110.21965 | M73: 150 | P73: cash | Q73: 45496
A74: NESLY | B74: NESLY | C74: 60 | D74: 40 | E74: navy scotch jacket w rounded collar & navy pleated skirt | F74: 55 | G74: =825+725*0.045 -> 857.625 | H74: 370 | I74: =+F74/G74*H74 -> 23.728319 | J74: =+I74+F74 -> 78.728319 | K74: 0.4 | L74: =+J74*1.4 -> 110.21965 | M74: 150 | P74: cash | Q74: 45458 | R74: =+M74*14.5 -> 2175
A75: NESLY | B75: NESLY | C75: 61 | D75: 42 | E75: navy scotch jacket w rounded collar & navy pleated skirt | F75: 55 | G75: =825+725*0.045 -> 857.625 | H75: 370 | I75: =+F75/G75*H75 -> 23.728319 | J75: =+I75+F75 -> 78.728319 | K75: 0.4 | L75: =+J75*1.4 -> 110.21965 | M75: 150 | P75: layby chidanho | Q75: 45433 | R75: =+M75*14.5 -> 2175
A76: NESLY | B76: NESLY | C76: 62 | D76: 44 | E76: navy scotch jacket w rounded collar & navy pleated skirt | F76: 55 | G76: =825+725*0.045 -> 857.625 | H76: 370 | I76: =+F76/G76*H76 -> 23.728319 | J76: =+I76+F76 -> 78.728319 | K76: 0.4 | L76: =+J76*1.4 -> 110.21965 | M76: 150 | P76: cash mutimodyo | Q76: 45447 | R76: =+M76*14.5 -> 2175
A77: NESLY | B77: NESLY | C77: 63 | D77: 46 | E77: navy scotch jacket w rounded collar & navy pleated skirt | F77: 55 | G77: =825+725*0.045 -> 857.625 | H77: 370 | I77: =+F77/G77*H77 -> 23.728319 | J77: =+I77+F77 -> 78.728319 | K77: 0.4 | L77: =+J77*1.4 -> 110.21965 | M77: 150 | P77: cash, | Q77: 45455 | R77: =+M77*14.5 -> 2175
B78: 45413
A79: xmeric | B79: xmeric | D79: 42 | E79: brown scotch suit | F79: 42 | G79: 768 | H79: 515 | I79: =+F79/G79*H79 -> 28.164062 | J79: =+F79+I79 -> 70.164062 | L79: =+J79*1.4 -> 98.229687 | M79: 125
A80: xmeric | B80: xmeric | D80: 44 | E80: brown scotch suit | F80: 42 | G80: 768 | H80: 515 | I80: =+F80/G80*H80 -> 28.164062 | J80: =+F80+I80 -> 70.164062 | L80: =+J80*1.4 -> 98.229687 | M80: 115 | P80: cash mutimodyo | Q80: 45447 | R80: =+M80*14.5 -> 1667.5
A81: xmeric | B81: xmeric | D81: 46 | E81: brown scotch suit | F81: 42 | G81: 768 | H81: 515 | I81: =+F81/G81*H81 -> 28.164062 | J81: =+F81+I81 -> 70.164062 | L81: =+J81*1.4 -> 98.229687 | M81: 125
A82: xmeric | B82: xmeric | D82: 48 | E82: brown scotch suit | F82: 42 | G82: 768 | H82: 515 | I82: =+F82/G82*H82 -> 28.164062 | J82: =+F82+I82 -> 70.164062 | L82: =+J82*1.4 -> 98.229687 | M82: 125
A83: xmeric | B83: xmeric | D83: 42 | E83: maroon scotch suit | F83: 42 | G83: 768 | H83: 515 | I83: =+F83/G83*H83 -> 28.164062 | J83: =+F83+I83 -> 70.164062 | L83: =+J83*1.4 -> 98.229687 | M83: 125
A84: xmeric | B84: xmeric | D84: 44 | E84: maroon scotch suit | F84: 42 | G84: 768 | H84: 515 | I84: =+F84/G84*H84 -> 28.164062 | J84: =+F84+I84 -> 70.164062 | L84: =+J84*1.4 -> 98.229687 | M84: 125
A85: xmeric | B85: xmeric | D85: 46 | E85: maroon scotch suit | F85: 42 | G85: 768 | H85: 515 | I85: =+F85/G85*H85 -> 28.164062 | J85: =+F85+I85 -> 70.164062 | L85: =+J85*1.4 -> 98.229687 | M85: 125
A86: xmeric | B86: xmeric | D86: 48 | E86: maroon scotch suit | F86: 42 | G86: 768 | H86: 515 | I86: =+F86/G86*H86 -> 28.164062 | J86: =+F86+I86 -> 70.164062 | L86: =+J86*1.4 -> 98.229687 | M86: 125
A87: xmeric | B87: xmeric | D87: 50 | E87: black suit | F87: 42 | G87: 768 | H87: 515 | I87: =+F87/G87*H87 -> 28.164062 | J87: =+F87+I87 -> 70.164062 | L87: =+J87*1.4 -> 98.229687 | M87: 125
A88: xmeric | B88: xmeric | D88: 52 | E88: black suit | F88: 42 | G88: 768 | H88: 515 | I88: =+F88/G88*H88 -> 28.164062 | J88: =+F88+I88 -> 70.164062 | L88: =+J88*1.4 -> 98.229687 | M88: 125
A89: xmeric | B89: xmeric | D89: 54 | E89: black suit | F89: 42 | G89: 768 | H89: 515 | I89: =+F89/G89*H89 -> 28.164062 | J89: =+F89+I89 -> 70.164062 | L89: =+J89*1.4 -> 98.229687 | M89: 125
A90: xmeric | B90: xmeric | D90: 56 | E90: black suit | F90: 42 | G90: 768 | H90: 515 | I90: =+F90/G90*H90 -> 28.164062 | J90: =+F90+I90 -> 70.164062 | L90: =+J90*1.4 -> 98.229687 | M90: 125
A92: another | B92: no name | E92: wooled 2 piece skirt black /cream | F92: 15 | L92: 45 | M92: 45 | P92: tete chipo | Q92: 45447 | R92: =+M92*14.5 -> 652.5
A93: another | B93: no name | E93: wooled 2 piece skirt | F93: 15 | L93: 45 | M93: 45 | P93: cash | Q93: 45451 | R93: =+M93*14.5 -> 652.5
A94: another | B94: no name | E94: wooled 2 piece trouser cream/black | F94: 15 | L94: 45 | M94: 45 | P94: layby nobuhle | Q94: 45448 | R94: =+M94*14.5 -> 652.5
A95: another | B95: no name | E95: wooled 2 piece skirt | F95: 15 | L95: 45 | M95: 45 | P95: cash | Q95: 45451 | R95: =+M95*14.5 -> 652.5
A96: another | B96: no name | E96: wooled 2 piece trouser | F96: 15 | L96: 45 | M96: 45 | P96: layby .Tarirai | Q96: 45451 | R96: =+M96*14.5 -> 652.5
A97: another | B97: no name | E97: wooled 2 piece trouser | F97: 15 | L97: 45 | M97: 45 | P97: cash | Q97: 45467
A98: another | B98: no name | E98: wooled 2 piece trouser | F98: 15 | L98: 45 | M98: 45
A99: woolen | C99: 48 | E99: beige trouser set | F99: 15 | G99: 4192 | H99: 3417 | I99: =+H99/G99*F99 -> 12.226861 | J99: =+F99+I99 -> 27.226861 | K99: 1.4 | L99: =+J99*K99 -> 38.117605 | M99: 45
B100: TOTAL OUTFITS | F100: =SUM(F4:F32) -> 818 | L100: =+J100*K100+J100 -> 0 | M100: =SUM(M4:M32) -> 3070
A101: 2022 | B101: 64 | C101: -28 | D101: =+B101+C101 -> 36
A102: 2023 | B102: 95 | C102: -48 | D102: =+B102+C102 -> 47
...

Sheet layby clients
A1: to | B1: date of purchase | C1: inst dates | D1: name | E1: inv no | F1: invoice total | G1: deposit | H1: inst | J1: layby bal
B3: 45220 | D3: dr zezai | F3: 125 | H3: -50
C4: 45231 | F4: 35 | H4: -75
H5: -10
C6: 45314 | H6: -25
F7: =SUM(F3:F5) -> 160 | H7: =SUM(H3:H6) -> -160 | J7: =+F7+H7 -> 0
B10: 45229 | D10: mrs komichi | F10: =35+35 -> 70 | H10: -25
C11: 45280 | H11: -20
C12: 45330 | H12: -25
F13: =SUM(F10:F11) -> 70 | H13: =SUM(H10:H12) -> -70 | J13: =+F13+H13 -> 0
B16: 45243 | D16: mai nyasha | F16: 55 | H16: -20
C17: 45252 | H17: -15
B18: 45290 | F18: 55 | H18: -20
C19: 45293 | H19: -20
C20: 45293 | H20: -20
C21: 45295 | H21: -15
C22: 45295 | F22: 55 | H22: -15
C23: 45306 | H23: -20
C24: 45313 | H24: -10
C25: 45321 | H25: -10
F26: =SUM(F16:F25) -> 165 | G26: =SUM(G16:G25) -> 0 | H26: =SUM(H16:H25) -> -165 | J26: =+F26+H26 -> 0
B29: 45273 | D29: mai poly | F29: 55 | H29: -25 | L29: 787654076
C30: 45275 | H30: -30
B31: 45278 | F31: 70 | H31: -15
C32: 45313 | H32: -55
F34: =SUM(F29:F31) -> 125 | H34: =SUM(H29:H32) -> -125 | J34: =+F34+H34 -> 0
B37: 45281 | D37: ruth tsopotsa | F37: 420 | H37: -300
D38: returned in stock | H38: -105
H39: -15
F40: =SUM(F37:F39) -> 420 | H40: =SUM(H37:H39) -> -420 | J40: =+F40+H40 -> 0
B43: 45294 | D43: chikwanha | F43: 200 | H43: -80
C44: 45318 | H44: -90
C45: 45338 | H45: -30
F46: =SUM(F43:F44) -> 200 | H46: =SUM(H43:H45) -> -200 | J46: =+F46+H46 -> 0
B49: 45308 | D49: nyadzi | F49: 25 | H49: -10
C50: 45322 | H50: -10
F51: =SUM(F49:F50) -> 25 | H51: =SUM(H49:H50) -> -20 | J51: =+F51+H51 -> 5
B53: 45309 | D53: mrs mhonda | F53: 150 | H53: -25
C54: 22 ap | H54: -125
F55: =SUM(F53:F54) -> 150 | H55: =SUM(H53:H54) -> -150 | J55: =+F55+H55 -> 0
B57: 45313 | D57: nyereyemhuka | F57: 125 | H57: -65
C58: 45329 | H58: -60
F59: =SUM(F57:F58) -> 125 | H59: =SUM(H57:H58) -> -125 | J59: =+F59+H59 -> 0
B61: 45314 | D61: sakupwanya | F61: 150 | H61: -100
F62: 125 | I62: muti
F63: 125 | H63: -100
C64: 45365 | H64: -135
C65: 45394 | H65: -65
F66: =SUM(F61:F63) -> 400 | H66: =SUM(H61:H65) -> -400 | J66: =+F66+H66 -> 0
B68: 45313 | D68: Dennis restaurant | F68: 55 | H68: -20
D69: RETURNED
F70: =SUM(F68:F69) -> 55 | H70: =SUM(H68:H69) -> -20 | J70: =+F70+H70 -> 35
B72: 45320 | D72: chirinda | F72: 55 | H72: -30
C73: 45351 | H73: -25
F74: =SUM(F72:F73) -> 55 | H74: =SUM(H72:H73) -> -55 | J74: =+H74+F74 -> 0
B76: 45330 | D76: Ushe | F76: =90+45 -> 135 | H76: -100
F77: -90
F78: =SUM(F76:F77) -> 45 | H78: =SUM(H76:H77) -> -100 | J78: =+F78+H78 -> -55
B80: 45332 | D80: Nyereyemhuka | F80: 110 | H80: -60
C81: 45357 | H81: -50
F82: =SUM(F80:F81) -> 110 | H82: =SUM(H80:H81) -> -110 | J82: =+F82+H82 -> 0
B84: 45332 | D84: chidzenga | F84: 125 | H84: -40
C85: 45349 | F85: 210 | H85: -130
C86: 45384 | H86: -65
C87: 45458 | H87: -100
F88: =SUM(F84:F85) -> 335 | H88: =SUM(H84:H87) -> -335 | J88: =+F88+H88 -> 0
B90: 45337 | D90: mai chido | F90: 55 | H90: -20
C91: 45349 | H91: -35
F92: =SUM(F90:F91) -> 55 | H92: =SUM(H90:H91) -> -55
B94: 45339 | D94: sigauke | F94: 95 | H94: -30
C95: 45349 | H95: -40
C96: 45390 | H96: -25
F97: =SUM(F94:F96) -> 95 | H97: =SUM(H94:H96) -> -95 | J97: =+F97+H97 -> 0
B99: 45364 | D99: kanganwai | F99: 200 | H99: -100
B100: 45366 | H100: -100
F101: =SUM(F99:F100) -> 200 | H101: =SUM(H99:H100) -> -200 | J101: =+F101+H101 -> 0
C103: 45320 | D103: mai simba phone shop | F103: 125 | H103: -20
C104: 45352 | H104: -20
C105: 45358 | H105: -20
C106: 45366 | H106: -20
C107: 45374 | H107: -20
C108: 45378 | H108: -20
F109: =SUM(F103:F108) -> 125 | H109: =SUM(H103:H108) -> -120 | J109: =+F109+H109 -> 5
B111: 45356 | D111: murwira item botique | F111: 30 | H111: -10
B112: 45362 | H112: -10
B113: 45366 | H113: -10
F114: =SUM(F111:F113) -> 30 | G114: =SUM(G111:G113) -> 0 | H114: =SUM(H111:H113) -> -30
B116: 45377 | D116: Dr Zezai | F116: 90 | H116: -40
C117: 45394 | F117: 110 | H117: =-50-20 -> -70
C118: 45502 | H118: -90
F119: =SUM(F116:F118) -> 200 | H119: =SUM(H116:H118) -> -200 | J119: =+F119+H119 -> 0
B121: 45384 | D121: bhomani | F121: 150 | H121: -100
C122: 45385 | F122: 110 | H122: -100
C123: 45386 | H123: -60
F124: =SUM(F121:F123) -> 260 | H124: =SUM(H121:H123) -> -260 | J124: =+F124+H124 -> 0
B126: 45384 | D126: manhambara | F126: =125+150 -> 275 | H126: -90
C127: 45390 | H127: -100
C128: 45415 | H128: -85
F129: =SUM(F126:F128) -> 275 | H129: =SUM(H126:H128) -> -275 | J129: =+F129+H129 -> 0
B131: 45390 | D131: caroline | F131: 260 | H131: -100
...

Sheet credit clients 
A1: to | C1: date of purchase | D1: inv no. | E1: amount | F1: paid to date | I1: USD Bal 2022
B3: Winnie | E3: 215
A4: 2 | B4: Nyasha Mashingaidz
A5: 7 | B5: majasi | C5: 43088 | E5: =150+60+150+65 -> 425 | F5: =+E5-#REF! -> #REF! | G5: =+F5 -> #REF!
B7: mai chitindi | C7: 43571 | E7: 125
C8: 43597
E9: =SUM(E7:E8) -> 125 | I9: =+E9+#REF! -> #REF!
B11: mai jordan | E11: 65 | F11: -30
C12: 43550 | E12: 65 | F12: -40
C13: 43612 | F13: -50
C14: 43613 | E14: 200
C15: 43847 | F15: -50
E16: =SUM(E11:E15) -> 330 | F16: =SUM(F11:F15) -> -170 | I16: =+E16+F16 -> 160
B18: pauline gatsi | C18: 43546 | D18: 431 | E18: 200
C19: 43551
C20: 43551 | E20: =125+180 -> 305
E21: 175
C22: 43553
C23: 43593 | E23: 65
C24: 43602 | E24: =45+85 -> 130
C25: 43607 | E25: =70+65 -> 135
C26: 43608 | E26: 65
C27: 43616
C28: 43616 | E28: 415
C29: 43630 | E29: 90
C30: 43664
C31: 43664 | E31: 200
C32: 43679 | E32: 300
C33: 43694
C34: 43694 | E34: 100
C35: 43732 | E35: 215
C36: 43748
C37: 43748 | E37: 125
C38: 44169 | E38: 150
C39: 43820 | E39: 120
C40: 43859
C41: 43861 | E41: 280
C42: 43865 | E42: 75
C43: 43867 | E43: 55
C44: 43874 | E44: 50
C45: 43873 | E45: 125
B46: pauline Gatsi | C46: 43904
E47: =SUM(E18:E46) -> 3375 | K47: 745
B49: pauline Gatsi | E49: 745
C50: 43977 | G50: -300
C51: 43977 | E51: =80+45 -> 125
E52: =SUM(E49:E51) -> 870 | G52: =SUM(G49:G51) -> -300 | I52: =+E52+G52 -> 570
B53: Pauline Gatsi | E53: 570
B56: mavis | C56: 43698 | D56: 550 | E56: 65 | G56: 0
C57: 43732 | E57: 235
C58: 43733 | G58: -100
C59: 43733 | E59: 280
C60: 43742 | G60: -100
C61: 43742 | E61: =125+65 -> 190
C62: 43798 | E62: 68
C63: 43798 | E63: 65
C64: 44170 | E64: =125+150 -> 275
C65: 43820 | D65: 642 | E65: 115
C66: 43900 | G66: -400
G67: -65
C68: 43973 | G68: -200
E71: =SUM(E56:E68) -> 1293 | F71: =SUM(F56:F60) -> 0 | G71: =SUM(G56:G68) -> -865 | I71: =+E71+G71 -> 428
B73: bonnie musara | C73: 43907 | E73: 100
C74: 43964 | G74: -100
C75: 43964 | E75: 90 | G75: -50
C76: 43978 | E76: =125+125+90 -> 340
E79: =SUM(E73:E78) -> 530 | G79: =SUM(G74:G78) -> -150 | I79: =+E79+G79 -> 380
B83: 43770
A85: 11 | B85: Tatenda | C85: 43789 | D85: 401 | E85: 25
C86: 43473 | E86: 25
C87: 43495 | E87: =-(50/3.4) -> -14.705882
C88: 43552 | E88: =-50/3.4 -> -14.705882
C89: 43567 | E89: =65*0.75 -> 48.75
C90: 43619 | E90: -10
C91: 43679 | E91: -10
C92: 43680 | E92: 10
C93: 43739 | E93: -5
C94: 43801 | E94: -5
C95: 43812 | E95: =125*0.75 -> 93.75
C96: 44258 | E96: 60
C97: 44348 | E97: -8
C98: 44382 | E98: -10
C99: 44509 | E99: 25
C100: 44531 | E100: -10
C101: 10 dc | E101: -10
C102: 44594 | E102: -10
C103: 44621 | E103: -10
C104: 44650 | E104: -10
C105: 44693 | E105: 70
C106: 44713 | E106: -10
C107: 44743 | E107: -10
C108: 44838 | E108: -14
C109: 44872 | E109: -15
C110: 45238 | E110: 15
C111: 44919 | E111: -20
C112: 44986 | E112: -10
C113: 45019 | E113: -10
... C117: 45281 | E117: -20
E119: =SUM(E85:E117) -> 157.08824 | I119: =+E119 -> 157.08824
A121: 13 | B121: pauline | C121: 43473 | D121: 404 | E121: 25
...

Sheet daily sales
A1: date | B1: USD SALE | C1: PRICE | D1: item description | E1: DISC/OVER | F1: DEBIT CARD | G1: ecocash/ zipit | H1: layby | J1: layby deposit DEBIT | K1: layby inst/ final pmnt CASH | L1: layby inst/ final pmnt DEBIT | M1: credit sale | N1: credit sale payment CASH | O1: credit sale payment DEBIT | P1: disc | Q1: consignment comm | R1: total cash daily received | S1: total daily sales | T1: total debit received
D2: JANUARY
A5: 44928 | B5: 25 | D5: altin yak maroon tennis sale 37
B6: 20 | D6: layby inst Sarah
B7: =SUM(B5:B6) -> 45
A9: 44929 | B9: 190 | D9: elisa star blue flowery chiffon maxi 42 | E9: -10
B10: 80 | C10: 200 | D10: layby mrs chikwanha elisa star pink flowery maxi 44
B11: =SUM(B9:B10) -> 270 | E11: =SUM(E9:E10) -> -10
A13: 44930 | B13: 35 | D13: miss rose green satin top 50
B14: 35 | D14: miss rose black satin top 50
B15: 70 | D15: modafly black dres w polka dot bottom 46
B16: 40 | D16: lasiea navy skirt w bottom frill sale
B17: 72 | D17: cr inst handina
B18: =SUM(B13:B17) -> 252
A20: 44931 | B20: 15 | D20: layby inst sara
B21: 15 | C21: 55 | D21: layby sara pardussi navy jacket sale 48
D22: moda fly - black dress w flared polka dot bottonm 44 | E22: transfer bank
B23: 50 | D23: kifayette blue top w ruffled neck54 mudirira | E23: -5
B24: 125 | D24: cr inst zanele
B26: =SUM(B20:B25) -> 205 | E26: =SUM(E23:E25) -> -5
A28: 45297 | B28: 180 | D28: ixora mint green chiffon gown 58
B29: 35 | D29: layby inst mrs chibwe | E29: account already deleted
B30: =SUM(B28:B29) -> 215
A32: 45298 | D32: returned in stock ruth tsopotsa - dissa beige/black 44
A34: 45300 | B34: 40 | D34: haza scotch jacket w zip design44
D35: alevva denim / satin maxi dress 52
D36: platin pink dress 44
D37: cr purchase raviro
C38: 45 | D38: scosta light blue shirt 44
C39: 55 | D39: la gazelle black trousers w belt 46
B40: =SUM(B34:B39) -> 40
A42: 45301 | B42: 150 | D42: nude beige max dress 44
B43: 15 | D43: layby instalment ruth tsopotsa
B44: =SUM(B42:B43) -> 165
A46: 45302 | B46: 125 | D46: firmas beige dress 44
B47: 55 | D47: luani orange casual dress w front design sale
B48: =SUM(B46:B47) -> 180
A50: 45303 | B50: 5 | D50: bayker panty black 6
A52: 45306 | B52: 20 | D52: layby inst Sarah
B53: 110 | D53: cr inst lilian
B54: =SUM(B52:B53) -> 130
A56: 45307 | B56: 25 | D56: gold shawl
B57: 200 | D57: cr inst matsika
B58: =SUM(B56:B57) -> 225
A60: 45309 | B60: 10 | C60: 25 | D60: layby nyadzi collectables - versace red tracksuit 3xl
B61: 65 | D61: vende black dress w black/white neck 54
B62: 50 | D62: miss rose green satin top 46
B63: 75 | D63: elegant line green/white shirt dress 46
B64: 25 | C64: 150 | D64: layby mrs mhonda - nude black/gold dress 48
B65: 10 | D65: x2 bayker panty 5 black & colour
B66: 25 | D66: brown wallet
B67: =SUM(B60:B66) -> 260
A69: 45310 | B69: 120 | D69: credit inst mai rev makuwerere
B70: 40 | D70: 8 bayker panties black 5
B71: 90 | D71: 18 bayker panties size 4
B73: =SUM(B69:B72) -> 250
A75: 45311 | B75: 45 | D75: scosta ladies shirt 54 yellow stripe old stock
B76: 60 | D76: cr inst mutanho
B77: =SUM(B75:B76) -> 105
A79: 45313 | B79: 65 | C79: 125 | D79: layby nyereyemhuka - beyzaz blue/white dress 38
B80: 55 | D80: layby inst mai poly
B81: 45 | D81: hember beige bandage skirt 38
B82: 20 | C82: 55 | D82: layby denis - big number black heed sandals 41 | E82: returned
B83: =SUM(B79:B82) -> 185
A85: 45314 | B85: 10 | D85: layby inst sarah
B86: 100 | D86: layby mrs sakupwanya
C87: 150 | D87: nude pink maxi dress - mai muti
C88: 125 | D88: jupiter green pleated dress w gold design 54
C89: 125 | D89: love me navy/white w navy hem 50
B90: 60 | D90: cr inst mrs mawango
C91: 35 | D91: w
B92: 120 | D92: miss glamour blue chiffon step dress w pleated sleeves | E92: -5
B93: 100 | D93: layby inst mrs sakupwanya
B94: =SUM(B85:B93) -> 390 | E94: =SUM(E92:E93) -> -5
A96: 45315 | B96: 25 | D96: layby inst dr zezai
B97: 10 | D97: x2 bayker panties beige & black size 6
B98: 10 | D98: atik black tights xxl
B99: =SUM(B96:B98) -> 45
D101: cr pur tete chipo
C102: 65 | D102: oreya army green multi colour 2pc
C103: 55 | D103: samsara orange multi colour 2pc | E103: avondale stocksheet
C104: 35 | D104: oreya mustard top w front design 2xl
A107: 45318 | B107: 20 | D107: cr inst sandra stanbic
B108: 90 | D108: layby inst chikwanha
B109: 35 | D109: royal blue clutch bag
B110: 35 | D110: gold embroidery clutch
B111: 35 | D111: pink clutch
B112: 115 | D112: black rose black/white 2 piece 44 | E112: -10
D113: sales loss | E113: -10
B114: =SUM(B107:B112) -> 330 | E114: =SUM(E112:E113) -> -20
A116: 45320 | B116: 10 | D116: oreya grey t shirt
B117: 30 | D117: layby Chirinda
C118: 45 | D118: hember black bandage skirt 58
C119: 10 | D119: oreya long sleeve t shirt green xxl
B120: =SUM(B116:B119) -> 40
A122: 45321 | B122: 10 | D122: layby inst sarah
B123: 25 | D123: serda red/white sandals 39
B124: 25 | D124: atik pink night dress xl
B125: =SUM(B122:B124) -> 60
A127: 45322 | B127: 10 | D127: layby inst nyadzi
...

Sheet sales analysis
A1: to
C2: INITIAL ESTABLISHMENT | D2: GROWTH | E2: NORMAL | F2: NORMAL | G2: COVID | H2: COVID/EASTGATE | I2: COVID | J2: RECOVERY | K2: NORMAL/ AVONDALE/CAR | L2: CAR/baby shop/ RECOVERY
B3: month | C3: year 1 (sept-dec) 2015 | D3: year 2 ( 2016) | E3: year 3 ( 2017) | F3: year 4 (2018) | G3: year 5 (2019) | H3: year 6 2020 | I3: year 7 2021 | J3: year 8 2022 | K3: year 9 2023 | L3: yr 10 2024
B4: jan | D4: 3811 | E4: 5584 | F4: 8183 | G4: 2814 | H4: 4180 | I4: 1485 | J4: 6068 | K4: 4140 | L4: =+'daily sales'!B139 -> 3230
B5: feb | D5: 4126 | E5: 5317 | F5: 5000 | G5: 2883 | H5: 3413 | I5: 1570 | J5: 5403 | K5: 6376 | L5: =+'daily sales'!B264 -> 3380
B6: mar | D6: 5742 | E6: 6635 | F6: 6500 | G6: 6262 | H6: 6532 | I6: 6010 | J6: 6778 | K6: 8031 | L6: =+'daily sales'!B415 -> 5258
B7: apr | D7: 12651 | E7: 7539 | F7: 7200 | G7: 2162 | H7: 128 | I7: 4066 | J7: 8490 | K7: 11232 | L7: =+'daily sales'!B610 -> 7090
B8: may | D8: 5651 | E8: 6359 | F8: 9000 | G8: 6517 | H8: 3594 | I8: 6722 | J8: 8879 | K8: 10926 | L8: =+'daily sales'!B801 -> 7471
B9: jun | D9: 8161 | E9: 11905 | F9: 10000 | G9: 1498 | H9: 3961 | I9: 7798 | J9: 9362 | K9: 7742 | L9: =+'daily sales'!B1022 -> 8907
B10: jul | D10: 6484 | E10: 6736 | F10: 8000 | G10: 6873 | H10: 5060 | I10: 4364 | J10: 6653 | K10: 9525 | L10: =+'daily sales'!B1164 -> 6286
B11: aug | D11: 8230 | E11: 10761 | F11: 7000 | G11: 5505 | H11: 3150 | I11: 6270 | J11: 8335 | K11: 10015
B12: sept | C12: 6540 | D12: 11580 | E12: 6736 | F12: 12000 | G12: 6114 | H12: 5083 | I12: 8932 | J12: 6658 | K12: 8403
B13: oct | C13: 11157 | D13: 10088 | E13: 18642.6 | F13: 15000 | G13: 6691 | H13: 3875 | I13: 6199 | J13: 9675 | K13: 7623
B14: nov | C14: 6993 | D14: 6191 | E14: 9327 | F14: 10000 | G14: 6841 | H14: 4706 | I14: 7739 | J14: 6915 | K14: 8747
B15: dec | C15: 9405 | D15: 8897 | E15: 8279 | F15: 8000 | G15: 7148 | H15: 6947 | I15: 11255 | J15: 8645 | K15: 13002
B16: total | C16: =SUM(C4:C15) -> 34095 | D16: =SUM(D4:D15) -> 91612 | E16: =SUM(E4:E15) -> 103820.6 | F16: =SUM(F4:F15) -> 105883 | G16: =SUM(G4:G15) -> 61308 | H16: =SUM(H4:H15) -> 50629 | I16: =SUM(I4:I15) -> 72410 | J16: =SUM(J4:J15) -> 91861 | ... L16: =SUM(L4:L15) -> 41622
B18: av monthly | C18: =+C16/4 -> 8523.75 | D18: =+D16/12 -> 7634.3333 | E18: =+E16/12 -> 8651.7167 | F18: =+F16/12 -> 8823.5833 | G18: =+G16/12 -> 5109 | H18: =+H16/12 -> 4219.0833 | I18: =+I16/12 -> 6034.1667 | J18: =+J16/12 -> 7655.0833 | K18: =+K16/12 -> 8813.5 | L18: =+L16/12 -> 3468.5
B20: quarterly analysis
B21: 1st | D21: =+D4+D5+D6 -> 13679 | E21: =+E4+E5+E6 -> 17536 | F21: =+F4+F5+F6 -> 19683 | G21: =+G4+G5+G6 -> 11959 | H21: =+H4+H5+H6 -> 14125 | I21: =+I4+I5+I6 -> 9065 | J21: =+J4+J5+J6 -> 18249 | K21: =+K4+K5+K6 -> 18547 | L21: =+L4+L5+L6 -> 11868
B22: 2nd | D22: =+D7+D8+D9 -> 26463 | E22: =+E7+E8+E9 -> 25803 | F22: =+F7+F8+F9 -> 26200 | G22: =+G7+G8+G9 -> 10177 | H22: =+H7+H8+H9 -> 7683 | I22: =+I7+I8+I9 -> 18586 | J22: =+J7+J8+J9 -> 26731 | K22: =+K7+K8+K9 -> 29900 | L22: =+L7+L8+L9 -> 23468
B23: 3rd | D23: =+D10+D11+D12 -> 26294 | E23: =+E10+E11+E12 -> 24233 | F23: =+F10+F11+F12 -> 27000 | G23: =+G10+G11+G12 -> 18492 | H23: =+H10+H11+H12 -> 13293 | I23: =+I10+I11+I12 -> 19566 | J23: =+J10+J11+J12 -> 21646 | K23: =+K10+K11+K12 -> 27943 | L23: =+L10+L11+L12 -> 6286
B24: 4th | D24: =+D13+D14+D15 -> 25176 | E24: =+E13+E14+E15 -> 36248.6 | F24: =+F13+F14+F15 -> 33000 | G24: =+G13+G14+G15 -> 20680 | H24: =+H13+H14+H15 -> 15528 | I24: =+I13+I14+I15 -> 25193 | J24: =+J13+J14+J15 -> 25235 | K24: =+K13+K14+K15 -> 29372 | L24: =+L13+L14+L15 -> 0
D26: =SUM(D21:D25) -> 91612 | E26: =SUM(E21:E25) -> 103820.6 | F26: =SUM(F21:F25) -> 105883 | G26: =SUM(G21:G25) -> 61308 | H26: =SUM(H21:H25) -> 50629 | I26: =SUM(I21:I25) -> 72410 | J26: =SUM(J21:J25) -> 91861 | K26: =SUM(K21:K25) -> 105762 | L26: =SUM(L21:L25) -> 41622
B28: average quarterly | D28: =+D26/4 -> 22903 | E28: =+E26/4 -> 25955.15 | F28: =+F26/4 -> 26470.75 | G28: =+G26/4 -> 15327 | H28: =+H26/4 -> 12657.25 | I28: =+I26/4 -> 18102.5 | J28: =+J26/4 -> 22965.25 | K28: =+K26/4 -> 26440.5 | L28: =+L26/4 -> 10405.5
C32: end november | D32: jan | E32: feb | F32: march | G32: apr | H32: may | I32: june | J32: july | K32: aug | L32: sept
C33: sales | D33: =3230+1300 -> 4530
C34: suzuki | H34: =6000+1000 -> 7000 | I34: 1650 | J34: 350
C35: travel | E35: 1100 | F35: 6000
C36: roundtable | D36: 70 | E36: 70 | F36: 300 | H36: 1300 | I36: 1700
C37: 1000 round | D37: 1000 | E37: 1000 | F37: 1000 | H37: 1000 | I37: 1000
C38: teamwork | D38: 300 | F38: 300 | G38: 300 | H38: 300 | I38: 300
C39: fsbs | D39: 300 | E39: 80 | H39: 300 | I39: 300
C40: baby shop good will | D40: 1000 | E40: 1000
C41: baby shop original stock pur | D41: 780 | F41: 500 | G41: 600
C42: sharewealth | D42: 1000 | E42: 980 | G42: 480 | H42: 480 | I42: 480
C43: rentals EB | D43: 250 | E43: 250 | F43: 250 | G43: 250 | H43: 250 | I43: 250
C44: rentals collectibles | D44: 260 | E44: 260 | F44: 260 | G44: 260 | H44: 260 | I44: 260
C45: simukai
C46: salary Pau | D46: 175 | E46: 175 | F46: 175 | G46: 175 | H46: 175 | I46: 175
C47: salary tatenda | D47: 175 | E47: 175 | F47: 175 | G47: 175 | H47: 175 | I47: 175
C48: salary Nyadzi | D48: 150 | E48: 150 | F48: 150 | G48: 150 | H48: 150 | I48: 150
B49: =+(1964+2400)/18.5-65 -> 170.89189 | C49: temba | H49: 400
C50: shop licence | D50: 300 | I50: 600
C51: stock purchase | F51: =848*1.045 -> 886.16 | G51: =725*1.045+1035*1.045 -> 1839.2 | H51: =628+520+300+74+380+300+450+150 -> 2802 | J51: =360+500+400 -> 1260
C52: cargo | F52: 934 | G52: =242+364+419 -> 1025 | H52: =535+515 -> 1050 | I52: =403+496 -> 899
D53: =SUM(D34:D50) -> 5760 | E53: =SUM(E34:E50) -> 5240 | F53: =SUM(F34:F50) -> 9110 | G53: =SUM(G34:G50) -> 2390 | H53: =SUM(H34:H52) -> 15642 | I53: =SUM(I34:I50) -> 7040
C54: net inflow/outflow | D54: =+D33-D53 -> -1230
C57: loans stock debts | F57: march | G57: apr | H57: may | I57: june | J57: jun | K57: jul | L57: july | M57: aug
B58: 1000 | C58: sharewealth | F58: 480 | G58: 480 | H58: 480 | I58: 480
B59: 300 | C59: fsbs | G59: 165 | H59: 200 | I59: 200
B60: 2500 | C60: round table | F60: 300 | H60: 1300
B61: 2000 | C61: isaac | J61: 2000
B62: =1400+170 -> 1570 | C62: temba | H62: 700 | I62: 700 | J62: 500
C63: kudzai | F63: 500 | G63: 500 | H63: 500 | I63: 500 | J63: 500 | K63: 500 | L63: 500 | M63: 500
C64: white moon | I64: 500
C65: xmeric, wool sets, tights | H65: =450+65+48 -> 563
C66: oreya | J66: 400 | K66: 400
C67: roda | J67: 375 | K67: 375
E71: june | F71: july | G71: aug | H71: sept | I71: oct | J71: nov | K71: dec
C72: subs
C73: bosha
C74: mafake
C75: musapa
C76: mutanho
C77: muzenda
C78: sithole
C80: loans
C81: bosha | D81: 300 | E81: 30
C82: mafake
C83: musapa
C84: mutanho | D84: 300
C85: muzenda
C86: sithole | D86: 129

Sheet sops
A1: to
B2: all layby & credit sales instalments to be updated on invoice for audit purposes
B3: daily analysis to be completed daily & check all transactions against receipts, invoices, pos & zimra machine
B5: DAILY SALES TO BE RECORDED AND RECONCILED DAILY
B7: REGULAR STOCK SPOT CHECK ESP ON NEW STOCK
B9: stock taken by clients home for fitting | G9: double check labels and quanity when returned
G10: double check labels and quanity when going out
G11: record in the stock out diary when stock leaves the shop
G12: tick and cancell returned stock
G13: record stock taken by client on the daily analysis and cash/credit invoice
G14: end of every week cross check if there is stock that went out which has not been returned
B16: discounts | G16: only given on cash purchases
G17: have a cash discount receipt stating discount amount and signed by the client
G18: max discount discretion is $5
B20: cash received allocation
G21: weekly $100 savings | L21: 100
G22: weekly $ 50 education fund savings | L22: 50
F23: balance to | G23: stock procurement | L23: 0.5
G24: investment | L24: 0.1
G25: home improvement | L25: 0.1
G26: working capital | L26: 0.3
B28: STAFF LEAVE DAYS
C29: PAU # of days | D29: dates | G29: TATENDA # of days | H29: dates | K29: nyadzi # of days | L29: dates
C30: 14 | D30: 45292 | G30: 14 | H30: dec '23 - jan '24 | K30: 7 | L30: feb '24
G31: 3 | H31: 19-21 feb
G32: 5 | H32: 26 feb-1 mar
B35: TOTAL | C35: =SUM(C30:C34) -> 14 | G35: =SUM(G30:G34) -> 22 | K35: =SUM(K30:K34) -> 7

Sheet stock purchase 2023
A1: SHOP | B1: shop | C1: label | D1: qnty | E1: size | F1: Item | G1: purchase price / unit $ | H1: total purchase price | I1: total cost excl stock | J1: Indirect Cost / unit | K1: Total Unit Cost | L1: Multiplier | M1: Rec Price | N1: Actual Price | O1: reduced 4 sale | P1: stock take 4 | R1: date | S1: sales
C2: 45323
B3: white moon | C3: wioma | E3: 44 | F3: brown beige winter dress | G3: 25 | M3: 90 | N3: 90 | Q3: macy tagwirei | R3: 45359 | S3: =+N3*18000 -> 1620000
B4: white moon | C4: wioma | E4: 46 | F4: brown beige winter dress | G4: 25 | M4: 90 | N4: 90 | Q4: layby zezai | R4: 45377 | S4: =+N4*20000 -> 1800000
B5: white moon | C5: wioma | E5: 48 | F5: brown beige winter dress | G5: 25 | M5: 90 | N5: 90 | Q5: cash, | R5: 45369 | S5: =+N5*18000 -> 1620000
B6: white moon | C6: wioma | E6: 50 | F6: brown beige winter dress | G6: 25 | M6: 90 | N6: 90 | Q6: cash mai prudence | R6: 45358 | S6: =+N6*18000 -> 1620000
B7: white moon | C7: wioma | E7: 52 | F7: brown winter dress w beige sleeves | G7: 25 | M7: 90 | N7: 90 | Q7: cash | R7: 45384 | S7: =+N7*35000 -> 3150000
B8: white moon | C8: wioma | E8: 54 | F8: brown winter dress w beige sleeves | G8: 25 | M8: 90 | N8: 90
B9: white moon | C9: wioma | E9: 56 | F9: brown winter dress w beige sleeves | G9: 25 | M9: 90 | N9: 90
B10: white moon | C10: wioma | E10: 58 | F10: brown winter dress w beige sleeves | G10: 25 | M10: 90 | N10: 90
B11: white moon | C11: wioma | E11: 44 | F11: black/white scotch w bottom pleats | G11: 25 | M11: 90 | N11: 90 | Q11: cash | R11: 45372 | S11: =+N11*20000 -> 1800000
B12: white moon | C12: wioma | E12: 46 | F12: black/white scotch w bottom pleats | G12: 25 | M12: 90 | N12: 90 | Q12: macy tagwirei | R12: 45359 | S12: =+N12*18000 -> 1620000
B13: white moon | C13: wioma | E13: 48 | F13: black/white scotch w bottom pleats | G13: 25 | M13: 90 | N13: 90 | Q13: cash | R13: 45378 | S13: =+N13*30000 -> 2700000
B14: white moon | C14: wioma | E14: 50 | F14: black/white scotch w bottom pleats | G14: 25 | M14: 90 | N14: 90 | Q14: cash | R14: 45384 | S14: =+N14*35000 -> 3150000
C15: wioma | E15: 44 | F15: beige / brown w front slit design | N15: 90
C16: wioma | E16: 46 | F16: beige / brown w front slit design | N16: 90
C17: wioma | E17: 48 | F17: beige / brown w front slit design | N17: 90
C18: wioma | E18: 50 | F18: beige / brown w front slit design | N18: 90
G19: =SUM(G3:G14) -> 300 | M19: =SUM(M3:M14) -> 1080
C20: 45352
B21: GOWNS
B22: Tango | C22: calino | E22: 42 | F22: green satin wrap over w sheer sleeves | G22: 45 | H22: 4192 | I22: 3417 | J22: =+I22/H22*G22 -> 36.680582 | K22: =+G22+J22 -> 81.680582 | L22: 1.4 | M22: =+K22*L22 -> 114.35281 | N22: 150
B23: Tango | C23: calino | E23: 44 | F23: green satin wrap over w sheer sleeves | G23: 45 | H23: 4192 | I23: 3417 | J23: =+I23/H23*G23 -> 36.680582 | K23: =+G23+J23 -> 81.680582 | L23: 1.4 | M23: =+K23*L23 -> 114.35281 | N23: 150
B24: Tango | C24: calino | E24: 46 | F24: green satin wrap over w sheer sleeves | G24: 45 | H24: 4192 | I24: 3417 | J24: =+I24/H24*G24 -> 36.680582 | K24: =+G24+J24 -> 81.680582 | L24: 1.4 | M24: =+K24*L24 -> 114.35281 | N24: 150 | Q24: cash emilia | R24: 45386 | S24: =+N24*35000 -> 5250000
B25: Tango | C25: calino | E25: 48 | F25: green satin wrap over w sheer sleeves | G25: 45 | H25: 4192 | I25: 3417 | J25: =+I25/H25*G25 -> 36.680582 | K25: =+G25+J25 -> 81.680582 | L25: 1.4 | M25: =+K25*L25 -> 114.35281 | N25: 150 | Q25: mandidzinga | R25: 45379 | S25: =+N25*30000 -> 4500000
B26: Tango | C26: calino | E26: 36 | F26: gold satin wrap over w sheer sleeves | G26: 45 | H26: 4192 | I26: 3417 | J26: =+I26/H26*G26 -> 36.680582 | K26: =+G26+J26 -> 81.680582 | L26: 1.4 | M26: =+K26*L26 -> 114.35281 | N26: 150
B27: Tango | C27: calino | E27: 38 | F27: gold satin wrap over w sheer sleeves | G27: 45 | H27: 4192 | I27: 3417 | J27: =+I27/H27*G27 -> 36.680582 | K27: =+G27+J27 -> 81.680582 | L27: 1.4 | M27: =+K27*L27 -> 114.35281 | N27: 150
B28: Tango | C28: calino | E28: 40 | F28: gold satin wrap over w sheer sleeves | G28: 45 | H28: 4192 | I28: 3417 | J28: =+I28/H28*G28 -> 36.680582 | K28: =+G28+J28 -> 81.680582 | L28: 1.4 | M28: =+K28*L28 -> 114.35281 | N28: 150
B29: Tango | C29: calino | E29: 42 | F29: gold satin wrap over w sheer sleeves | G29: 45 | H29: 4192 | I29: 3417 | J29: =+I29/H29*G29 -> 36.680582 | K29: =+G29+J29 -> 81.680582 | L29: 1.4 | M29: =+K29*L29 -> 114.35281 | N29: 150 | Q29: cash | R29: 45378 | S29: =+N29*30000 -> 4500000
B30: fervente | C30: fervente | E30: 38 | F30: gold gown | G30: 38 | H30: 4192 | I30: 3417 | J30: =+I30/H30*G30 -> 30.974714 | K30: =+G30+J30 -> 68.974714 | L30: 1.4 | M30: =+K30*L30 -> 96.564599 | N30: 125
B31: fervente | C31: fervente | E31: 40 | F31: gold gown | G31: 38 | H31: 4192 | I31: 3417 | J31: =+I31/H31*G31 -> 30.974714 | K31: =+G31+J31 -> 68.974714 | L31: 1.4 | M31: =+K31*L31 -> 96.564599 | N31: 125
B32: fervente | C32: fervente | E32: 42 | F32: gold gown | G32: 38 | H32: 4192 | I32: 3417 | J32: =+I32/H32*G32 -> 30.974714 | K32: =+G32+J32 -> 68.974714 | L32: 1.4 | M32: =+K32*L32 -> 96.564599 | N32: 125
B33: fervente | C33: fervente | E33: 38 | F33: rose gold gown | G33: 29 | H33: 4192 | I33: 3417 | J33: =+I33/H33*G33 -> 23.638597 | K33: =+G33+J33 -> 52.638597 | L33: 1.4 | M33: =+K33*L33 -> 73.694036 | N33: 125
B34: fervente | C34: fervente | E34: 40 | F34: rose gold gown | G34: 29 | H34: 4192 | I34: 3417 | J34: =+I34/H34*G34 -> 23.638597 | K34: =+G34+J34 -> 52.638597 | L34: 1.4 | M34: =+K34*L34 -> 73.694036 | N34: 125
B35: fervente | C35: fervente | E35: 42 | F35: rose gold gown | G35: 29 | H35: 4192 | I35: 3417 | J35: =+I35/H35*G35 -> 23.638597 | K35: =+G35+J35 -> 52.638597 | L35: 1.4 | M35: =+K35*L35 -> 73.694036 | N35: 125
B36: fiero | C36: ladonatella | E36: 44 | F36: black /white sheer one arm gown | G36: 68 | H36: 4192 | I36: 3417 | J36: =+I36/H36*G36 -> 55.428435 | K36: =+G36+J36 -> 123.42844 | L36: 1.4 | M36: =+K36*L36 -> 172.79981 | N36: 200
B37: fiero | C37: ladonatella | E37: crew | F37: black /white sheer one arm gown | G37: 68 | H37: 4192 | I37: 3417 | J37: =+I37/H37*G37 -> 55.428435 | K37: =+G37+J37 -> 123.42844 | L37: 1.4 | M37: =+K37*L37 -> 172.79981 | N37: 200
B38: fiero | C38: ladonatella | E38: 48 | F38: black /white sheer one arm gown | G38: 68 | H38: 4192 | I38: 3417 | J38: =+I38/H38*G38 -> 55.428435 | K38: =+G38+J38 -> 123.42844 | L38: 1.4 | M38: =+K38*L38 -> 172.79981 | N38: 200 | Q38: cash emilia | R38: 45386 | S38: =+N38*35000 -> 7000000
B39: fiero | C39: fiero | E39: 52 | F39: rose gold gown w front slit & sheer sleeve | G39: 68 | H39: 4192 | I39: 3417 | J39: =+I39/H39*G39 -> 55.428435 | K39: =+G39+J39 -> 123.42844 | L39: 1.4 | M39: =+K39*L39 -> 172.79981 | N39: 200
B40: fiero | C40: fiero | E40: 54 | F40: rose gold gown w front slit & sheer sleeve | G40: 68 | H40: 4192 | I40: 3417 | J40: =+I40/H40*G40 -> 55.428435 | K40: =+G40+J40 -> 123.42844 | L40: 1.4 | M40: =+K40*L40 -> 172.79981 | N40: 200
B41: fiero | C41: fiero | E41: 56 | F41: rose gold gown w front slit & sheer sleeve | G41: 68 | H41: 4192 | I41: 3417 | J41: =+I41/H41*G41 -> 55.428435 | K41: =+G41+J41 -> 123.42844 | L41: 1.4 | M41: =+K41*L41 -> 172.79981 | N41: 200
B42: fiero | C42: fiero | E42: 52 | F42: gold short gown | G42: 39 | H42: 4192 | I42: 3417 | J42: =+I42/H42*G42 -> 31.789838 | K42: =+G42+J42 -> 70.789838 | L42: 1.4 | M42: =+K42*L42 -> 99.105773
B43: fiero | C43: fiero | E43: 54 | F43: gold short gown | G43: 39 | H43: 4192 | I43: 3417 | J43: =+I43/H43*G43 -> 31.789838 | K43: =+G43+J43 -> 70.789838 | L43: 1.4 | M43: =+K43*L43 -> 99.105773 | N43: 125
B44: fiero | C44: fiero | E44: 56 | F44: gold short gown | G44: 39 | H44: 4192 | I44: 3417 | J44: =+I44/H44*G44 -> 31.789838 | K44: =+G44+J44 -> 70.789838 | L44: 1.4 | M44: =+K44*L44 -> 99.105773 | N44: 125
F45: TOTAL | G45: =SUM(G22:G44) -> 1086 | N45: =SUM(N22:N44) -> 3400
B46: DRESSES
B47: White pepper | C47: moda milla | E47: 42 | F47: black dress w white stripe | G47: 33 | H47: 4192 | I47: 3417 | J47: =+I47/H47*G47 -> 26.899094 | K47: =+G47+J47 -> 59.899094 | L47: 1.4 | M47: =+K47*L47 -> 83.858731 | N47: 110
B48: White pepper | C48: moda milla | E48: 44 | F48: black dress w white stripe | G48: 33 | H48: 4192 | I48: 3417 | J48: =+I48/H48*G48 -> 26.899094 | K48: =+G48+J48 -> 59.899094 | L48: 1.4 | M48: =+K48*L48 -> 83.858731 | N48: 110 | Q48: cash | R48: 45378 | S48: =+N48*30000 -> 3300000
B49: White pepper | C49: moda milla | E49: 46 | F49: black dress w white stripe | G49: 33 | H49: 4192 | I49: 3417 | J49: =+I49/H49*G49 -> 26.899094 | K49: =+G49+J49 -> 59.899094 | L49: 1.4 | M49: =+K49*L49 -> 83.858731 | N49: 110
B50: White pepper | C50: moda milla | E50: 48 | F50: black dress w white stripe | G50: 33 | H50: 4192 | I50: 3417 | J50: =+I50/H50*G50 -> 26.899094 | K50: =+G50+J50 -> 59.899094 | L50: 1.4 | M50: =+K50*L50 -> 83.858731 | N50: 110
B51: black rose volonte | C51: black rose | E51: 38 | F51: green pleated skirt & blouse | G51: 40 | H51: 4192 | I51: 3417 | J51: =+I51/H51*G51 -> 32.604962 | K51: =+G51+J51 -> 72.604962 | L51: 1.4 | M51: =+K51*L51 -> 101.64695 | N51: 125
B52: black rose volonte | C52: black rose | E52: 40 | F52: green pleated skirt & blouse | G52: 40 | H52: 4192 | I52: 3417 | J52: =+I52/H52*G52 -> 32.604962 | K52: =+G52+J52 -> 72.604962 | L52: 1.4 | M52: =+K52*L52 -> 101.64695 | N52: 125
B53: black rose volonte | C53: black rose | E53: 42 | F53: green pleated skirt & blouse | G53: 40 | H53: 4192 | I53: 3417 | J53: =+I53/H53*G53 -> 32.604962 | K53: =+G53+J53 -> 72.604962 | L53: 1.4 | M53: =+K53*L53 -> 101.64695 | N53: 110 | Q53: tete chipo | R53: 45379 | S53: =+N53*30000 -> 3300000
B54: black rose volonte | C54: black rose | E54: 44 | F54: green pleated skirt & blouse | G54: 40 | H54: 4192 | I54: 3417 | J54: =+I54/H54*G54 -> 32.604962 | K54: =+G54+J54 -> 72.604962 | L54: 1.4 | M54: =+K54*L54 -> 101.64695 | N54: 110
B55: black rose volonte | C55: black rose | E55: 44 | F55: coffee pleated skirt & blouse | G55: 42 | H55: 4192 | I55: 3417 | J55: =+I55/H55*G55 -> 34.23521 | K55: =+G55+J55 -> 76.23521 | L55: 1.4 | M55: =+K55*L55 -> 106.72929 | N55: 110
B56: black rose volonte | C56: black rose | E56: 46 | F56: coffee pleated skirt & blouse | G56: 42 | H56: 4192 | I56: 3417 | J56: =+I56/H56*G56 -> 34.23521 | K56: =+G56+J56 -> 76.23521 | L56: 1.4 | M56: =+K56*L56 -> 106.72929 | N56: 110
B57: black rose volonte | C57: black rose | E57: 48 | F57: coffee pleated skirt & blouse | G57: 42 | H57: 4192 | I57: 3417 | J57: =+I57/H57*G57 -> 34.23521 | K57: =+G57+J57 -> 76.23521 | L57: 1.4 | M57: =+K57*L57 -> 106.72929 | N57: 110
B58: black rose volonte | C58: black rose | E58: 50 | F58: coffee pleated skirt & blouse | G58: 42 | H58: 4192 | I58: 3417 | J58: =+I58/H58*G58 -> 34.23521 | K58: =+G58+J58 -> 76.23521 | L58: 1.4 | M58: =+K58*L58 -> 106.72929 | N58: 110
B59: black rose volonte | C59: black rose | E59: 44 | F59: orange pleated skirt & blouse | G59: 37 | H59: 4192 | I59: 3417 | J59: =+I59/H59*G59 -> 30.15959 | K59: =+G59+J59 -> 67.15959 | L59: 1.4 | M59: =+K59*L59 -> 94.023426 | N59: 125 | Q59: tete chipo | R59: 45379 | S59: =+N59*30000 -> 3750000
B60: black rose volonte | C60: black rose | E60: 46 | F60: orange pleated skirt & blouse | G60: 37 | H60: 4192 | I60: 3417 | J60: =+I60/H60*G60 -> 30.15959 | K60: =+G60+J60 -> 67.15959 | L60: 1.4 | M60: =+K60*L60 -> 94.023426 | N60: 125 | Q60: cash | R60: 45378 | S60: =+N60*30000 -> 3750000
B61: black rose volonte | C61: black rose | E61: 48 | F61: orange pleated skirt & blouse | G61: 37 | H61: 4192 | I61: 3417 | J61: =+I61/H61*G61 -> 30.15959 | K61: =+G61+J61 -> 67.15959 | L61: 1.4 | M61: =+K61*L61 -> 94.023426 | N61: 125
B62: black rose volonte | C62: black rose | E62: 50 | F62: orange pleated skirt & blouse | G62: 37 | H62: 4192 | I62: 3417 | J62: =+I62/H62*G62 -> 30.15959 | K62: =+G62+J62 -> 67.15959 | L62: 1.4 | M62: =+K62*L62 -> 94.023426 | N62: 125
B63: IDEAL | C63: mast fashion | E63: 42 | F63: green/white dress net material w white belt | G63: 27 | H63: 4192 | I63: 3417 | J63: =+I63/H63*G63 -> 22.008349 | K63: =+G63+J63 -> 49.008349 | L63: 1.4 | M63: =+K63*L63 -> 68.611689 | N63: 110
B64: IDEAL | C64: mast fashion | E64: 44 | F64: green/white dress net material w white belt | G64: 27 | H64: 4192 | I64: 3417 | J64: =+I64/H64*G64 -> 22.008349 | K64: =+G64+J64 -> 49.008349 | L64: 1.4 | M64: =+K64*L64 -> 68.611689 | N64: 110
B65: IDEAL | C65: mast fashion | E65: 46 | F65: green/white dress net material w white belt | G65: 27 | H65: 4192 | I65: 3417 | J65: =+I65/H65*G65 -> 22.008349 | K65: =+G65+J65 -> 49.008349 | L65: 1.4 | M65: =+K65*L65 -> 68.611689 | N65: 110
B66: IDEAL | C66: mast fashion | E66: 48 | F66: green/white dress net material w white belt | G66: 27 | H66: 4192 | I66: 3417 | J66: =+I66/H66*G66 -> 22.008349 | K66: =+G66+J66 -> 49.008349 | L66: 1.4 | M66: =+K66*L66 -> 68.611689 | N66: 110 | Q66: cash | R66: 45371 | S66: =+N66*20000 -> 2200000
B67: IDEAL | C67: my tenim | E67: 42 | F67: denim shirt dress w white tie/dye design | G67: 35 | H67: 4192 | I67: 3417 | J67: =+I67/H67*G67 -> 28.529342 | K67: =+G67+J67 -> 63.529342 | L67: 1.4 | M67: =+K67*L67 -> 88.941078 | N67: 110
B68: IDEAL | C68: my tenim | E68: 44 | F68: denim shirt dress w white tie/dye design | G68: 35 | H68: 4192 | I68: 3417 | J68: =+I68/H68*G68 -> 28.529342 | K68: =+G68+J68 -> 63.529342 | L68: 1.4 | M68: =+K68*L68 -> 88.941078 | N68: 110
B69: IDEAL | C69: my tenim | E69: 46 | F69: denim shirt dress w white tie/dye design | G69: 35 | H69: 4192 | I69: 3417 | J69: =+I69/H69*G69 -> 28.529342 | K69: =+G69+J69 -> 63.529342 | L69: 1.4 | M69: =+K69*L69 -> 88.941078 | N69: 110
B70: IDEAL | C70: my tenim | E70: 48 | F70: denim shirt dress w white tie/dye design | G70: 35 | H70: 4192 | I70: 3417 | J70: =+I70/H70*G70 -> 28.529342 | K70: =+G70+J70 -> 63.529342 | L70: 1.4 | M70: =+K70*L70 -> 88.941078 | N70: 110
B71: IDEAL | C71: M | E71: 42 | F71: beige dress w black frill | G71: 36 | H71: 4192 | I71: 3417 | J71: =+I71/H71*G71 -> 29.344466 | K71: =+G71+J71 -> 65.344466 | L71: 1.4 | M71: =+K71*L71 -> 91.482252 | N71: 125
B72: IDEAL | C72: M | E72: 44 | F72: beige dress w black frill | G72: 36 | H72: 4192 | I72: 3417 | J72: =+I72/H72*G72 -> 29.344466 | K72: =+G72+J72 -> 65.344466 | L72: 1.4 | M72: =+K72*L72 -> 91.482252 | N72: 125
B73: IDEAL | C73: M | E73: 46 | F73: beige dress w black frill | G73: 36 | H73: 4192 | I73: 3417 | J73: =+I73/H73*G73 -> 29.344466 | K73: =+G73+J73 -> 65.344466 | L73: 1.4 | M73: =+K73*L73 -> 91.482252 | N73: 125
B74: IDEAL | C74: M | E74: 48 | F74: beige dress w black frill | G74: 36 | H74: 4192 | I74: 3417 | J74: =+I74/H74*G74 -> 29.344466 | K74: =+G74+J74 -> 65.344466 | L74: 1.4 | M74: =+K74*L74 -> 91.482252 | N74: 125
B75: IDEAL | C75: F & B girls | E75: 50 | F75: black/gold denim shirt dress w belt | G75: 42 | H75: 4192 | I75: 3417 | J75: =+I75/H75*G75 -> 34.23521 | K75: =+G75+J75 -> 76.23521 | L75: 1.4 | M75: =+K75*L75 -> 106.72929 | N75: 125
B76: IDEAL | C76: F & B girls | E76: 52 | F76: black/gold denim shirt dress w belt | G76: 42 | H76: 4192 | I76: 3417 | J76: =+I76/H76*G76 -> 34.23521 | K76: =+G76+J76 -> 76.23521 | L76: 1.4 | M76: =+K76*L76 -> 106.72929 | N76: 125
B77: IDEAL | C77: F & B girls | E77: 54 | F77: black/gold denim shirt dress w belt | G77: 42 | H77: 4192 | I77: 3417 | J77: =+I77/H77*G77 -> 34.23521 | K77: =+G77+J77 -> 76.23521 | L77: 1.4 | M77: =+K77*L77 -> 106.72929 | N77: 125
B78: IDEAL | C78: F & B girls | E78: 56 | F78: black/gold denim shirt dress w belt | G78: 42 | H78: 4192 | I78: 3417 | J78: =+I78/H78*G78 -> 34.23521 | K78: =+G78+J78 -> 76.23521 | L78: 1.4 | M78: =+K78*L78 -> 106.72929 | N78: 125 | Q78: cash mazanhi | R78: 45379 | S78: =+N78*30000 -> 3750000
B79: fervente | C79: fervente | E79: 38 | F79: hot pink pleated dress w waist design | G79: 22 | H79: 4192 | I79: 3417 | J79: =+I79/H79*G79 -> 17.932729 | K79: =+G79+J79 -> 39.932729 | L79: 1.4 | M79: =+K79*L79 -> 55.905821 | N79: 110
B80: fervente | C80: fervente | E80: 40 | F80: hot pink pleated dress w waist design | G80: 22 | H80: 4192 | I80: 3417 | J80: =+I80/H80*G80 -> 17.932729 | K80: =+G80+J80 -> 39.932729 | L80: 1.4 | M80: =+K80*L80 -> 55.905821 | N80: 110
B81: fervente | C81: fervente | E81: 42 | F81: hot pink pleated dress w waist design | G81: 22 | H81: 4192 | I81: 3417 | J81: =+I81/H81*G81 -> 17.932729 | K81: =+G81+J81 -> 39.932729 | L81: 1.4 | M81: =+K81*L81 -> 55.905821 | N81: 110
B82: fervente | C82: fervente | E82: 38 | F82: cream pleated dress w waist design | G82: 22 | H82: 4192 | I82: 3417 | J82: =+I82/H82*G82 -> 17.932729 | K82: =+G82+J82 -> 39.932729 | L82: 1.4 | M82: =+K82*L82 -> 55.905821 | N82: 110
B83: fervente | C83: fervente | E83: 40 | F83: cream pleated dress w waist design | G83: 22 | H83: 4192 | I83: 3417 | J83: =+I83/H83*G83 -> 17.932729 | K83: =+G83+J83 -> 39.932729 | L83: 1.4 | M83: =+K83*L83 -> 55.905821 | N83: 110
B84: fervente | C84: fervente | E84: 42 | F84: cream pleated dress w waist design | G84: 22 | H84: 4192 | I84: 3417 | J84: =+I84/H84*G84 -> 17.932729 | K84: =+G84+J84 -> 39.932729 | L84: 1.4 | M84: =+K84*L84 -> 55.905821 | N84: 110
B85: darkmen | C85: darkmen | E85: 1 | F85: green/black polka dot cotton dress | G85: 24 | H85: 4192 | I85: 3417 | J85: =+I85/H85*G85 -> 19.562977 | K85: =+G85+J85 -> 43.562977 | L85: 1.4 | M85: =+K85*L85 -> 60.988168 | N85: 110
B86: darkmen | C86: darkmen | E86: 2 | F86: green/black polka dot cotton dress | G86: 24 | H86: 4192 | I86: 3417 | J86: =+I86/H86*G86 -> 19.562977 | K86: =+G86+J86 -> 43.562977 | L86: 1.4 | M86: =+K86*L86 -> 60.988168 | N86: 110 | Q86: cash mazanhi | R86: 45374 | S86: =+N86*20000 -> 2200000
B87: darkmen | C87: darkmen | E87: 1 | F87: beige/black cotton dress | G87: 24 | H87: 4192 | I87: 3417 | J87: =+I87/H87*G87 -> 19.562977 | K87: =+G87+J87 -> 43.562977 | L87: 1.4 | M87: =+K87*L87 -> 60.988168 | N87: 110
B88: darkmen | C88: darkmen | E88: 2 | F88: beige/black cotton dress | G88: 24 | H88: 4192 | I88: 3417 | J88: =+I88/H88*G88 -> 19.562977 | K88: =+G88+J88 -> 43.562977 | L88: 1.4 | M88: =+K88*L88 -> 60.988168 | N88: 110 | Q88: cash mazanhi | R88: 45374 | S88: =+N88*20000 -> 2200000
B89: darkmen | C89: darkmen | E89: 1 | F89: denim look midi sleeveless dress | G89: 23 | H89: 4192 | I89: 3417 | J89: =+I89/H89*G89 -> 18.747853 | K89: =+G89+J89 -> 41.747853 | L89: 1.4 | M89: =+K89*L89 -> 58.446994 | N89: 110
B90: darkmen | C90: darkmen | E90: 2 | F90: denim look midi sleeveless dress | G90: 23 | H90: 4192 | I90: 3417 | J90: =+I90/H90*G90 -> 18.747853 | K90: =+G90+J90 -> 41.747853 | L90: 1.4 | M90: =+K90*L90 -> 58.446994 | N90: 110
B91: modagun | C91: modagun | E91: 50 | F91: green chiffon short dress | G91: 25 | H91: 4192 | I91: 3417 | J91: =+I91/H91*G91 -> 20.378101 | K91: =+G91+J91 -> 45.378101 | L91: 1.4 | M91: =+K91*L91 -> 63.529342 | N91: 110
B92: modagun | C92: modagun | E92: 52 | F92: green chiffon short dress | G92: 25 | H92: 4192 | I92: 3417 | J92: =+I92/H92*G92 -> 20.378101 | K92: =+G92+J92 -> 45.378101 | L92: 1.4 | M92: =+K92*L92 -> 63.529342 | N92: 110
B93: modagun | C93: modagun | E93: 54 | F93: green chiffon short dress | G93: 25 | H93: 4192 | I93: 3417 | J93: =+I93/H93*G93 -> 20.378101 | K93: =+G93+J93 -> 45.378101 | L93: 1.4 | M93: =+K93*L93 -> 63.529342 | N93: 110
B94: modagun | C94: modagun | E94: 56 | F94: green chiffon short dress | G94: 25 | H94: 4192 | I94: 3417 | J94: =+I94/H94*G94 -> 20.378101 | K94: =+G94+J94 -> 45.378101 | L94: 1.4 | M94: =+K94*L94 -> 63.529342 | N94: 110
B95: modagun | C95: modagun | E95: 50 | F95: cream/hot pink chiffon dress | G95: 25 | H95: 4192 | I95: 3417 | J95: =+I95/H95*G95 -> 20.378101 | K95: =+G95+J95 -> 45.378101 | L95: 1.4 | M95: =+K95*L95 -> 63.529342 | N95: 110
B96: modagun | C96: modagun | E96: 52 | F96: cream/hot pink chiffon dress | G96: 25 | H96: 4192 | I96: 3417 | J96: =+I96/H96*G96 -> 20.378101 | K96: =+G96+J96 -> 45.378101 | L96: 1.4 | M96: =+K96*L96 -> 63.529342 | N96: 110
B97: modagun | C97: modagun | E97: 54 | F97: cream/hot pink chiffon dress | G97: 25 | H97: 4192 | I97: 3417 | J97: =+I97/H97*G97 -> 20.378101 | K97: =+G97+J97 -> 45.378101 | L97: 1.4 | M97: =+K97*L97 -> 63.529342 | N97: 110
B98: modagun | C98: modagun | E98: 56 | F98: cream/hot pink chiffon dress | G98: 25 | H98: 4192 | I98: 3417 | J98: =+I98/H98*G98 -> 20.378101 | K98: =+G98+J98 -> 45.378101 | L98: 1.4 | M98: =+K98*L98 -> 63.529342 | N98: 110
B99: white moon | C99: fimas | E99: 44 | F99: army green flared chiffon dress w flower design | G99: 25 | H99: 4192 | I99: 3417 | J99: =+I99/H99*G99 -> 20.378101 | K99: =+G99+J99 -> 45.378101 | L99: 1.4 | M99: =+K99*L99 -> 63.529342 | N99: 110 | Q99: layby manhambara | R99: 45384 | S99: =+N99*35000 -> 3850000
B100: white moon | C100: fimas | E100: 46 | F100: army green flared chiffon dress w flower design | G100: 25 | H100: 4192 | I100: 3417 | J100: =+I100/H100*G100 -> 20.378101 | K100: =+G100+J100 -> 45.378101 | L100: 1.4 | M100: =+K100*L100 -> 63.529342 | N100: 110
...

Sheet stock movement
B36: stock type | C36: 2022 opening level | D36: 2022 closing level | E36: amnt sold during the year | F36: % sale
A38: 1 | B38: face towels | C38: 9 | D38: 2 | E38: =+C38-D38 -> 7 | F38: =+E38/C38*100 -> 77.777778
A39: 2 | B39: panties | C39: 209 | D39: 69 | E39: =+C39-D39 -> 140 | F39: =+E39/C39*100 -> 66.985646
A40: 3 | B40: clutch bags | C40: 72 | D40: 28 | E40: =+C40-D40 -> 44 | F40: =+E40/C40*100 -> 61.111111
A41: 4 | B41: jerseys | C41: 82 | D41: 32 | E41: =+C41-D41 -> 50 | F41: =+E41/C41*100 -> 60.97561
A42: 5 | B42: scarfs | C42: 24 | D42: 10 | E42: =+C42-D42 -> 14 | F42: =+E42/C42*100 -> 58.333333
A43: 6 | B43: dresses | C43: 912 | D43: 381 | E43: =+C43-D43 -> 531 | F43: =+E43/C43*100 -> 58.223684
A44: 7 | B44: coserts | C44: 19 | D44: 8 | E44: =+C44-D44 -> 11 | F44: =+E44/C44*100 -> 57.894737
A45: 8 | B45: handbags | C45: 57 | D45: 25 | E45: =+C45-D45 -> 32 | F45: =+E45/C45*100 -> 56.140351
A46: 9 | B46: jackets | C46: 48 | D46: 22 | E46: =+C46-D46 -> 26 | F46: =+E46/C46*100 -> 54.166667
A47: 10 | B47: pantyhose | C47: 49 | D47: 25 | E47: =+C47-D47 -> 24 | F47: =+E47/C47*100 -> 48.979592
A48: 11 | B48: tops & blouses | C48: 271 | D48: 139 | E48: =+C48-D48 -> 132 | F48: =+E48/C48*100 -> 48.708487
A49: 12 | B49: dress outfits | C49: 64 | D49: 36 | E49: =+C49-D49 -> 28 | F49: =+E49/C49*100 -> 43.75
... A58: 21 | B58: pajamas | C58: 4 | D58: 3 | E58: =+C58-D58 -> 1 | F58: =+E58/C58*100 -> 25
