Workbook

Sheet Budget
A1: to | B1: trip | C1: date - | D1: destination | E1: ticket | F1: visa | G1: currency commission | H1: acc | I1: misc | J1: transport inc airport | K1: food | L1: extra kg | M1: cargo | N1: airport duty | O1: stock | P1: personal | Q1: 2 MONTHS RENTAL | R1: 2 MONTHS SALARIES | S1: TOTAL COST | T1: TOTAL overheads | U1: total recommende sales value | V1: total actual sales value | W1: profit | X1: profit in USD
B3: istanbul | C3: 30 may-10 june 2021 | D3: istanbul | E3: 930 | F3: 230 | H3: 200 | J3: 10 | K3: 50 | M3: =886+1723+1000 -> 3609 | O3: 9148 | P3: 500 | Q3: 400 | R3: 400 | S3: =SUM(E3:R3) -> 15477
B7: istanbul november 2021 trip
B8: 0 | G8: =844*0.04+75 -> 108.76 | H8: =25*6 -> 150 | I8: =3*15+10 -> 55 | J8: 50 | K8: 20 | L8: 250 | M8: 1200 | N8: 360 | O8: 6556 | P8: 0 | Q8: 400 | R8: 600 | S8: =SUM(B8:R8) -> 9749.76
B10: istanbul kapura Dec | I10: =+O10*0.06 -> 210.3 | M10: =70*17+50+20*17+50 -> 1630 | O10: =1992+1048+465 -> 3505 | Q10: 200 | R10: 700 | S10: =SUM(G10:R10) -> 6245.3
B13: istanbul april2022 | E13: 850 | H13: =135+60 -> 195 | I13: 55 | J13: 50 | K13: 20 | L13: =4*110+75*3 -> 665 | M13: =80*17.5+50 -> 1450 | N13: =720+15+40 -> 775 | O13: =+'stock purchase 2026'!#REF! -> #REF! | P13: =100+15+35+20+17+18+15+10+35 -> 265 | Q13: 300 | R13: 375 | S13: =SUM(E13:R13) -> #REF!
B16: istanbulsept 2022 | C16: 10 -22 sept | D16: istanbul | E16: =1220+135 -> 1355 | F16: 220 | G16: =3000*0.05 -> 150 | H16: =40+30*5+80 -> 270 | I16: 50 | J16: 50 | K16: 50 | L16: =3*120+4*75 -> 660 | M16: 0 | N16: =600+30+40 -> 670 | O16: 6911 | P16: =66+10+200+40+50 -> 366 | Q16: 500 | R16: 375 | S16: =SUM(E16:R16) -> 11627 | T16: =+E16+F16+G16+H16+I16+J16+K16+L16+M16+N16+P16+Q16+R16 -> 4716
B17: via Germany | C17: 17-20 sept | D17: germany | E17: 370
B19: ISTANBUL | C19: 19-27 NOV | D19: ISTANBUL | E19: 800 | H19: 250 | I19: 16 | J19: 50 | K19: 50 | L19: 200 | N19: 480 | O19: 4607 | P19: 250 | Q19: 500 | R19: 400 | S19: =SUM(E19:R19) -> 7603 | T19: =+S19-O19 -> 2996 | U19: =+'stock purchase 2026'!#REF! -> #REF! | V19: =+'stock purchase 2026'!#REF! -> #REF! | W19: =+V19-S19 -> #REF!
B23: istanbul March 2023 | C23: 5-12 mar | D23: istanbul | E23: 1235 | H23: 240 | I23: 100 | J23: 50 | K23: 50 | L23: =500+225 -> 725 | N23: 840 | O23: 8267 | P23: 50 | Q23: =+(2200+500) -> 2700 | R23: 1000 | S23: =SUM(E23:R23) -> 15257 | T23: =+S23-O23 -> 6990
B24: via Germany | C24: 28 feb-4 march | D24: germany | E24: 100 | H24: 180 | I24: 50 | J24: 40 | K24: 40 | S24: =SUM(E24:R24) -> 410 | T24: =+S24 -> 410
T25: =SUM(T23:T24) -> 7400
B26: istanbul | C26: 7-13 march | D26: istanbul | E26: 951 | H26: 240 | I26: 100 | J26: =50+30 -> 80 | K26: =50+20 -> 70 | L26: =500+75*9 -> 1175 | N26: =8*120+90 -> 1050 | O26: 9682 | P26: 400 | Q26: =2200+500 -> 2700 | R26: =+(400+400+200) -> 1000 | S26: =SUM(E26:R26) -> 17448 | T26: =+S26-O26 -> 7766
L28: =+E26+H26+I26+J26+K26+L26+N26 -> 3666 | M28: =+L26+N26 -> 2225 | N28: =32*8 -> 256
L29: =+L28/N28 -> 14.320312 | N29: =+M28/N28 -> 8.6914062
B30: ISTANBUL MAY 2023
B34: ISTANBUL | C34: 2-9 JULY 2023 | D34: istanbul | E34: 1080 | H34: 200 | I34: 50 | J34: =40+40+5+7 -> 92 | K34: 20 | L34: =130+300 -> 430 | M34: =15*16.5+25 -> 272.5 | N34: 480 | O34: 6066 | P34: 200 | Q34: =950*2+250*2 -> 2400 | R34: =+(175*2+100*2)+240 -> 790 | S34: =SUM(E34:R34) -> 12080.5 | T34: =+S34-O34 -> 6014.5
B37: istanbul sept/oct | C37: 25-29 15-18 | D37: istanbul | E37: 930 | F37: 400 | H37: =8*45 -> 360 | I37: =60+100+35+35 -> 230 | J37: =50+30+40+10 -> 130 | K37: 50 | L37: =2*120+3*75 -> 465 | M37: =502+25*16.5+25*16.5 -> 1327 | N37: =4*120 -> 480 | O37: 6440 | P37: 100 | Q37: =950*2+250*2 -> 2400 | R37: =+(175*2+120*2)+240 -> 830 | S37: =SUM(E37:R37) -> 14142 | T37: =+S37-O37 -> 7702
B38: new york | C38: 30-14 oct | D38: new york/ florida | E38: 900 | F38: 160 | H38: =593+180 -> 773 | J38: =42+42+27+60+17+14+8 -> 210 | K38: 180 | L38: =30+40 -> 70 | N38: 120 | O38: 1327 | P38: =54+25+35+29+20+53 -> 216 | S38: =SUM(E38:R38) -> 3956 | T38: =+S38-O38 -> 2629
B39: total | E39: =SUM(E37:E38) -> 1830 | F39: =SUM(F37:F38) -> 560 | G39: =SUM(G37:G38) -> 0 | H39: =SUM(H37:H38) -> 1133 | I39: =SUM(I37:I38) -> 230 | J39: =SUM(J37:J38) -> 340 | K39: =SUM(K37:K38) -> 230 | L39: =SUM(L37:L38) -> 535 | ... P39: =SUM(P37:P38) -> 316 | S39: =SUM(S37:S38) -> 18098 | T39: =SUM(T37:T38) -> 10331
B41: BABY WEAR | C41: 25-29 15-18 | D41: istanbul | E41: 300 | F41: 50 | G41: 0 | H41: 0 | I41: 100 | J41: 20 | K41: 20 | L41: 200 | M41: 439 | N41: 120 | O41: 2400 | Q41: 500 | R41: 300 | S41: =SUM(E41:R41) -> 4449 | T41: =+S41-O41 -> 2049
B44: istanbul | C44: 13-20nov | D44: istanbul | E44: 800 | H44: =6*45 -> 270 | I44: 50 | J44: 30 | K44: 50 | M44: 902 | O44: 3687 | P44: 30 | Q44: 500 | R44: =350+240+360 -> 950 | S44: =SUM(E44:R44) -> 7269 | T44: =+S44-O44 -> 3582
B45: BABY WEAR | E45: 300 | H45: =2*35 -> 70 | I45: 150 | K45: 20 | M45: =568-8*15.5+600 -> 1044 | O45: 1215 | P45: 20 | Q45: 500 | R45: 420 | S45: =SUM(E45:R45) -> 3739 | T45: =+S45-O45 -> 2524
B47: baby wear omer | C47: cargo | M47: 400 | O47: 532 | Q47: 500 | R47: 400 | S47: =SUM(E47:R47) -> 1832 | T47: =+S47-O47 -> 1300
B50: turkey trip august | C50: AUGUST 2024. | E50: 1100 | H50: =45*6 -> 270 | I50: 100 | K50: 50 | M50: 1234 | O50: 5000 | P50: 200 | Q50: =250*2 -> 500 | R50: 800 | S50: =SUM(E50:R50) -> 9254 | T50: =+S50-O50 -> 4254
B51: exotic blossom | E51: 200 | M51: =320+243 -> 563 | O51: 1400 | S51: =SUM(E51:R51) -> 2163 | T51: =+S51-O51 -> 763
B52: baby
B55: CHINA TRIP | C55: 3-12 JAN 2025. | D55: GUANGZHOU | E55: 1100 | H55: =46*5 -> 230 | I55: 50 | J55: 50 | K55: 70 | L55: 83.571429 | M55: =188*18 -> 3384 | N55: 585.15625 | P55: 100
B56: exotic blossom | E56: 800 | F56: 70 | H56: =+H55*0.7 -> 161 | I56: 50 | J56: =+J55*0.7 -> 35 | K56: =+K55*0.7 -> 49 | L56: 84 | M56: 2384 | N56: 585 | O56: 3550 | P56: 100 | Q56: 500 | R56: 800 | S56: =SUM(E56:R56) -> 9168 | T56: =+S56-O56 -> 5618
B57: exotic babies | E57: 300 | F57: 30 | H57: =+H55*0.3 -> 69 | J57: =+J55*0.3 -> 15 | K57: =+K55*0.3 -> 21 | M57: 1000 | O57: 1650 | Q57: 550 | R57: 350 | S57: =SUM(E57:R57) -> 3985 | T57: =+S57-O57 -> 2335
B59: Turkey trip | C59: 26 april - 5 may | D59: istanbul | E59: 1200 | F59: 360 | H59: 280 | I59: 100 | K59: 100 | M59: 2217 | N59: =295.3125+120 -> 415.3125 | O59: 4112 | P59: 100 | Q59: 500 | R59: 560 | S59: =SUM(E59:R59) -> 9944.3125 | T59: =+S59-O59 -> 5832.3125
B61: Turkey trip | C61: 28 SEPT - 5 OCT | D61: ISTANBUL | E61: 1080 | H61: 240 | I61: 75 | K61: 80 | L61: =200+75*4 -> 500 | N61: =400+4000/32 -> 525 | O61: 5225 | P61: 200 | Q61: 500 | R61: 500 | S61: =SUM(E61:R61) -> 8925 | T61: =+S61-O61 -> 3700
T62: =+S62-O62 -> 0
B63: CHINA TRIP | C63: 12-22 NOV | D63: GUANGZHOU | E63: 1425 | F63: 125 | H63: =(588/3*9)/7 -> 252 | I63: 50 | J63: 50 | K63: 80 | L63: 571.42857 | N63: 400 | O63: 4072 | P63: 120 | Q63: 500 | R63: 400 | S63: =SUM(E63:R63) -> 8045.4286 | T63: =+S63-O63 -> 3973.4286
D66: 2026…
C67: 11-18 JAN 2026.. | D67: ISTANBUL | E67: 1050 | H67: 200 | J67: 50 | K67: 50 | L67: 75 | M67: =53*17+125 -> 1026 | N67: 200 | O67: 4609 | P67: 50 | Q67: 500 | R67: 400 | S67: =SUM(E67:R67) -> 8210 | T67: =+S67-O67 -> 3601
B83: NOTES
B84: MARCH TRIP - | C84: FIND MANY CLEARANCE SALES, good opportunity for big margins
C85: buy outfits & dresses for occassions then
C86: buy winter items and leave for may, can also do kapura
C87: if i buy winter things on layby i should not do a trip in June coz this coincides with layby final payments, cargo costs and duty.
C88: unless the trip is for going to collect the items on layby
C89: JACKETS ARE NOT PROFITABLE IF BOUGHT FOR MORE THAN $15 EACH
C90: winter items are bulky and heavy. Resulting in high cargo charges. Better to buy winter items all through out the year.
E93: jan-dec 208m
E105: SALES ANALYSIS 2016-2021
E106: month | F106: 2016 | G106: 2017 | H106: 2018 | I106: 2019 | J106: 2020 | K106: 2021
E107: jan | F107: 3811 | I107: 2814 | J107: 4180
E108: feb | F108: 4126 | I108: 2883 | J108: 3413
E109: mar | F109: 5742 | I109: 6262 | J109: 6532
E110: apr | F110: 12651 | I110: 2162 | J110: 128
E111: may | F111: 5651 | I111: 6517 | J111: 3594
E112: jun | F112: 8161 | I112: 1498 | J112: 3961
E113: jul | F113: 6484 | I113: 6873 | J113: 5060
E114: aug | F114: 8230 | I114: 5505 | J114: 3150
E115: sept | I115: 7189 | J115: 5083
E116: oct | I116: 6691 | J116: 3875
E117: nov | I117: 6841 | J117: 4706
E118: dec | I118: 7148 | J118: 6947
B126: sales graph since inception
C127: month | D127: sales | E127: expenses | F127: stock
C128: 42248 | D128: 6540 | E128: 4941
C129: 42278 | D129: 11157 | E129: 5768
C130: 42309 | D130: 6993 | E130: 2988 | F130: 4682
C131: 42339 | D131: 9405 | E131: 7452
C132: 42370 | D132: 3811 | E132: 4168 | F132: 2074
C133: 42401 | D133: 4126 | E133: 3225
C134: 42430 | D134: 5742 | E134: 3971 | F134: 10401
C135: 42461 | D135: 12651 | E135: 4337 | F135: 1250
C136: 42491
C137: 42522
C138: 42552
C141: total | D141: =SUM(D128:D140) -> 60425
B144: MARCH CASH BUDGET
D145: Rent | E145: 200 | G145: fron daily sales | I145: 100 | J145: per week for rent
D146: round table | E146: 90 | I146: 50 | J146: per week for client refund
D147: visa insurance | E147: 38 | I147: 20 | J147: per week tete connie
D148: visa application | E148: 200 | I148: 150 | J148: per week savings
D149: kudzi refund | E149: 90
D150: china dresses | E150: 300 | I150: =SUM(I145:I149) -> 320
D151: turkey cargo | E151: 150
D152: carpenter shop shelving | E152: 70
D153: shop licence | E153: 300
D154: vida track suit | E154: 41
E158: =SUM(E145:E157) -> 1479
D159: seke
D160: fence | E160: 130
D161: poles | E161: 70

Sheet STOCK TAKE
A1: to
B2: STOCK TAKE OCTOBER 2020
B4: LABEL | C4: DESCRIPTION | D4: PURCHASE PRICE | E4: SALE PRICE | J4: LABEL | K4: DESCRIPTION | L4: PURCHASE PRICE | M4: SALE PRICE
B6: MISSING STOCK | J6: MISSING STOCK
A7: 1 | B7: Le mirage | C7: burnt orage/white 2 piece | D7: 25 | I7: 1 | J7: adalyn | K7: navy dress w pleated back
A8: 2 | B8: le mirage | C8: navy 2 pc w printed skirt | D8: 25 | J8: versace | K8: grey 2 piece track suit from avondale
A9: 3 | B9: ell shirt dress | C9: shirt dress | D9: 9 | J9: nesly | K9: coffee suit
B10: tights | C10: tights | D10: 5 | K10: nesly coffee suit
B11: oreya | C11: maroon sude wedge shoe | D11: 8 | J11: TANGO EZGI | K11: PINK TOP/FLOWERY SKIRT
D12: =SUM(D7:D11) -> 72
B13: eastgate sales
A14: 1 | B14: yuxi fashion | C14: red wrap over dress | D14: 10 | E14: 45
C15: green dress cotton multi colour
B17: SALES ANALYSIS BY CATGORY
B18: STOCK | C18: OPENING QNTY | D18: CLOSING QNTY | E18: SALES QNTY | F18: % SALE | K18: stock not on stock sheet
B19: DRESS OUTFITS | J19: 1 | K19: mardi | L19: green/beige floral flared dress repeat - | M19: 28 | N19: 110
B20: 2 PIECE OUTFITS
B21: DRESSES | C21: 669 | D21: 355 | E21: =+C21-D21 -> 314 | F21: =+E21/C21*100 -> 46.935725 | K21: oreya white t shirt w front glitter
B22: SKIRTS | C22: 106 | D22: 83 | E22: =+C22-D22 -> 23 | F22: =+E22/C22*100 -> 21.698113 | K22: FI & BI | L22: black jeggin 46 | M22: sold but not on stocksheet
B23: TOPS | C23: 155 | D23: 86 | E23: =+C23-D23 -> 69 | F23: =+E23/C23*100 -> 44.516129
B24: TROUSERS | C24: 59 | D24: 34 | E24: =+C24-D24 -> 25 | F24: =+E24/C24*100 -> 42.372881
B25: WOOLEN TOPS | C25: 99 | D25: 41 | E25: =+C25-D25 -> 58 | F25: =+E25/C25*100 -> 58.585859
B26: JACKETS | C26: 31 | D26: 22 | E26: =+C26-D26 -> 9 | F26: =+E26/C26*100 -> 29.032258
B27: JERSEY | C27: 59 | D27: 26 | E27: =+C27-D27 -> 33 | F27: =+E27/C27*100 -> 55.932203
B28: TRACK SUITS | C28: 59 | D28: 34 | E28: =+C28-D28 -> 25 | F28: =+E28/C28*100 -> 42.372881
B29: SHOES | C29: 200 | D29: 111 | E29: =+C29-D29 -> 89 | F29: =+E29/C29*100 -> 44.5
B30: CLUTCH | C30: 12 | D30: 6 | E30: =+C30-D30 -> 6 | F30: =+E30/C30*100 -> 50
B31: COSERT | C31: 10 | D31: 4 | E31: =+C31-D31 -> 6 | F31: =+E31/C31*100 -> 60
B32: HANDBAGS | C32: 25 | D32: 9 | E32: =+C32-D32 -> 16 | F32: =+E32/C32*100 -> 64
B33: PANTY | C33: 103 | D33: 49 | E33: =+C33-D33 -> 54 | F33: =+E33/C33*100 -> 52.427184
B34: GYPSY SOCKS | C34: 40 | D34: 36 | E34: =+C34-D34 -> 4 | F34: =+E34/C34*100 -> 10
B45: OCTOBER STOCK TAKE 2022
C46: over | D46: under
B47: OVERS
B48: rouge grey knit dress 2 pc w hood
B50: UNDER
A51: channel | B51: navy | E51: balance with the one addedback jan 2022 stock take
B52: SKIRTS
A53: escarell | B53: black knit | E53: To check amount actually bought
A54: escarell | B54: black knit | E54: To check amount actually bought
B56: TROUSERS
A57: la gazelle | B57: 8 | C57: 36 | D57: trousers
A58: la curuse | B58: 14 | C58: 52 | D58: denim trousers
B59: SHIRTS & TOPS
A60: oreya | B60: white sleeveless long t shirt | C60: M
B61: WOOLEN TOPS
A62: oreya | B62: light throw blue with glitter front
A63: oreya | B63: polo neck burgundy
A64: oreya | B64: polo neck burgundy
A65: oreya | B65: twin set black | C65: L
A66: oreya | B66: t shirt jacket black
B68: JERSEYS
A69: oreya | B69: navy / maroon short jersey
A70: oreya | B70: jersey maroon with fur neck & sleeves 2020
B72: TRACK SUITS
A73: versace | B73: versarche grey trouser set
A74: bavinchi | B74: NAVY 3 PIECE | C74: 4xl
B76: SHOES
A77: ALTIN YAK | B77: maroon wedge
A78: ALTIN YAK | B78: black wedge w elastic top
B79: HANDBAGS
B80: LV black handbag w single handle
B82: ladies ankle socks black
A84: scarfs | B84: all colours

Sheet cashflow
A1: to | B1: CASHFLOW -2018 | C1: Jan | D1: Feb | E1: Mar | F1: Apr | G1: May | H1: Jun | I1: Jul | J1: Aug | K1: Sep | L1: Oct | M1: Nov | N1: Dec | P1: %
B2: INFLOWS
B3: SALES
B4: Cash sales | C4: =+'daily sales'!#REF! -> #REF!
B5: pos purchases
C6: =SUM(C4:C5) -> #REF!
B8: LOANS
B9: stanbic bank loan
B10: loans personal
B11: loans other
B14: refunds
B17: Total | C17: =+C6+C12+C14 -> #REF!
B19: MONTHLY EXPENSES
B20: stock purchases | C20: =+cashbook!#REF!+cashbook!#REF!+cashbook!#REF!+cashbook!#REF!+cashbook!#REF! -> #REF! | S20: 145
B22: operating expenses | C22: =SUM(C23:C58) -> 1903 | S22: 255
B23: parking | C23: 10 | S23: 75
B24: fuel | C24: 20 | S24: 50
B25: salaries
B26: Pauline | S26: 155
B27: Tatenda | S27: 323
B28: allowance self | C28: 321 | S28: 195
B29: staff transport allowance | S29: 62
B30: Pauline | C30: =87+18 -> 105
B31: Tatenda
B32: staff commission
B33: Pauline | C33: 21
B34: Tatenda | C34: 21
B35: rentals | C35: 250 | S35: 30
B36: rates | S36: =SUM(S20:S35) -> 1290
B37: electricity
B38: cleaning & packaging materials & shop utilities | C38: 10
B39: stationery
B40: car running expenses | R40: =346-24-13 -> 309
B41: miscellaneous
B42: airtime | C42: 50
B43: Business refreshments
B44: small asset procurement
B45: big asset procurement | C45: 600
B46: sales discount
B47: refunds
B48: money transfer charges
B49: membership fees
B50: licence fees and registrations | C50: 410
B51: gym subs & training
B52: bank fees & charges
B53: pos bank comission 2.5%
B54: zimra QPD
B55: medical | C55: 85
B56: donations
B57: company fees
B59: stock procurement costs | C59: =SUM(C60:C74) -> 1352
B60: visa
B61: ticket | C61: =1259+93 -> 1352
B62: extra kgs - bags packed to 32kg
B63: Luggage exess bags
B64: accomodation
B65: transport
B66: food
B67: cargo
B68: duty
B69: travel incidentals
B70: transportation charge for goods from a/port
B71: airport fees
B72: T & S
B73: loss on change of ticket
B74: PASSPORT APPLICATION
B75: EDUCATION | C75: =SUM(C76:C79) -> 0
B76: school fees.
B77: monthly allowance
B78: other
B80: LOAN REPAYMENT: | C80: =SUM(C81:C86) -> 0
B81: loan sharewealth
B82: loan ruwa ladies
B83: stanbic business loan
B84: loans others
B85: other loans
B87: TOTAL EXPENDITURE | C87: =+C80+C75+C59+C22+C20 -> #REF!
B90: TOTAL INCOME | C90: =+C17 -> #REF!
B91: TOTAL EXPENSES | C91: =+C87 -> #REF!
B93: SURPLUS/DEFICIT | C93: =+C90-C91 -> #REF!
B96: INVESTMENTS
B97: Allan Gray
B98: home improvement/ construction
B99: $600 round
B100: $10 daily savings
B101: $20 daily savings
B102: school fees fund
B103: TOTAL
B115: NOTES
B116: sharewealth bricks loan to be classsified as home improvements
B117: major expenditure in 2020 included the construction and roofing of the house extension/cottage. Plumbing works and construction of the storm water drain,
B121: sales schedule
... B132: july

Sheet cash budget

Sheet cashbook
A1: to | C1: cash USD | D1: debit card | E1: Cash bond ecocash | F1: cash /DEBIT convert to USD | G1: TOTAL | J1: expenditure | K1: cash | L1: personal
J2: JANUARY 2026..
J3: rentals & opc
J4: city of harare licence 2026 | K4: =+(6044+60+91+4200+63)/25 -> 418.32
J8: salaries & transport
J9: Transport Pau | K9: 80
J10: Transport Tatenda | K10: 80
J11: packaging plastics | K11: 20
J12: travel
J13: accomodation momento | K13: 200
J14: transport | K14: 50
J15: food | K15: 50
J16: misc | K16: 50
J17: stock | M17: =1129/52 -> 21.711538
J18: turkey stock pur | K18: 4609
J19: stock procurement cost
J20: TD freight & duty - angel sandals | K20: 232
J21: turkey stock stock freight & duty | K21: 200
J22: turkey stock 2 freight & AWB | K22: =52.2*7+125 -> 490.4
J23: turkey stock 2 duty | K23: =(14600/33)+120+76 -> 638.42424
J24: stock distribution cost
J25: cleaning & refreshment
J26: packaging plastics | K26: 20
J27: taxation
J28: zimra quarterly tax | K28: 260
J29: loan repayments
J30: viano loan repayment - paid ruwa local board | K30: 100
J33: personal
J34: part salary | L34: =100+10 -> 110
K35: =SUM(K4:K34) -> 7498.1442 | L35: =SUM(L4:L34) -> 110
J38: FEBRUARY
J39: rentals & opc
J40: LAPF jan rentals and opc | K40: =140+40.625 -> 180.625
J41: lapf opc arrear as feb statement - exotic | K41: 93.939394
J42: lapf opc arrear as feb statement - baby shop | K42: 124.24242
J43: salaries & transport
J44: Jan salary Pau | K44: 200
J45: Jan salary Tatenda | K45: 200
J46: Transport Pau | K46: 80
J47: Transport Tatenda | K47: 80
J48: other staff costs
J49: medical aid | K49: 260
J50: funeral cover | K50: 44
J52: travel
J53: stock
J54: kapris stock | K54: 160
J55: ferat layby | K55: 166
J56: roda credit payment | K56: 250
J57: mahmut baby part paymnt | K57: 600
J58: ideal payment | K58: 412
J59: ahmed winter | K59: 140
J60: mavellino instalment 1 | K60: 400
J62: stock procurement cost
J63: kapris sending charges | K63: =160*0.045 -> 7.2
J64: biker charges | K64: 5
J65: turkey payments sending charges | K65: 32
J66: baby shop stock cargo omer stock | K66: 330
J67: exotic blossom stock cargo kapris | K67: =5.9*14.5+25 -> 110.55
J68: sending charges 852* 0.045 | K68: 38
J69: stock distribution cost
J70: biker charges | K70: 7
J72: cleaning & refreshment
J73: packaging china duty & freight | K73: =30+34 -> 64
J74: cleaning agents | K74: 10
J75: taxation
J77: loan repayments
J78: sharewealth | M78: paid by ct
J79: roundtable | K79: 376
J81: personal
J82: part salary | L82: =100+100+40+20 -> 260
J85: rounds
J86: 1k round | K86: 1000
J87: fsbs | K87: 300
J88: 200 round monthly | K88: 200
J89: 200 twice a month
J92: FEBRUARY
J93: rentals & opc
J97: salaries & transport
J98: feb salary Pau | K98: 200
J99: feb salary Tatenda | K99: 200
J100: Transport Pau | K100: 80
J101: Transport Tatenda | K101: 80
J102: commission | K102: 2
J103: other staff costs
J104: medical aid
J105: funeral cover
J107: travel
J108: stock
J109: mavellino instalment 2 | K109: 275
J110: fervent stock mai muti | K110: 110
J115: MARCH
J116: rentals & opc
J117: march rentals and opc | K117: 300
J119: TRAVEL EXPENSES - stock procurement
J120: china ticket part pymnt - 1498-500 | K120: 500
J122: stock purchase
J123: mavellino final inst | K123: 275
J124: mavellino 2nd suit seri | K124: 275
J125: ahmed moda repeat | K125: 140
J126: ajar purple gown | K126: 100
...

Sheet daily sales
A1: date | B1: USD cash SALE | C1: USD POS SALE | D1: ZIG POS SALE | E1: item description | F1: CASH | G1: POS | H1: layby sale cost | I1: layby inst/ deposit / fnl pyment cash | J1: layby inst/ deposit final pmnt DEBIT | K1: credit sale cost | L1: credit sale payment CASH | M1: credit sale payment DEBIT | N1: DISC
A3: 46024 | E3: LAYBY INST MANYUMWA | J3: 65
E4: china daisy brown/beige 3 pc linen set | G4: 110
E5: china coffee/orange chiffon 2pc dress w fur sleeves | G5: 120
E6: layby Eve Mutsvangwa | I6: 90
E7: elise china 2pc linen trouser set | H7: 110
D8: confirm which one | E8: china red/black maxi w black lining | H8: 125
B9: =+J9 -> 65 | C9: =+G9+I9 -> 320 | G9: =SUM(G3:G8) -> 230 | H9: =SUM(H3:H8) -> 235 | I9: =SUM(I3:I8) -> 90 | J9: =SUM(J3:J8) -> 65 | K9: =SUM(K3:K8) -> 0 | L9: =SUM(L3:L8) -> 0 | M9: =SUM(M3:M8) -> 0 | N9: =SUM(N3:N8) -> 0
A11: 46025 | E11: china black 2pc tracksuit w white line | F11: 100
E12: angel original nude shoe on sale | F12: 25
E13: bayker black panties s4 | F13: 5
B14: =+F14 -> 130 | F14: =SUM(F11:F13) -> 130
A16: 46027 | E16: cr inst mrs muzenda | F16: 75
E17: hairband fascinator | F17: 15
B18: =+F18 -> 90 | F18: =SUM(F16:F17) -> 90
A20: 46028 | E20: layby inst eve mutsvangwa | F20: 145
E21: cr inst nampala | F21: 60
E22: china yellow stripe shirt dress | F22: 65
E23: cr pur lydia shoe shop -round fascinator | K23: 25
E24: china gold belt | G24: 5
B25: =+F25 -> 270 | C25: =+G25 -> 5 | F25: =SUM(F20:F24) -> 270 | G25: =SUM(G20:G24) -> 5 | H25: =SUM(H20:H24) -> 0 | I25: =SUM(I20:I24) -> 0 | J25: =SUM(J20:J24) -> 0 | K25: =SUM(K20:K24) -> 25
A27: 46029 | E27: cr pur mrs musapatika
E28: wioma black/grey winter dress | K28: 55
E29: kakor pink /cream chiffon dress | K29: 60
E30: angel brown sandals 39 | K30: 30
K31: =SUM(K28:K30) -> 145
A33: 46030 | E33: black executive bag | F33: 50
E34: bayker black panty xl | F34: 5
E35: angel maroon block heel 10 | F35: 25
E36: angel black heel w top buckle 10 | F36: 25
E37: angel red heel 40 | F37: 25
E38: cr pur tete nyaradzo
E39: x2 china seamless panties xl | K39: 10
E40: china lace panty 3xl | K40: 5
E41: x2 bayker black panty xxl | K41: 10
E42: x2 bayker colourful panty 2xl | K42: 10
E43: channel maroon track dress on sale | G43: 25
E44: cr inst Wendy | F44: 70
B45: =+F45 -> 200 | C45: =+G45 -> 25 | F45: =SUM(F33:F44) -> 200 | G45: =SUM(G33:G44) -> 25 | H45: =SUM(H33:H44) -> 0 | I45: =SUM(I33:I44) -> 0 | J45: =SUM(J33:J44) -> 0 | K45: =SUM(K33:K44) -> 35 | L45: =SUM(L33:L44) -> 0
A47: 46031 | E47: cr inst zvenyika | G47: 100
E48: cr inst lydia | G48: 25
B49: =+G49 -> 125 | G49: =SUM(G47:G48) -> 125
A51: 46032 | E51: x5 bayker black xl | G51: 25
E52: oreya t shirt lime green | G52: 35
E53: oreya pink t shirt | G53: 35
E54: catania black top w bottom silver glitter | G54: 35
E55: ashley steward white lace dress on sale | G55: 25
E56: black headband fascinator | G56: 15
E57: angel brown sandals 10 | G57: 30
E58: x1 bayker beige panty 3xl | G58: 6
B60: =+G60 -> 206 | G60: =SUM(G51:G59) -> 206
A62: 46034 | E62: livello red/black satin dress 44 | F62: 145 | N62: 5
E63: balenciaga black big bag | F63: 55 | N63: 5
E64: layby mhonde | I64: 20
E65: brown hanbag weave design | H65: 45
E66: angel brown sandal 12M | F66: 30
B67: =+F67+I67 -> 250 | F67: =SUM(F62:F66) -> 230 | G67: =SUM(G62:G66) -> 0 | H67: =SUM(H62:H66) -> 45 | I67: =SUM(I62:I66) -> 20 | J67: =SUM(J62:J66) -> 0 | K67: =SUM(K62:K66) -> 0 | L67: =SUM(L62:L66) -> 0 | M67: =SUM(M62:M66) -> 0 | N67: =SUM(N62:N66) -> 10
A69: 46035 | E69: cr inst musapatika | F69: 30
E70: cr pur musapatika
E71: perla maroon dress w jacket 50 | K71: 125
E72: angel maroon shoes w square heels | K72: 25
B74: =+F74 -> 30 | F74: =SUM(F69:F73) -> 30 | K74: =SUM(K71:K73) -> 150
A76: 46036
A78: 46037 | E78: china chiffon 2pc dress w fur sleeves | F78: 125
E79: china cream/polka dot skirt /blous set | F79: 125
B80: =+F80 -> 250 | F80: =SUM(F78:F79) -> 250
A82: 46038 | E82: ezgi pink scuba dress w glitter & sheer sleeves 38 | F82: 120 | N82: 5
E83: cr inst kambarami | M83: 20
E84: china hairband fascinator | M84: 15
B86: =+F86 -> 120 | C86: =+M86 -> 35 | F86: =SUM(F82:F85) -> 120 | M86: =SUM(M83:M85) -> 35
A88: 46039 | E88: layby pur mr banda - nolina scatch skirt 50 | H88: 65 | I88: 30
E89: layby inst irene | F89: 35
B90: =+F90+I90 -> 65 | F90: =SUM(F89) -> 35 | H90: =SUM(H88:H89) -> 65 | I90: =SUM(I88:I89) -> 30
A92: 46041 | E92: hairband fascinator | F92: 15
E93: layby inst chidzenga | F93: 26
E94: earrings | F94: 5
B96: =+F96 -> 46 | F96: =SUM(F92:F95) -> 46
A98: 46042 | E98: layby mrs mapotsa
E99: more green/black brocade dress layby | H99: 180 | I99: 100
E100: mint green boxy clutch | H100: 15
B102: =+I102 -> 100 | H102: =SUM(H99:H101) -> 195 | I102: =SUM(I99:I101) -> 100
A104: 46043 | E104: jupiter coffee pleated dress w top 52 | G104: 150
E105: yina navy blue shirt dress | G105: 65
E106: china black/white pleated dress | G106: 80
E107: cr inst memory ndava | F107: 55
E108: cr inst mai poly | L108: 125
E109: cr pur mai poly - formanta black suit s42 | K109: 180 | L109: 55
E110: layby inst mhonde | J110: 25
E111: credit inst matsika | L111: 60
E112: cr inst nyamakupi | L112: 55
E113: panas line beige lace dress | F113: 60
B114: =+F114+J114+L114 -> 435 | C114: =+G114 -> 295 | F114: =SUM(F104:F113) -> 115 | G114: =SUM(G104:G112) -> 295 | H114: =SUM(H104:H112) -> 0 | I114: =SUM(I104:I112) -> 0 | J114: =SUM(J104:J112) -> 25 | K114: =SUM(K104:K112) -> 180 | L114: =SUM(L104:L112) -> 295 | M114: =SUM(M104:M112) -> 0 | N114: =SUM(N104:N112) -> 0
A116: 46044 | B116: =+F116 -> 40 | E116: cr inst abiba | F116: 40
A118: 46045 | E118: layby insy mapotsa | F118: 95
E119: textport beige/black polka dot 52 | F119: 125
E120: angel black sandals slip on 12m | F120: 30
E121: dejavu brown lace dress 44 | F121: 125
B123: =+F123 -> 375 | C123: =+G123 -> 0 | D123: =+H123 -> 0 | F123: =SUM(F118:F122) -> 375
A125: 46046 | E125: yna yellow/white shirt dress | F125: 55
E126: layby mrs shambira - yna yellow casual dress long | H126: 65 | I126: 35
...

Sheet dresses
B1: SHOP | C1: LABEL | D1: Q | E1: size | F1: Item | H1: pur price | I1: total purchase price | J1: total cost | K1: Indirect Cost / unit | L1: Total Unit Cost | M1: Multiplier | N1: recommended | O1: Actual Price | P1: SALE | Q1: S/T JAN '25 | R1: s/take jan2026 | S1: status | T1: date
F2: BALL GOWNS
C3: TEMEL CARGO APRIL2021
C4: nivola | D4: 1 | E4: 46 | F4: rose gold gown mermaid design | H4: 59 | I4: 959 | J4: 1284 | K4: =+H4/I4*J4 -> 78.994786 | L4: =+H4+K4 -> 137.99479 | M4: 0.3 | N4: =+L4*M4+L4 -> 179.39322 | O4: 200 | P4: 60
C5: nivola | D5: 2 | E5: 44 | F5: rose gold ball gown mermaid style | H5: 67 | I5: 8183 | J5: 13183 | K5: =+H5/I5*J5 -> 107.93853 | L5: =+H5+K5 -> 174.93853 | M5: 0.3 | N5: =+L5*M5+L5 -> 227.42009 | O5: 250 | P5: 80
C6: 44713
C7: nivola | D7: 3 | E7: 42 | F7: gold lace mermaid gown | H7: 75 | I7: 580 | J7: 200 | K7: =+H7/I7*J7 -> 25.862069 | L7: =+H7+K7 -> 100.86207 | M7: 0.3 | N7: =+L7*M7+L7 -> 131.12069 | O7: 150 | P7: 80
C8: nivola | D8: 4 | E8: 44 | F8: gold lace mermaid gown | H8: 75 | I8: 580 | J8: 200 | K8: =+H8/I8*J8 -> 25.862069 | L8: =+H8+K8 -> 100.86207 | M8: 0.3 | N8: =+L8*M8+L8 -> 131.12069 | O8: 150 | P8: 80
C9: Tiana | D9: 6 | E9: 44 | F9: green sleeveless ball gown | H9: 70 | I9: 580 | J9: 200 | K9: =+H9/I9*J9 -> 24.137931 | L9: =+H9+K9 -> 94.137931 | M9: 0.3 | N9: =+L9*M9+L9 -> 122.37931 | O9: 150
C10: Tiana | D10: 7 | E10: 46 | F10: green sleeveless ball gown | H10: 70 | I10: 580 | J10: 200 | K10: =+H10/I10*J10 -> 24.137931 | L10: =+H10+K10 -> 94.137931 | M10: 0.3 | N10: =+L10*M10+L10 -> 122.37931 | O10: 150
C11: Tiana | D11: 8 | E11: 48 | F11: green sleeveless ball gown | H11: 70 | I11: 580 | J11: 200 | K11: =+H11/I11*J11 -> 24.137931 | L11: =+H11+K11 -> 94.137931 | M11: 0.3 | N11: =+L11*M11+L11 -> 122.37931 | O11: 150
C12: Tiana | D12: 9 | E12: 50 | F12: green sleeveless ball gown | H12: 70 | I12: 580 | J12: 200 | K12: =+H12/I12*J12 -> 24.137931 | L12: =+H12+K12 -> 94.137931 | M12: 0.3 | N12: =+L12*M12+L12 -> 122.37931 | O12: 150
C13: 44743
B14: prosperity Tiana | C14: Tiana | D14: 11 | E14: 48 | F14: burgundy gown | H14: 60 | I14: 952 | J14: =+I14+440 -> 1392 | K14: =+H14/I14*J14 -> 87.731092 | L14: =+H14+K14 -> 147.73109 | M14: 0.3 | N14: =+L14*M14+L14 -> 192.05042 | O14: 200
F15: sept 2022 stock | L15: =+H15+K15 -> 0
B16: tiana | C16: tiana | D16: 12 | E16: 48 | F16: green straight pleated gown | H16: 50 | I16: 6911 | J16: 4716 | K16: =+H16/I16*J16 -> 34.11952 | L16: =+H16+K16 -> 84.11952 | M16: 0.3 | N16: =+L16*M16+L16 -> 109.35538 | O16: 80
B17: tiana | C17: tiana | D17: 13 | E17: 50 | F17: green straight pleated gown | H17: 50 | I17: 6911 | J17: 4716 | K17: =+H17/I17*J17 -> 34.11952 | L17: =+H17+K17 -> 84.11952 | M17: 0.3 | N17: =+L17*M17+L17 -> 109.35538 | O17: 80
B18: tiana | C18: tiana | D18: 14 | E18: 44 | F18: green w short dress inside | H18: 65 | I18: 6911 | J18: 4716 | K18: =+H18/I18*J18 -> 44.355375 | L18: =+H18+K18 -> 109.35538 | M18: 0.3 | N18: =+L18*M18+L18 -> 142.16199 | O18: 80
B19: tiana | C19: tiana | D19: 16 | E19: 48 | F19: green w short dress inside | H19: 65 | I19: 6911 | J19: 4716 | K19: =+H19/I19*J19 -> 44.355375 | L19: =+H19+K19 -> 109.35538 | M19: 0.3 | N19: =+L19*M19+L19 -> 142.16199 | O19: 80
B20: tiana | C20: tiana | D20: 17 | E20: 50 | F20: green w short dress inside | H20: 65 | I20: 6911 | J20: 4716 | K20: =+H20/I20*J20 -> 44.355375 | L20: =+H20+K20 -> 109.35538 | M20: 0.3 | N20: =+L20*M20+L20 -> 142.16199 | O20: 80
B21: nivola | C21: nivola | D21: 18 | E21: 42 | F21: black chiffon gown w ruched bust | H21: 40 | I21: 6911 | J21: 4716 | K21: =+H21/I21*J21 -> 27.295616 | L21: =+H21+K21 -> 67.295616 | M21: 0.3 | N21: =+L21*M21+L21 -> 87.4843 | O21: 150 | S21: grey area
B22: favana | C22: favana | D22: 20 | E22: 56 | F22: lilac gown | H22: 70 | I22: 6911 | J22: 4716 | K22: =+H22/I22*J22 -> 47.767327 | L22: =+H22+K22 -> 117.76733 | M22: 0.3 | N22: =+L22*M22+L22 -> 153.09753 | O22: 180
B23: favana | C23: favana | D23: 21 | E23: 52 | F23: mint green gown | H23: 70 | I23: 6911 | J23: 4716 | K23: =+H23/I23*J23 -> 47.767327 | L23: =+H23+K23 -> 117.76733 | M23: 0.3 | N23: =+L23*M23+L23 -> 153.09753 | O23: 180
B24: favana | C24: favana | D24: 22 | E24: 54 | F24: mint green gown | H24: 70 | I24: 6911 | J24: 4716 | K24: =+H24/I24*J24 -> 47.767327 | L24: =+H24+K24 -> 117.76733 | M24: 0.3 | N24: =+L24*M24+L24 -> 153.09753 | O24: 180
B25: nivola | C25: nivola | D25: 23 | E25: 42 | F25: navy chiffon gown w pleated bust | H25: 50 | I25: 6911 | J25: 4716 | K25: =+H25/I25*J25 -> 34.11952 | L25: =+H25+K25 -> 84.11952 | M25: 0.3 | N25: =+L25*M25+L25 -> 109.35538 | O25: 180 | P25: 125
B26: nivola | C26: nivola | D26: 24 | E26: 44 | F26: navy chiffon gown w pleated bust | H26: 50 | I26: 6911 | J26: 4716 | K26: =+H26/I26*J26 -> 34.11952 | L26: =+H26+K26 -> 84.11952 | M26: 0.3 | N26: =+L26*M26+L26 -> 109.35538 | O26: 180 | P26: 125
B27: nivola | C27: nivola | D27: 25 | E27: 46 | F27: navy chiffon gown w pleated bust | H27: 50 | I27: 6911 | J27: 4716 | K27: =+H27/I27*J27 -> 34.11952 | L27: =+H27+K27 -> 84.11952 | M27: 0.3 | N27: =+L27*M27+L27 -> 109.35538 | O27: 180 | P27: 125 | S27: cash returned mabhiza | T27: 45541
B28: nivola | C28: nivola | D28: 26 | E28: 48 | F28: navy chiffon gown w pleated bust | H28: 50 | I28: 6911 | J28: 4716 | K28: =+H28/I28*J28 -> 34.11952 | L28: =+H28+K28 -> 84.11952 | M28: 0.3 | N28: =+L28*M28+L28 -> 109.35538 | O28: 180 | P28: 125
F29: TURKEY TRIP NOV 2022
C30: Donna Miranda | D30: 27 | E30: 46 | F30: gold fishtail | H30: 55 | I30: 4607 | J30: =7503-I30 -> 2896 | K30: =+H30/I30*J30 -> 34.573475 | L30: =+H30+K30 -> 89.573475 | M30: 0.3 | N30: =+L30*M30+L30 -> 116.44552 | O30: 180 | P30: 125
C31: Donna Miranda | D31: 27 | E31: 48 | F31: gold fishtail | H31: 55 | I31: 4607 | J31: =7503-I31 -> 2896 | K31: =+H31/I31*J31 -> 34.573475 | L31: =+H31+K31 -> 89.573475 | M31: 0.3 | N31: =+L31*M31+L31 -> 116.44552 | O31: 180
C32: 9 Aug 2023 temel cargo
C33: nivola | D33: 31 | E33: 44 | F33: nude pleated flared gown | H33: 55 | I33: 440 | J33: =198+20 -> 218 | K33: =+H33/I33*J33 -> 27.25 | L33: =+H33+K33 -> 82.25 | M33: 0.4 | N33: =+L33*1.4 -> 115.15 | O33: 150 | P33: 80
C34: sept. 2023 | F34: GOWNS | I34: 5278
B35: nivola | C35: nivola | D35: 34 | E35: 46 | F35: black stretch gown | H35: 55 | I35: 5278 | J35: 7702 | K35: =+H35/I35*J35 -> 80.259568 | L35: =+H35+K35 -> 135.25957 | M35: 0.4 | N35: =+L35*1.4 -> 189.3634 | O35: 150
B36: nivola | C36: nivola | D36: 35 | E36: 48 | F36: black stretch gown | H36: 55 | I36: 5278 | J36: 7702 | K36: =+H36/I36*J36 -> 80.259568 | L36: =+H36+K36 -> 135.25957 | M36: 0.4 | N36: =+L36*1.4 -> 189.3634 | O36: 150
B37: nivola | C37: nivola | D37: 36 | E37: 50 | F37: black stretch gown | H37: 55 | I37: 5278 | J37: 7702 | K37: =+H37/I37*J37 -> 80.259568 | L37: =+H37+K37 -> 135.25957 | M37: 0.4 | N37: =+L37*1.4 -> 189.3634 | O37: 150
B38: Liza Line | C38: via torino | D38: 38 | E38: 46 | F38: white/ silver ball gown | H38: 65 | I38: 5278 | J38: 7702 | K38: =+H38/I38*J38 -> 94.852217 | L38: =+H38+K38 -> 159.85222 | M38: 0.4 | N38: =+L38*1.4 -> 223.7931 | O38: 180 | P38: 125
C39: 45352
B40: fervente | C40: K | D40: 43 | E40: 42 | F40: gold gown fancy sleeves | H40: 38 | I40: 4192 | J40: 3417 | K40: =+J40/I40*H40 -> 30.974714 | L40: =+H40+K40 -> 68.974714 | M40: 1.4 | N40: =+L40*M40 -> 96.564599 | O40: 125 | P40: 80
B41: fervente | C41: fervente | D41: 44 | E41: 38 | F41: rose gold gown w fancy sleeves | H41: 29 | I41: 4192 | J41: 3417 | K41: =+J41/I41*H41 -> 23.638597 | L41: =+H41+K41 -> 52.638597 | M41: 1.4 | N41: =+L41*M41 -> 73.694036 | O41: 125 | P41: 80
B42: fervente | C42: fervente | D42: 45 | E42: 40 | F42: rose gold gown | H42: 29 | I42: 4192 | J42: 3417 | K42: =+J42/I42*H42 -> 23.638597 | L42: =+H42+K42 -> 52.638597 | M42: 1.4 | N42: =+L42*M42 -> 73.694036 | O42: 125 | P42: 80
B43: fervente | C43: fervente | D43: 46 | E43: 42 | F43: rose gold gown | H43: 29 | I43: 4192 | J43: 3417 | K43: =+J43/I43*H43 -> 23.638597 | L43: =+H43+K43 -> 52.638597 | M43: 1.4 | N43: =+L43*M43 -> 73.694036 | O43: 125 | P43: 80
B44: fiero | C44: ladonatella | D44: 47 | E44: 44 | F44: black /white sheer one arm gown | H44: 68 | I44: 4192 | J44: 3417 | K44: =+J44/I44*H44 -> 55.428435 | L44: =+H44+K44 -> 123.42844 | M44: 1.4 | N44: =+L44*M44 -> 172.79981 | O44: 200 | P44: 125
B45: fiero | C45: ladonatella | D45: 48 | E45: 52 | F45: rose gold gown w front slit & sheer sleeve | H45: 68 | I45: 4192 | J45: 3417 | K45: =+J45/I45*H45 -> 55.428435 | L45: =+H45+K45 -> 123.42844 | M45: 1.4 | N45: =+L45*M45 -> 172.79981 | O45: 200 | P45: 150
C46: ladonatella | F46: gown w one arm | O46: 180 | R46: added 2026 | S46: cash | T46: 46059
F47: JULY '24
C48: ladonatella | D48: 50 | E48: 48 | F48: gold short gown w one arm | H48: 52 | I48: 431 | J48: 120 | K48: =+H48/I48*J48 -> 14.477958 | L48: =+H48+K48 -> 66.477958 | N48: =+L48*1.4 -> 93.069142 | O48: 125 | P48: 90
C49: august '24
C50: LEGENDA | D50: 51 | E50: 52 | F50: rose gold gown with lace upper | H50: 75 | I50: 5000 | J50: 4254 | K50: =+H50/I50*J50 -> 63.81 | L50: =+H50+K50 -> 138.81 | M50: DE | N50: =+L50*1.4 -> 194.334 | O50: 220 | P50: 125
C51: gani | D51: 52 | E51: 56 | F51: beige chiffon dress w front overlay & glitter | H51: 68 | I51: 5000 | J51: 4254 | K51: =+H51/I51*J51 -> 57.8544 | L51: =+H51+K51 -> 125.8544 | N51: =+L51*1.4 -> 176.19616 | O51: 180
C52: gani | D52: 53 | E52: 58 | F52: beige chiffon dress w front overlay & glitter | H52: 68 | I52: 5000 | J52: 4254 | K52: =+H52/I52*J52 -> 57.8544 | L52: =+H52+K52 -> 125.8544 | N52: =+L52*1.4 -> 176.19616 | O52: 180
C53: moda ruj | D53: 55 | E53: 48 | F53: gold gown | H53: 40 | I53: 5000 | J53: 4254 | K53: =+H53/I53*J53 -> 34.032 | L53: =+H53+K53 -> 74.032 | N53: =+L53*1.4 -> 103.6448 | O53: 125 | S53: cash | T53: 46112
C54: moda ruj | D54: 56 | E54: 50 | F54: gold gown | H54: 40 | I54: 5000 | J54: 4254 | K54: =+H54/I54*J54 -> 34.032 | L54: =+H54+K54 -> 74.032 | N54: =+L54*1.4 -> 103.6448 | O54: 125
C55: moda ruj | D55: 57 | E55: 52 | F55: gold gown | H55: 40 | I55: 5000 | J55: 4254 | K55: =+H55/I55*J55 -> 34.032 | L55: =+H55+K55 -> 74.032 | N55: =+L55*1.4 -> 103.6448 | O55: 125
C56: april 2025.
C57: MORE | E57: xxl | F57: Green brocade sleeveless gown w flowers | H57: 41 | I57: 1090 | J57: 1099 | K57: =+H57/I57*J57 -> 41.338532 | L57: =+H57+K57 -> 82.338532 | N57: =+L57*1.4 -> 115.27394 | O57: 150 | P57: 125 | S57: cash | T57: 46106
C58: MORE | E58: 4xl | F58: Green brocade gown w flowers | H58: 41 | I58: 1090 | J58: 1099 | K58: =+H58/I58*J58 -> 41.338532 | L58: =+H58+K58 -> 82.338532 | N58: =+L58*1.4 -> 115.27394 | O58: 180 | S58: layby mapotsa | T58: 46042
C59: MORE | E59: 5xl | F59: gold brocade gown w sleeves &flowers | H59: 41 | I59: 1090 | J59: 1099 | K59: =+H59/I59*J59 -> 41.338532 | L59: =+H59+K59 -> 82.338532 | N59: =+L59*1.4 -> 115.27394 | O59: 150 | S59: cash | T59: 46129
C60: MORE | E60: xl | F60: gold brocade gown w flowers sleeveless | H60: 41 | I60: 1090 | J60: 1099 | K60: =+H60/I60*J60 -> 41.338532 | L60: =+H60+K60 -> 82.338532 | N60: =+L60*1.4 -> 115.27394 | O60: 150 | S60: jaricha layby | T60: 46094
C61: MAY 2025.
C62: NIVOLA | F62: gold gown w waist flower | H62: 55 | I62: 6149 | J62: =5832-600 -> 5232 | K62: =+H62/I62*J62 -> 46.797853 | L62: =+H62+K62 -> 101.79785 | N62: =+L62*1.4 -> 142.51699 | O62: 250 | P62: 150 | S62: layby njagu | T62: 46081
C63: NIVOLA | F63: gold gown w waist flower | H63: 55 | I63: 6149 | J63: =5832-600 -> 5232 | K63: =+H63/I63*J63 -> 46.797853 | L63: =+H63+K63 -> 101.79785 | N63: =+L63*1.4 -> 142.51699 | O63: 250 | P63: 150 | S63: cash | T63: 46087
C64: NIVOLA | F64: gold gown w waist flower | H64: 55 | I64: 6149 | J64: =5832-600 -> 5232 | K64: =+H64/I64*J64 -> 46.797853 | L64: =+H64+K64 -> 101.79785 | N64: =+L64*1.4 -> 142.51699 | O64: 250 | P64: 150
C65: NIVOLA | F65: gold gown w waist flower | H65: 55 | I65: 6149 | J65: =5832-600 -> 5232 | K65: =+H65/I65*J65 -> 46.797853 | L65: =+H65+K65 -> 101.79785 | N65: =+L65*1.4 -> 142.51699 | O65: 250 | P65: 150
C66: NIVOLA | F66: pink gown w waist flower | H66: 55 | I66: 6149 | J66: =5832-600 -> 5232 | K66: =+H66/I66*J66 -> 46.797853 | L66: =+H66+K66 -> 101.79785 | N66: =+L66*1.4 -> 142.51699 | O66: 250 | P66: 150
C67: NIVOLA | F67: pink gown w waist flower | H67: 55 | I67: 6149 | J67: =5832-600 -> 5232 | K67: =+H67/I67*J67 -> 46.797853 | L67: =+H67+K67 -> 101.79785 | N67: =+L67*1.4 -> 142.51699 | O67: 250 | P67: =+H67*3 -> 165
C68: JULY
C69: ladonatella | E69: 44 | F69: green gown w sheer sleeves | H69: 55 | I69: =477*1.05 -> 500.85 | J69: 100 | K69: =+H69/I69*J69 -> 10.981332 | L69: =+H69+K69 -> 65.981332 | N69: =+L69*1.4 -> 92.373864 | O69: 150
C70: ladonatella | E70: 46 | F70: green gown | H70: 55 | I70: =477*1.05 -> 500.85 | J70: 100 | K70: =+H70/I70*J70 -> 10.981332 | L70: =+H70+K70 -> 65.981332 | N70: =+L70*1.4 -> 92.373864 | O70: 150
C71: ladonatella | E71: 48 | F71: green gown | H71: 55 | I71: =477*1.05 -> 500.85 | J71: 100 | K71: =+H71/I71*J71 -> 10.981332 | L71: =+H71+K71 -> 65.981332 | N71: =+L71*1.4 -> 92.373864 | O71: 150
C72: ladonatella | E72: 52 | F72: green gown | H72: 55 | I72: =477*1.05 -> 500.85 | J72: 100 | K72: =+H72/I72*J72 -> 10.981332 | L72: =+H72+K72 -> 65.981332 | N72: =+L72*1.4 -> 92.373864 | O72: 150
C73: ladonatella | E73: 54 | F73: green gown | H73: 55 | I73: =477*1.05 -> 500.85 | J73: 100 | K73: =+H73/I73*J73 -> 10.981332 | L73: =+H73+K73 -> 65.981332 | N73: =+L73*1.4 -> 92.373864 | O73: 150
C74: ladonatella | E74: 56 | F74: green gown | H74: 55 | I74: =477*1.05 -> 500.85 | J74: 100 | K74: =+H74/I74*J74 -> 10.981332 | L74: =+H74+K74 -> 65.981332 | N74: =+L74*1.4 -> 92.373864 | O74: 150
C75: moss fashion | E75: 48 | F75: green gown w lace sleeve & tail | H75: 80 | I75: =320*1.05 -> 336 | J75: 70 | K75: =+H75/I75*J75 -> 16.666667 | L75: =+H75+K75 -> 96.666667 | N75: =+L75*1.4 -> 135.33333 | O75: 150 | S75: cash | T75: 46106
C76: moss fashion | E76: 48 | F76: green gown w tail | H76: 80 | I76: =320*1.05 -> 336 | J76: 70 | K76: =+H76/I76*J76 -> 16.666667 | L76: =+H76+K76 -> 96.666667 | N76: =+L76*1.4 -> 135.33333 | O76: 150 | S76: cash | T76: 46097
C77: moss fashion | E77: 46 | F77: green gown w tail | H77: 80 | I77: =320*1.05 -> 336 | J77: 70 | K77: =+H77/I77*J77 -> 16.666667 | L77: =+H77+K77 -> 96.666667 | N77: =+L77*1.4 -> 135.33333 | O77: 150 | S77: mutimodyo | T77: 46097
C78: moss fashion | E78: 50 | F78: green gown w tail | H78: 80 | I78: =320*1.05 -> 336 | J78: 70 | K78: =+H78/I78*J78 -> 16.666667 | L78: =+H78+K78 -> 96.666667 | N78: =+L78*1.4 -> 135.33333 | O78: 150 | P78: available - my wedding dress
C79: 45901 | L79: =+H79+K79 -> 0 | N79: =+L79*1.4 -> 0
B80: legenda | C80: legenda | E80: 46 | F80: gold pleated dress | H80: 55 | I80: 5225 | J80: 3700 | K80: =+H80/I80*J80 -> 38.947368 | L80: =+H80+K80 -> 93.947368 | N80: =+L80*1.4 -> 131.52632 | O80: 145 | S80: cash | T80: 46095
B81: legenda | C81: legenda | E81: 50 | F81: gold pleated dress | H81: 55 | I81: 5225 | J81: 3700 | K81: =+H81/I81*J81 -> 38.947368 | L81: =+H81+K81 -> 93.947368 | N81: =+L81*1.4 -> 131.52632 | O81: 150 | P81: 150 | S81: cash | T81: 46107
B82: ajar | C82: elita line | E82: 42 | F82: black gown | H82: 30 | I82: 5225 | J82: 3700 | K82: =+H82/I82*J82 -> 21.244019 | L82: =+H82+K82 -> 51.244019 | N82: =+L82*1.4 -> 71.741627 | O82: 125 | P82: 125
B83: modalux | C83: nzambi | E83: 44 | F83: black gown w pink polka dot sleeves | H83: 46 | I83: 5225 | J83: 3700 | K83: =+H83/I83*J83 -> 32.574163 | L83: =+H83+K83 -> 78.574163 | N83: =+L83*1.4 -> 110.00383 | O83: 150 | P83: 125
B84: modalux | C84: nzambi | E84: 46 | F84: black gown w pink polka dot sleeves | H84: 46 | I84: 5225 | J84: 3700 | K84: =+H84/I84*J84 -> 32.574163 | L84: =+H84+K84 -> 78.574163 | N84: =+L84*1.4 -> 110.00383 | O84: 150 | P84: 125
B85: modalux | C85: nzambi | E85: 48 | F85: black gown w pink polka dot sleeves | H85: 46 | I85: 5225 | J85: 3700 | K85: =+H85/I85*J85 -> 32.574163 | L85: =+H85+K85 -> 78.574163 | N85: =+L85*1.4 -> 110.00383 | O85: 150 | P85: 125
B86: modalux | C86: nzambi | E86: 50 | F86: black gown w pink polka dot sleeves | H86: 46 | I86: 5225 | J86: 3700 | K86: =+H86/I86*J86 -> 32.574163 | L86: =+H86+K86 -> 78.574163 | N86: =+L86*1.4 -> 110.00383 | O86: 150 | P86: 125
B87: Orhan | C87: piyamor | E87: 48 | F87: copper gown w pleated sleeve | H87: 55 | I87: 5225 | J87: 3700 | K87: =+H87/I87*J87 -> 38.947368 | L87: =+H87+K87 -> 93.947368 | N87: =+L87*1.4 -> 131.52632 | O87: 150 | P87: 150 | S87: cash | T87: 46094
B88: Orhan | C88: piyamor | E88: 50 | F88: copper gown w pleated sleeve | H88: 55 | I88: 5225 | J88: 3700 | K88: =+H88/I88*J88 -> 38.947368 | L88: =+H88+K88 -> 93.947368 | N88: =+L88*1.4 -> 131.52632 | O88: 150 | P88: 150
B89: DIAZZ | C89: DIAZZ | E89: 40 | F89: black gown | H89: 20 | I89: 5225 | J89: 3700 | K89: =+H89/I89*J89 -> 14.162679 | L89: =+H89+K89 -> 34.162679 | N89: =+L89*1.4 -> 47.827751 | O89: 125 | P89: 80
B90: DIAZZ | C90: DIAZZ | E90: 44 | F90: black gown | H90: 20 | I90: 5225 | J90: 3700 | K90: =+H90/I90*J90 -> 14.162679 | L90: =+H90+K90 -> 34.162679 | N90: =+L90*1.4 -> 47.827751 | O90: 125 | P90: 80 | S90: pastor komichi | T90: 46086
B91: DIAZZ | C91: DIAZZ | E91: 46 | F91: black gown | H91: 20 | I91: 5225 | J91: 3700 | K91: =+H91/I91*J91 -> 14.162679 | L91: =+H91+K91 -> 34.162679 | N91: =+L91*1.4 -> 47.827751 | O91: 125 | P91: 80
B92: DIAZZ | C92: DIAZZ | E92: 46 | F92: black gown | H92: 20 | I92: 5225 | J92: 3700 | K92: =+H92/I92*J92 -> 14.162679 | L92: =+H92+K92 -> 34.162679 | N92: =+L92*1.4 -> 47.827751 | O92: 125 | P92: 80 | S92: returned in stock. Purchase made by mai Ushe 2025
B93: fervents | C93: K | E93: 42 | F93: black short gown with boob top | H93: 41 | I93: 5225 | J93: 3700 | K93: =+H93/I93*J93 -> 29.033493 | L93: =+H93+K93 -> 70.033493 | N93: =+L93*1.4 -> 98.04689 | O93: 125 | P93: 125
B94: fervents | C94: K | E94: 44 | F94: black short gown with boob top | H94: 41 | I94: 5225 | J94: 3700 | K94: =+H94/I94*J94 -> 29.033493 | L94: =+H94+K94 -> 70.033493 | N94: =+L94*1.4 -> 98.04689 | O94: 125 | P94: 125
B95: fervents | C95: K | E95: 46 | F95: black short gown with boob top | H95: 41 | I95: 5225 | J95: 3700 | K95: =+H95/I95*J95 -> 29.033493 | L95: =+H95+K95 -> 70.033493 | N95: =+L95*1.4 -> 98.04689 | O95: 125 | P95: 125
B96: fervents | C96: fervente | E96: 36 | F96: coffee long gown | H96: 35 | I96: 5225 | J96: 3700 | K96: =+H96/I96*J96 -> 24.784689 | L96: =+H96+K96 -> 59.784689 | N96: =+L96*1.4 -> 83.698565 | O96: 125 | S96: cash | T96: 46081
B97: fervents | E97: 38 | F97: coffee long gown | H97: 35 | I97: 5225 | J97: 3700 | K97: =+H97/I97*J97 -> 24.784689 | L97: =+H97+K97 -> 59.784689 | N97: =+L97*1.4 -> 83.698565 | O97: 125 | P97: 125
C98: china nov 2025
C99: MORE liuha | F99: GOLD BROCADE GOWN W OFF SHOULDER DESIGN | H99: 280 | I99: =+H99/7 -> 40 | J99: 4072 | K99: 3073 | L99: =+I99/J99*K99 -> 30.18664 | M99: =+I99+L99 -> 70.18664 | O99: =+M99*1.5 -> 105.27996 | P99: 150
C100: MORE liuha | E100: 3XL | F100: black brocade dress w pink flowers | H100: 280 | I100: =+H100/7 -> 40 | J100: 4072 | K100: 3073 | L100: =+I100/J100*K100 -> 30.18664 | M100: =+I100+L100 -> 70.18664 | O100: =+M100*1.5 -> 105.27996 | P100: 150 | S100: cash | T100: 46107
...

Sheet jkts & jerserys
B1: SHOP | C1: LABEL | D1: Q | E1: size | F1: Item | G1: pur price | H1: total purchase price | I1: total cost | J1: Indirect Cost / unit | K1: Total Unit Cost | L1: Multiplier | M1: recommended | N1: Actual Price | O1: SALE | P1: S/T JAN '25 | Q1: status | R1: date | S1: sales
F2: JACKETS | M2: =+K2*L2+K2 -> 0
C3: MAY 2019 STOCK | M3: =+K3*L3+K3 -> 0
C4: haza | D4: 5 | E4: 40 | F4: scotch w pocket design | G4: 12 | H4: 8277 | I4: 15182 | J4: =+G4/H4*I4 -> 22.010874 | K4: =+G4+J4 -> 34.010874 | L4: 0.3 | M4: =+K4*L4+K4 -> 44.214136 | N4: 65 | Q4: from avondale
C5: haza | D5: 6 | E5: 46 | F5: scotch w pocket design | G5: 12 | H5: 8277 | I5: 15182 | J5: =+G5/H5*I5 -> 22.010874 | K5: =+G5+J5 -> 34.010874 | L5: 0.3 | M5: =+K5*L5+K5 -> 44.214136 | N5: 65 | Q5: from avondale
C6: gossi/ trieste | D6: 7 | E6: 52 | F6: denim jacket big size | G6: 20 | H6: 787 | I6: =787+388+40+47 -> 1262 | J6: =+G6/H6*I6 -> 32.071156 | K6: =+G6+J6 -> 52.071156 | L6: 0.3 | M6: =+K6*L6+K6 -> 67.692503 | N6: 65
F7: may 2023 stock
B8: white moon | C8: ravir | D8: 10 | E8: 40 | F8: grey/white houndstooth blazer | G8: 25 | H8: 9682 | I8: 7766 | J8: =+G8/H8*I8 -> 20.052675 | K8: =+G8+J8 -> 45.052675 | L8: 0.4 | M8: =+K8*1.4 -> 63.073745 | N8: 100 | Q8: home
B9: white moon | C9: ravir | D9: 11 | E9: 42 | F9: grey/white houndstooth blazer | G9: 25 | H9: 9682 | I9: 7766 | J9: =+G9/H9*I9 -> 20.052675 | K9: =+G9+J9 -> 45.052675 | L9: 0.4 | M9: =+K9*1.4 -> 63.073745 | N9: 100
B10: white moon | C10: ravir | D10: 13 | E10: 38 | F10: blue/white scotch blazer | G10: 25 | H10: 9682 | I10: 7766 | J10: =+G10/H10*I10 -> 20.052675 | K10: =+G10+J10 -> 45.052675 | L10: 0.4 | M10: =+K10*1.4 -> 63.073745 | N10: 100 | Q10: from avondale to home to shop april
B11: white moon | C11: ravir | D11: 14 | E11: 42 | F11: blue/white scotch blazer | G11: 25 | H11: 9682 | I11: 7766 | J11: =+G11/H11*I11 -> 20.052675 | K11: =+G11+J11 -> 45.052675 | L11: 0.4 | M11: =+K11*1.4 -> 63.073745 | N11: 100
B12: roda | C12: roda | D12: 18 | E12: 42 | F12: black short velvet | G12: 35 | H12: 9682 | I12: 7766 | J12: =+G12/H12*I12 -> 28.073745 | K12: =+G12+J12 -> 63.073745 | L12: 0.4 | M12: =+K12*1.4 -> 88.303243 | N12: 125 | Q12: home
B13: roda | C13: roda | D13: 20 | E13: 50 | F13: black short velvet | G13: 35 | H13: 9682 | I13: 7766 | J13: =+G13/H13*I13 -> 28.073745 | K13: =+G13+J13 -> 63.073745 | L13: 0.4 | M13: =+K13*1.4 -> 88.303243 | N13: 125 | Q13: home
C14: may 2025. | F14: roda layby may 2025.
C15: RODA/ SIMODA | E15: 46 | F15: black/beige houndstooth jacket | G15: 23 | H15: 814 | I15: 584 | J15: =+G15/H15*I15 -> 16.501229 | K15: =+G15+J15 -> 39.501229 | M15: =+K15*1.4 -> 55.30172 | N15: 65 | Q15: home
C16: RODA/ SIMODA | E16: 50 | F16: black/beige houndstooth jacket | G16: 23 | H16: 814 | I16: 584 | J16: =+G16/H16*I16 -> 16.501229 | K16: =+G16+J16 -> 39.501229 | M16: =+K16*1.4 -> 55.30172 | N16: 65 | Q16: home
C17: RODA/ SIMODA | E17: 52 | F17: black/beige houndstooth jacket | G17: 23 | H17: 814 | I17: 584 | J17: =+G17/H17*I17 -> 16.501229 | K17: =+G17+J17 -> 39.501229 | M17: =+K17*1.4 -> 55.30172 | N17: 65 | Q17: home cash | R17: 46104
C18: RODA/ SIMODA | E18: 42 | F18: black/beige houndstooth jacket | G18: 23 | H18: 814 | I18: 584 | J18: =+G18/H18*I18 -> 16.501229 | K18: =+G18+J18 -> 39.501229 | M18: =+K18*1.4 -> 55.30172 | N18: 65 | Q18: home
C19: RODA/ SIMODA | E19: 44 | F19: black/beige houndstooth jacket | G19: 23 | H19: 814 | I19: 584 | J19: =+G19/H19*I19 -> 16.501229 | K19: =+G19+J19 -> 39.501229 | M19: =+K19*1.4 -> 55.30172 | N19: 65 | Q19: home
C20: RODA/ SIMODA | E20: 46 | F20: black/beige houndstooth jacket | G20: 23 | H20: 814 | I20: 584 | J20: =+G20/H20*I20 -> 16.501229 | K20: =+G20+J20 -> 39.501229 | M20: =+K20*1.4 -> 55.30172 | N20: 65 | Q20: home
C21: RODA/ SIMODA | E21: 48 | F21: black/beige houndstooth jacket | G21: 23 | H21: 814 | I21: 584 | J21: =+G21/H21*I21 -> 16.501229 | K21: =+G21+J21 -> 39.501229 | M21: =+K21*1.4 -> 55.30172 | N21: 65 | Q21: home
C22: RODA/ SIMODA | E22: 50 | F22: black/beige houndstooth jacket | G22: 23 | H22: 814 | I22: 584 | J22: =+G22/H22*I22 -> 16.501229 | K22: =+G22+J22 -> 39.501229 | M22: =+K22*1.4 -> 55.30172 | N22: 65 | Q22: home - cash | R22: 46119
C23: RODA/ SIMODA | E23: 52 | F23: black/beige houndstooth jacket | G23: 23 | H23: 814 | I23: 584 | J23: =+G23/H23*I23 -> 16.501229 | K23: =+G23+J23 -> 39.501229 | M23: =+K23*1.4 -> 55.30172 | N23: 65 | Q23: home
C24: RODA/ SIMODA | E24: 50 | F24: navy double breast trench coat | G24: 23 | H24: 814 | I24: 584 | J24: =+G24/H24*I24 -> 16.501229 | K24: =+G24+J24 -> 39.501229 | M24: =+K24*1.4 -> 55.30172 | N24: 125 | Q24: home
C25: RODA/ SIMODA | E25: 52 | F25: navy double breast trench coat | G25: 23 | H25: 814 | I25: 584 | J25: =+G25/H25*I25 -> 16.501229 | K25: =+G25+J25 -> 39.501229 | M25: =+K25*1.4 -> 55.30172 | N25: 125 | Q25: home
C26: RODA/ SIMODA | E26: 54 | F26: navy double breast trench coat | G26: 23 | H26: 814 | I26: 584 | J26: =+G26/H26*I26 -> 16.501229 | K26: =+G26+J26 -> 39.501229 | M26: =+K26*1.4 -> 55.30172 | N26: 125 | Q26: home
C27: RODA/ SIMODA | E27: 56 | F27: navy double breast trench coat | G27: 23 | H27: 814 | I27: 584 | J27: =+G27/H27*I27 -> 16.501229 | K27: =+G27+J27 -> 39.501229 | M27: =+K27*1.4 -> 55.30172 | N27: 125 | Q27: home
C28: RODA/ SIMODA | E28: 50 | F28: black double breast trench coat | G28: 23 | H28: 814 | I28: 584 | J28: =+G28/H28*I28 -> 16.501229 | K28: =+G28+J28 -> 39.501229 | M28: =+K28*1.4 -> 55.30172 | N28: 125 | Q28: home
C29: RODA/ SIMODA | E29: 52 | F29: black double breast trench coat | G29: 23 | H29: 814 | I29: 584 | J29: =+G29/H29*I29 -> 16.501229 | K29: =+G29+J29 -> 39.501229 | M29: =+K29*1.4 -> 55.30172 | N29: 125 | Q29: home
C30: RODA/ SIMODA | E30: 54 | F30: black double breast trench coat | G30: 23 | H30: 814 | I30: 584 | J30: =+G30/H30*I30 -> 16.501229 | K30: =+G30+J30 -> 39.501229 | M30: =+K30*1.4 -> 55.30172 | N30: 125 | Q30: home
C31: RODA/ SIMODA | E31: 52 | F31: beige double breast trench coat | G31: 23 | H31: 814 | I31: 584 | J31: =+G31/H31*I31 -> 16.501229 | K31: =+G31+J31 -> 39.501229 | M31: =+K31*1.4 -> 55.30172 | N31: 125 | Q31: home
C32: RODA/ SIMODA | E32: 52 | F32: beige double breast trench coat | G32: 23 | H32: 814 | I32: 584 | J32: =+G32/H32*I32 -> 16.501229 | K32: =+G32+J32 -> 39.501229 | M32: =+K32*1.4 -> 55.30172 | N32: 125 | Q32: home
C33: RODA/ SIMODA | E33: 52 | F33: beige/black 3/4 trench coat with hood | G33: 40 | H33: 814 | I33: 584 | J33: =+G33/H33*I33 -> 28.697789 | K33: =+G33+J33 -> 68.697789 | M33: =+K33*1.4 -> 96.176904 | N33: 125 | Q33: home
C34: RODA/ SIMODA | E34: 54 | F34: beige/black 3/4 trench coat with hood | G34: 40 | H34: 814 | I34: 584 | J34: =+G34/H34*I34 -> 28.697789 | K34: =+G34+J34 -> 68.697789 | M34: =+K34*1.4 -> 96.176904 | N34: 125 | Q34: home
C35: RODA/ SIMODA | E35: 56 | F35: beige/black 3/4 trench coat with hood | G35: 40 | H35: 814 | I35: 584 | J35: =+G35/H35*I35 -> 28.697789 | K35: =+G35+J35 -> 68.697789 | M35: =+K35*1.4 -> 96.176904 | N35: 125 | Q35: home
C36: marifel | E36: L | F36: H & M collection coffee reversible thick coat | G36: 35 | H36: 1304 | I36: 580 | J36: =+G36/H36*I36 -> 15.567485 | K36: =+G36+J36 -> 50.567485 | M36: =+K36*1.4 -> 70.794479 | N36: 120 | Q36: home
C37: marifel | E37: XL | F37: H & M collection coffee reversible thick coat | G37: 35 | H37: 1304 | I37: 580 | J37: =+G37/H37*I37 -> 15.567485 | K37: =+G37+J37 -> 50.567485 | M37: =+K37*1.4 -> 70.794479 | N37: 120 | Q37: home
C38: marifel | E38: L | F38: HSM textile burberry navy 3/4 quilted jacket | G38: 25 | H38: 1304 | I38: 580 | J38: =+G38/H38*I38 -> 11.119632 | K38: =+G38+J38 -> 36.119632 | M38: =+K38*1.4 -> 50.567485 | N38: 100 | Q38: home
C39: marifel | E39: XL | F39: HSM textile burberry navy 3/4 quilted jacket | G39: 25 | H39: 1304 | I39: 580 | J39: =+G39/H39*I39 -> 11.119632 | K39: =+G39+J39 -> 36.119632 | M39: =+K39*1.4 -> 50.567485 | N39: 100 | Q39: home
C40: marifel | E40: 2XL | F40: HSM textile burberry navy 3/4 quilted jacket | G40: 25 | H40: 1304 | I40: 580 | J40: =+G40/H40*I40 -> 11.119632 | K40: =+G40+J40 -> 36.119632 | M40: =+K40*1.4 -> 50.567485 | N40: 100 | Q40: home
C41: marifel | E41: 3XL | F41: HSM textile burberry navy 3/4 quilted jacket | G41: 25 | H41: 1304 | I41: 580 | J41: =+G41/H41*I41 -> 11.119632 | K41: =+G41+J41 -> 36.119632 | M41: =+K41*1.4 -> 50.567485 | N41: 100 | Q41: home
C42: marifel | E42: 4XL | F42: HSM textile burberry navy 3/4 quilted jacket | G42: 25 | H42: 1304 | I42: 580 | J42: =+G42/H42*I42 -> 11.119632 | K42: =+G42+J42 -> 36.119632 | M42: =+K42*1.4 -> 50.567485 | N42: 100 | Q42: home
C43: marifel | E43: L | F43: HSM textile burberry black 3/4 quilted jacket | G43: 25 | H43: 1304 | I43: 580 | J43: =+G43/H43*I43 -> 11.119632 | K43: =+G43+J43 -> 36.119632 | M43: =+K43*1.4 -> 50.567485 | N43: 100 | Q43: layby chaniwa returned home | R43: 45827
C44: marifel | E44: XL | F44: HSM textile burberry black 3/4 quilted jacket | G44: 25 | H44: 1304 | I44: 580 | J44: =+G44/H44*I44 -> 11.119632 | K44: =+G44+J44 -> 36.119632 | M44: =+K44*1.4 -> 50.567485 | N44: 100 | Q44: home
C45: marifel | E45: 2XL | F45: HSM textile burberry black 3/4 quilted jacket | G45: 25 | H45: 1304 | I45: 580 | J45: =+G45/H45*I45 -> 11.119632 | K45: =+G45+J45 -> 36.119632 | M45: =+K45*1.4 -> 50.567485 | N45: 100 | Q45: home
C46: marifel | E46: 3XL | F46: HSM textile burberry black 3/4 quilted jacket | G46: 25 | H46: 1304 | I46: 580 | J46: =+G46/H46*I46 -> 11.119632 | K46: =+G46+J46 -> 36.119632 | M46: =+K46*1.4 -> 50.567485 | N46: 100 | Q46: home
C47: marifel | E47: 4XL | F47: HSM textile burberry black 3/4 quilted jacket | G47: 25 | H47: 1304 | I47: 580 | J47: =+G47/H47*I47 -> 11.119632 | K47: =+G47+J47 -> 36.119632 | M47: =+K47*1.4 -> 50.567485 | N47: 100 | Q47: home
C48: marifel | E48: 5XL | F48: HSM textile burberry black 3/4 quilted jacket | G48: 25 | H48: 1304 | I48: 580 | J48: =+G48/H48*I48 -> 11.119632 | K48: =+G48+J48 -> 36.119632 | M48: =+K48*1.4 -> 50.567485 | N48: 100 | Q48: home
C49: aloha | E49: L | F49: HSM textile burberry BEIGE SHORT quilted jacket | G49: 22 | H49: 1304 | I49: 580 | J49: =+G49/H49*I49 -> 9.7852761 | K49: =+G49+J49 -> 31.785276 | M49: =+K49*1.4 -> 44.499387 | N49: 75 | Q49: home
C50: aloha | E50: 2XL | F50: HSM textile burberry BEIGE SHORT quilted jacket | G50: 22 | H50: 1304 | I50: 580 | J50: =+G50/H50*I50 -> 9.7852761 | K50: =+G50+J50 -> 31.785276 | M50: =+K50*1.4 -> 44.499387 | N50: 75 | Q50: home - cash | R50: 46112
C51: aloha | E51: 3XL | F51: HSM textile burberry BEIGE SHORT quilted jacket | G51: 22 | H51: 1304 | I51: 580 | J51: =+G51/H51*I51 -> 9.7852761 | K51: =+G51+J51 -> 31.785276 | M51: =+K51*1.4 -> 44.499387 | N51: 75 | Q51: home
C52: aloha | E52: 4XL | F52: HSM textile burberry BEIGE SHORT quilted jacket | G52: 22 | H52: 1304 | I52: 580 | J52: =+G52/H52*I52 -> 9.7852761 | K52: =+G52+J52 -> 31.785276 | M52: =+K52*1.4 -> 44.499387 | N52: 75 | Q52: home
C53: aloha | E53: 48 | F53: SHOWCASE black sleeveless quilted jkt w fur neck | G53: 40 | H53: 1304 | I53: 580 | J53: =+G53/H53*I53 -> 17.791411 | K53: =+G53+J53 -> 57.791411 | M53: =+K53*1.4 -> 80.907975 | N53: 120 | Q53: home
C54: aloha | E54: 50 | F54: SHOWCASE black sleeveless quilted jkt w fur neck | G54: 40 | H54: 1304 | I54: 580 | J54: =+G54/H54*I54 -> 17.791411 | K54: =+G54+J54 -> 57.791411 | M54: =+K54*1.4 -> 80.907975 | N54: 120 | Q54: home
C55: aloha | E55: 50 | F55: SHOWCASE beige sleeveless quilted jkt w fur neck | G55: 40 | H55: 1304 | I55: 580 | J55: =+G55/H55*I55 -> 17.791411 | K55: =+G55+J55 -> 57.791411 | M55: =+K55*1.4 -> 80.907975 | N55: 120 | Q55: home
F56: china sea cargo march 2026
C57: china | D57: china | E57: 3xl | F57: long houndstooth jacket | G57: 15 | H57: 15 | I57: 680 | J57: 160 | K57: =+H57/I57*J57 -> 3.5294118 | L57: =+H57+K57 -> 18.529412 | O57: =+L57*1.5 -> 27.794118 | P57: 60 | Q57: baba abisha | R57: 46141
C58: china | D58: china | E58: 3xl | F58: long houndstooth jacket | H58: 15 | I58: 680 | J58: 160 | K58: =+H58/I58*J58 -> 3.5294118 | L58: =+H58+K58 -> 18.529412 | O58: =+L58*1.5 -> 27.794118 | P58: 60
C59: china | D59: china | E59: 3xl | F59: long houndstooth jacket | H59: 15 | I59: 680 | J59: 160 | K59: =+H59/I59*J59 -> 3.5294118 | L59: =+H59+K59 -> 18.529412 | O59: =+L59*1.5 -> 27.794118 | P59: 60
C60: china | D60: china | E60: 4xl | F60: long houndstooth jacket | H60: 15 | I60: 680 | J60: 160 | K60: =+H60/I60*J60 -> 3.5294118 | L60: =+H60+K60 -> 18.529412 | O60: =+L60*1.5 -> 27.794118 | P60: 60
C61: china | D61: china | E61: 4xl | F61: long houndstooth jacket | H61: 15 | I61: 680 | J61: 160 | K61: =+H61/I61*J61 -> 3.5294118 | L61: =+H61+K61 -> 18.529412 | O61: =+L61*1.5 -> 27.794118 | P61: 60
C62: china | D62: china | E62: 4xl | F62: long houndstooth jacket | H62: 15 | I62: 680 | J62: 160 | K62: =+H62/I62*J62 -> 3.5294118 | L62: =+H62+K62 -> 18.529412 | O62: =+L62*1.5 -> 27.794118 | P62: 60
C63: china | D63: china | E63: 5xl | F63: long houndstooth jacket | H63: 15 | I63: 680 | J63: 160 | K63: =+H63/I63*J63 -> 3.5294118 | L63: =+H63+K63 -> 18.529412 | O63: =+L63*1.5 -> 27.794118 | P63: 60 | Q63: cash | R63: 46139
C64: china | D64: china | E64: 5xl | F64: long houndstooth jacket | H64: 15 | I64: 680 | J64: 160 | K64: =+H64/I64*J64 -> 3.5294118 | L64: =+H64+K64 -> 18.529412 | O64: =+L64*1.5 -> 27.794118 | P64: 60
C65: china | D65: china | E65: 5xl | F65: long houndstooth jacket | H65: 15 | I65: 680 | J65: 160 | K65: =+H65/I65*J65 -> 3.5294118 | L65: =+H65+K65 -> 18.529412 | O65: =+L65*1.5 -> 27.794118 | P65: 60
C66: china | D66: china | E66: 6xl | F66: long houndstooth jacket | H66: 15 | I66: 680 | J66: 160 | K66: =+H66/I66*J66 -> 3.5294118 | L66: =+H66+K66 -> 18.529412 | O66: =+L66*1.5 -> 27.794118 | P66: 60 | Q66: cash | R66: 46119
C67: china | D67: china | E67: 6xl | F67: long houndstooth jacket | H67: 15 | I67: 680 | J67: 160 | K67: =+H67/I67*J67 -> 3.5294118 | L67: =+H67+K67 -> 18.529412 | O67: =+L67*1.5 -> 27.794118 | P67: 60
C68: china | D68: china | E68: 6xl | F68: long houndstooth jacket | H68: 15 | I68: 680 | J68: 160 | K68: =+H68/I68*J68 -> 3.5294118 | L68: =+H68+K68 -> 18.529412 | O68: =+L68*1.5 -> 27.794118 | P68: 60
C69: china | D69: china | E69: 7xl | F69: long houndstooth jacket | H69: 15 | I69: 680 | J69: 160 | K69: =+H69/I69*J69 -> 3.5294118 | L69: =+H69+K69 -> 18.529412 | O69: =+L69*1.5 -> 27.794118 | P69: 60
C70: china | D70: china | E70: 7xl | F70: long houndstooth jacket | H70: 15 | I70: 680 | J70: 160 | K70: =+H70/I70*J70 -> 3.5294118 | L70: =+H70+K70 -> 18.529412 | O70: =+L70*1.5 -> 27.794118 | P70: 60
C71: china | D71: china | E71: 7xl | F71: long houndstooth jacket | H71: 15 | I71: 680 | J71: 160 | K71: =+H71/I71*J71 -> 3.5294118 | L71: =+H71+K71 -> 18.529412 | O71: =+L71*1.5 -> 27.794118 | P71: 60
C72: china | D72: china | E72: 3xl | F72: short houndstooth jacket | H72: 11 | I72: 680 | J72: 160 | K72: =+H72/I72*J72 -> 2.5882353 | L72: =+H72+K72 -> 13.588235 | O72: =+L72*1.5 -> 20.382353 | P72: 50 | Q72: cash | R72: 46113
C73: china | D73: china | E73: 3xl | F73: short houndstooth jacket | H73: 11 | I73: 680 | J73: 160 | K73: =+H73/I73*J73 -> 2.5882353 | L73: =+H73+K73 -> 13.588235 | O73: =+L73*1.5 -> 20.382353 | P73: 50
C74: china | D74: china | E74: 3xl | F74: short houndstooth jacket | H74: 11 | I74: 680 | J74: 160 | K74: =+H74/I74*J74 -> 2.5882353 | L74: =+H74+K74 -> 13.588235 | O74: =+L74*1.5 -> 20.382353 | P74: 50
C75: china | D75: china | E75: 4xl | F75: short houndstooth jacket | H75: 11 | I75: 680 | J75: 160 | K75: =+H75/I75*J75 -> 2.5882353 | L75: =+H75+K75 -> 13.588235 | O75: =+L75*1.5 -> 20.382353 | P75: 50 | Q75: cash | R75: 46114
C76: china | D76: china | E76: 4xl | F76: short houndstooth jacket | H76: 11 | I76: 680 | J76: 160 | K76: =+H76/I76*J76 -> 2.5882353 | L76: =+H76+K76 -> 13.588235 | O76: =+L76*1.5 -> 20.382353 | P76: 50 | Q76: mai govhati | R76: 46140
C77: china | D77: china | E77: 4xl | F77: short houndstooth jacket | H77: 11 | I77: 680 | J77: 160 | K77: =+H77/I77*J77 -> 2.5882353 | L77: =+H77+K77 -> 13.588235 | O77: =+L77*1.5 -> 20.382353 | P77: 50
C78: china | D78: china | E78: 5xl | F78: short houndstooth jacket | H78: 11 | I78: 680 | J78: 160 | K78: =+H78/I78*J78 -> 2.5882353 | L78: =+H78+K78 -> 13.588235 | O78: =+L78*1.5 -> 20.382353 | P78: 50
C79: china | D79: china | E79: 5xl | F79: short houndstooth jacket | H79: 11 | I79: 680 | J79: 160 | K79: =+H79/I79*J79 -> 2.5882353 | L79: =+H79+K79 -> 13.588235 | O79: =+L79*1.5 -> 20.382353 | P79: 50
C80: china | D80: china | E80: 5xl | F80: short houndstooth jacket | H80: 11 | I80: 680 | J80: 160 | K80: =+H80/I80*J80 -> 2.5882353 | L80: =+H80+K80 -> 13.588235 | O80: =+L80*1.5 -> 20.382353 | P80: 50
C81: china | D81: china | E81: 6xl | F81: short houndstooth jacket | H81: 11 | I81: 680 | J81: 160 | K81: =+H81/I81*J81 -> 2.5882353 | L81: =+H81+K81 -> 13.588235 | O81: =+L81*1.5 -> 20.382353 | P81: 50
C82: china | D82: china | E82: 6xl | F82: short houndstooth jacket | H82: 11 | I82: 680 | J82: 160 | K82: =+H82/I82*J82 -> 2.5882353 | L82: =+H82+K82 -> 13.588235 | O82: =+L82*1.5 -> 20.382353 | P82: 50
C83: china | D83: china | E83: 6xl | F83: short houndstooth jacket | H83: 11 | I83: 680 | J83: 160 | K83: =+H83/I83*J83 -> 2.5882353 | L83: =+H83+K83 -> 13.588235 | O83: =+L83*1.5 -> 20.382353 | P83: 50
C84: china | D84: china | E84: 7xl | F84: short houndstooth jacket | H84: 11 | I84: 680 | J84: 160 | K84: =+H84/I84*J84 -> 2.5882353 | L84: =+H84+K84 -> 13.588235 | O84: =+L84*1.5 -> 20.382353 | P84: 50 | Q84: cash | R84: 46114
C85: china | D85: china | E85: 7xl | F85: short houndstooth jacket | H85: 11 | I85: 680 | J85: 160 | K85: =+H85/I85*J85 -> 2.5882353 | L85: =+H85+K85 -> 13.588235 | O85: =+L85*1.5 -> 20.382353 | P85: 50
C86: china | D86: china | E86: 7xl | F86: short houndstooth jacket | H86: 11 | I86: 680 | J86: 160 | K86: =+H86/I86*J86 -> 2.5882353 | L86: =+H86+K86 -> 13.588235 | O86: =+L86*1.5 -> 20.382353 | P86: 50
C87: china | D87: china | E87: 3xl | F87: long brown scotch jacket | H87: 15 | I87: 680 | J87: 160 | K87: =+H87/I87*J87 -> 3.5294118 | L87: =+H87+K87 -> 18.529412 | O87: =+L87*1.5 -> 27.794118 | P87: 60
C88: china | D88: china | E88: 3xl | F88: long brown scotch jacket | H88: 15 | I88: 680 | J88: 160 | K88: =+H88/I88*J88 -> 3.5294118 | L88: =+H88+K88 -> 18.529412 | O88: =+L88*1.5 -> 27.794118 | P88: 60
C89: china | D89: china | E89: 3xl | F89: long brown scotch jacket | H89: 15 | I89: 680 | J89: 160 | K89: =+H89/I89*J89 -> 3.5294118 | L89: =+H89+K89 -> 18.529412 | O89: =+L89*1.5 -> 27.794118 | P89: 60
C90: china | D90: china | E90: 4xl | F90: long brown scotch jacket | H90: 15 | I90: 680 | J90: 160 | K90: =+H90/I90*J90 -> 3.5294118 | L90: =+H90+K90 -> 18.529412 | O90: =+L90*1.5 -> 27.794118 | P90: 60
C91: china | D91: china | E91: 4xl | F91: long brown scotch jacket | H91: 15 | I91: 680 | J91: 160 | K91: =+H91/I91*J91 -> 3.5294118 | L91: =+H91+K91 -> 18.529412 | O91: =+L91*1.5 -> 27.794118 | P91: 60
C92: china | D92: china | E92: 4xl | F92: long brown scotch jacket | H92: 15 | I92: 680 | J92: 160 | K92: =+H92/I92*J92 -> 3.5294118 | L92: =+H92+K92 -> 18.529412 | O92: =+L92*1.5 -> 27.794118 | P92: 60
C93: china | D93: china | E93: 5xl | F93: long brown scotch jacket | H93: 15 | I93: 680 | J93: 160 | K93: =+H93/I93*J93 -> 3.5294118 | L93: =+H93+K93 -> 18.529412 | O93: =+L93*1.5 -> 27.794118 | P93: 60 | Q93: cash | R93: 46114
C94: china | D94: china | E94: 5xl | F94: long brown scotch jacket | H94: 15 | I94: 680 | J94: 160 | K94: =+H94/I94*J94 -> 3.5294118 | L94: =+H94+K94 -> 18.529412 | O94: =+L94*1.5 -> 27.794118 | P94: 60 | Q94: cash | R94: 46119
C95: china | D95: china | E95: 5xl | F95: long brown scotch jacket | H95: 15 | I95: 680 | J95: 160 | K95: =+H95/I95*J95 -> 3.5294118 | L95: =+H95+K95 -> 18.529412 | O95: =+L95*1.5 -> 27.794118 | P95: 60
C96: china | D96: china | E96: 6xl | F96: long brown scotch jacket | H96: 15 | I96: 680 | J96: 160 | K96: =+H96/I96*J96 -> 3.5294118 | L96: =+H96+K96 -> 18.529412 | O96: =+L96*1.5 -> 27.794118 | P96: 60 | Q96: cash | R96: 46114
C97: china | D97: china | E97: 6xl | F97: long brown scotch jacket | H97: 15 | I97: 680 | J97: 160 | K97: =+H97/I97*J97 -> 3.5294118 | L97: =+H97+K97 -> 18.529412 | O97: =+L97*1.5 -> 27.794118 | P97: 60 | Q97: cash | R97: 46114
C98: china | D98: china | E98: 6xl | F98: long brown scotch jacket | H98: 15 | I98: 680 | J98: 160 | K98: =+H98/I98*J98 -> 3.5294118 | L98: =+H98+K98 -> 18.529412 | O98: =+L98*1.5 -> 27.794118 | P98: 60 | Q98: cash | R98: 46136
C99: china | D99: china | E99: 7xl | F99: long brown scotch jacket | H99: 15 | I99: 680 | J99: 160 | K99: =+H99/I99*J99 -> 3.5294118 | L99: =+H99+K99 -> 18.529412 | O99: =+L99*1.5 -> 27.794118 | P99: 60 | Q99: cash | R99: 46115
C100: china | D100: china | E100: 7xl | F100: long brown scotch jacket | H100: 15 | I100: 680 | J100: 160 | K100: =+H100/I100*J100 -> 3.5294118 | L100: =+H100+K100 -> 18.529412 | O100: =+L100*1.5 -> 27.794118 | P100: 60
...

Sheet suits
B1: SHOP | C1: LABEL | D1: Q | E1: size | F1: Item | G1: pur price | H1: total purchase price | I1: total cost | J1: Indirect Cost / unit | K1: Total Unit Cost | L1: Multiplier | M1: recommended | N1: Actual Price | O1: SALE | P1: S/T JAN '25 | Q1: status | R1: date | S1: sales
F3: OUTFITS & SUITS
B4: femeny | C4: jf lefone | D4: 1 | F4: white dress & jacket | G4: 33 | H4: 5920.5 | I4: 13960 | J4: =+G4/H4*I4 -> 77.810996 | K4: =+G4+J4 -> 110.811 | L4: 0.3 | M4: =+K4*L4+K4 -> 144.05429 | N4: 150
C5: dancing queen | D5: 2 | E5: 48 | F5: silver & black 2 piece | G5: 45 | H5: 5920.5 | I5: 13960 | J5: =+G5/H5*I5 -> 106.1059 | K5: =+G5+J5 -> 151.1059 | L5: 0.3 | M5: =+K5*L5+K5 -> 196.43767 | N5: 100 | P5: separate skirt & jacket
C6: hatunga | D6: 3 | E6: 38 | F6: gold 2 piece with front glitter | M6: =+K6*L6+K6 -> 0 | Q6: to pela mapeza
C7: fascino | D7: 4 | E7: 44 | F7: fascino cream/gold 2pc | G7: 55 | H7: 5500 | I7: 11950 | J7: =+G7/H7*I7 -> 119.5 | L7: 0.3 | M7: =+K7*L7+K7 -> 0 | N7: 220
C8: mavellino | D8: 5 | E8: 42 | F8: striped blue dress suit | G8: 55 | H8: 5690 | I8: 9443 | J8: =+G8/H8*I8 -> 91.276801 | K8: =+G8+J8 -> 146.2768 | L8: 0.3 | N8: 180 | Q8: layby mutema - returned | R8: 45612
C9: golden woman | E9: 48 | F9: cream/peachjacket w peach skirt skirt | N9: 80
C10: golden woman | E10: 50 | F10: cream/peachjacket w peach skirt skirt | N10: 80
C11: doganer | E11: 56 | F11: blush pink 3pc wlong pencil skirt | N11: 80
C12: doganer | E12: 58 | F12: blush pink 3pc wlong pencil skirt | N12: 80
C13: march 2019 stock | M13: =+K13*L13+K13 -> 0
C14: hatunga | D14: 6 | E14: 42 | F14: navy/pink 3 piece | G14: 50 | H14: 4794 | I14: 7939 | J14: =+G14/H14*I14 -> 82.801418 | K14: =+G14+J14 -> 132.80142 | L14: 0.3 | M14: =+K14*L14+K14 -> 172.64184 | N14: 200
C15: hatunga | D15: 7 | E15: 44 | F15: navy/pink 3 piece | G15: 50 | H15: 4794 | I15: 7939 | J15: =+G15/H15*I15 -> 82.801418 | K15: =+G15+J15 -> 132.80142 | L15: 0.3 | M15: =+K15*L15+K15 -> 172.64184 | N15: 200 | Q15: cash returned
F16: FEB 2020 STOCK | M16: =+K16*L16+K16 -> 0
B17: NIDA | C17: lavous | D17: 8 | E17: 48 | F17: scotch & yellow 2 piece | G17: 19 | H17: 5690 | I17: 9443 | J17: =+G17/H17*I17 -> 31.531986 | K17: =+G17+J17 -> 50.531986 | L17: 0.3 | M17: =+K17*L17+K17 -> 65.691582 | N17: 80
C18: antonella | D18: 9 | E18: 44 | F18: black 2 piece knit | G18: 20 | H18: 5690 | I18: 9443 | J18: =+G18/H18*I18 -> 33.191564 | K18: =+G18+J18 -> 53.191564 | L18: 0.3 | M18: =+K18*L18+K18 -> 69.149033 | N18: 95 | Q18: cashtook skirt and purple polo neck top remained
C19: antonella | D19: 10 | E19: 44 | F19: black 2 piece knit | G19: 20 | H19: 5690 | I19: 9443 | J19: =+G19/H19*I19 -> 33.191564 | K19: =+G19+J19 -> 53.191564 | L19: 0.3 | M19: =+K19*L19+K19 -> 69.149033 | N19: 95
C20: antonella | D20: 13 | E20: 46 | F20: black 2 piece knit | G20: 20 | H20: 5690 | I20: 9443 | J20: =+G20/H20*I20 -> 33.191564 | K20: =+G20+J20 -> 53.191564 | L20: 0.3 | M20: =+K20*L20+K20 -> 69.149033 | N20: 95 | O20: 60 | Q20: nyamakupi | R20: 45351 | S20: =+O20*10000 -> 600000
F21: JUNE 2020 STOCK | M21: =+K21*L21+K21 -> 0
C22: sincere | D22: 12 | E22: 48 | F22: 2 piece denim dress | G22: 28 | H22: 283 | I22: =+H22+314 -> 597 | J22: =+G22/H22*I22 -> 59.067138 | K22: =+G22+J22 -> 87.067138 | L22: 0.3 | M22: =+K22*L22+K22 -> 113.18728 | N22: 100 | Q22: cash | R22: 45650
F23: december 2020 stock | M23: =+K23*L23+K23 -> 0
C24: pinema | D24: 13 | E24: 42 | F24: white trouser set | G24: 28 | H24: 272 | I24: =+H24+50+16 -> 338 | J24: =+G24/H24*I24 -> 34.794118 | K24: =+G24+J24 -> 62.794118 | L24: 0.3 | M24: =+K24*L24+K24 -> 81.632353 | N24: 110 | O24: 55
C25: pinema | D25: 14 | E25: 44 | F25: white trouser set | G25: 28 | H25: 272 | I25: =+H25+50+16 -> 338 | J25: =+G25/H25*I25 -> 34.794118 | K25: =+G25+J25 -> 62.794118 | L25: 0.3 | M25: =+K25*L25+K25 -> 81.632353 | N25: 110 | O25: 55
C26: pinema | D26: 15 | E26: 46 | F26: white trouser set | G26: 28 | H26: 272 | I26: =+H26+50+16 -> 338 | J26: =+G26/H26*I26 -> 34.794118 | K26: =+G26+J26 -> 62.794118 | L26: 0.3 | M26: =+K26*L26+K26 -> 81.632353 | N26: 110 | O26: 55
C27: pinema | D27: 16 | E27: 48 | F27: white trouser set | G27: 28 | H27: 272 | I27: =+H27+50+16 -> 338 | J27: =+G27/H27*I27 -> 34.794118 | K27: =+G27+J27 -> 62.794118 | L27: 0.3 | M27: =+K27*L27+K27 -> 81.632353 | N27: 110 | O27: 55
F28: dec 2021 stock | M28: =+K28*L28+K28 -> 0
B29: ideal | C29: ceber | D29: 17 | E29: 42 | F29: cream dress w gold jacket | G29: 41 | H29: 6556 | I29: 9750 | J29: =+G29/H29*I29 -> 60.97468 | K29: =+G29+J29 -> 101.97468 | L29: 0.3 | M29: =+K29*L29+K29 -> 132.56708 | N29: 150
B30: ideal | C30: ceber | D30: 18 | E30: 44 | F30: cream dress w gold jacket | G30: 41 | H30: 6556 | I30: 9750 | J30: =+G30/H30*I30 -> 60.97468 | K30: =+G30+J30 -> 101.97468 | L30: 0.3 | M30: =+K30*L30+K30 -> 132.56708 | N30: 150
B31: ideal | C31: ceber | D31: 19 | E31: 48 | F31: cream dress w gold jacket | G31: 41 | H31: 6556 | I31: 9750 | J31: =+G31/H31*I31 -> 60.97468 | K31: =+G31+J31 -> 101.97468 | L31: 0.3 | M31: =+K31*L31+K31 -> 132.56708 | N31: 150
B32: ideal | C32: gicca | D32: 20 | E32: 50 | F32: cream dress w gold jacket | G32: 41 | H32: 6556 | I32: 9750 | J32: =+G32/H32*I32 -> 60.97468 | K32: =+G32+J32 -> 101.97468 | L32: 0.3 | M32: =+K32*L32+K32 -> 132.56708 | N32: 150
B33: ideal | C33: gicca | D33: 21 | E33: 56 | F33: cream dress w gold jacket | G33: 41 | H33: 6556 | I33: 9750 | J33: =+G33/H33*I33 -> 60.97468 | K33: =+G33+J33 -> 101.97468 | L33: 0.3 | M33: =+K33*L33+K33 -> 132.56708 | N33: 150
B34: ideal | C34: gicca | D34: 22 | E34: 58 | F34: cream dress w gold jacket | G34: 41 | H34: 6556 | I34: 9750 | J34: =+G34/H34*I34 -> 60.97468 | K34: =+G34+J34 -> 101.97468 | L34: 0.3 | M34: =+K34*L34+K34 -> 132.56708 | N34: 150
B35: doganer | C35: doganer | E35: 48 | F35: blue dress / long jacket set | N35: 80
F36: NOV Turkey trip
C37: Nesly | D37: 23 | E37: 44 | F37: charcoal stripe skirt suit | G37: 55 | H37: 8267 | I37: 7400 | J37: =+G37/H37*I37 -> 49.231886 | K37: =+G37+J37 -> 104.23189 | L37: 0.3 | M37: =+K37*1.3 -> 135.50145 | N37: 150 | Q37: cash | R37: 45890
C38: Nesly | D38: 24 | E38: 44 | F38: navy skirt suit | G38: 55 | H38: 8267 | I38: 7400 | J38: =+G38/H38*I38 -> 49.231886 | K38: =+G38+J38 -> 104.23189 | L38: 0.3 | M38: =+K38*1.3 -> 135.50145 | N38: 150
C39: murray & co | D39: 26 | E39: 38 | F39: black skirt suit | G39: 60 | H39: 8267 | I39: 7400 | J39: =+G39/H39*I39 -> 53.707512 | K39: =+G39+J39 -> 113.70751 | L39: 0.3 | M39: =+K39*1.3 -> 147.81977 | N39: 80
C40: TEMEL CARGO 29 MAR '23
C41: NESLY | D41: 27 | F41: black w blue pinstripe | G41: 50 | H41: =+(700+612+375)*1.5 -> 2530.5 | I41: 631 | J41: =+G41/H41*I41 -> 12.467892 | K41: =+G41+J41 -> 62.467892 | L41: 0.4 | M41: =+K41*1.3 -> 81.208259 | N41: 150
F42: TURKEY MAY 2023
B43: nesly | C43: nesly | D43: 28 | E43: 38 | F43: coffee scotch small size | G43: 55 | H43: 9682 | I43: 7766 | J43: =+G43/H43*I43 -> 44.115885 | K43: =+G43+J43 -> 99.115885 | L43: 0.4 | M43: =+K43*1.4 -> 138.76224 | N43: 150 | Q43: cash | R43: 45804
B44: nesly | C44: nesly | D44: 29 | E44: 46 | F44: stripe trouser suit | G44: 55 | H44: 9682 | I44: 7766 | J44: =+G44/H44*I44 -> 44.115885 | K44: =+G44+J44 -> 99.115885 | L44: 0.4 | M44: =+K44*1.4 -> 138.76224 | N44: 150
C45: TURKEY MAY 2023 | F45: TROUSER SET
B46: tango | C46: misi Misia | D46: 30 | E46: 44 | F46: black trouser w black/white top | G46: 33 | H46: 9682 | I46: 7766 | J46: =+G46/H46*I46 -> 26.469531 | K46: =+G46+J46 -> 59.469531 | L46: 0.4 | M46: =+K46*1.4 -> 83.257344 | N46: 125
B47: moons | C47: moons | D47: 31 | E47: 40 | F47: blue trouser set w blue white blouse | G47: 40 | H47: 9682 | I47: 7766 | J47: =+G47/H47*I47 -> 32.08428 | K47: =+G47+J47 -> 72.08428 | L47: 0.4 | M47: =+K47*1.4 -> 100.91799 | N47: 125
B48: moons | C48: moons | D48: 32 | E48: 44 | F48: blue trouser set w blue white blouse | G48: 40 | H48: 9682 | I48: 7766 | J48: =+G48/H48*I48 -> 32.08428 | K48: =+G48+J48 -> 72.08428 | L48: 0.4 | M48: =+K48*1.4 -> 100.91799 | N48: 125
B49: moons | C49: moons | D49: 33 | E49: 46 | F49: blue trouser set w blue white blouse | G49: 40 | H49: 9682 | I49: 7766 | J49: =+G49/H49*I49 -> 32.08428 | K49: =+G49+J49 -> 72.08428 | L49: 0.4 | M49: =+K49*1.4 -> 100.91799 | N49: 125
B50: moons | C50: moons | D50: 34 | E50: 48 | F50: blue trouser set w blue white blouse | G50: 40 | H50: 9682 | I50: 7766 | J50: =+G50/H50*I50 -> 32.08428 | K50: =+G50+J50 -> 72.08428 | L50: 0.4 | M50: =+K50*1.4 -> 100.91799 | N50: 125
F51: JULY 2023 STOCK
B52: NESLEY | C52: NESLEY | D52: 35 | E52: 38 | F52: black 2 piece suit | G52: 50 | H52: 6066 | I52: 6015 | J52: =+G52/H52*I52 -> 49.579624 | K52: =+G52+J52 -> 99.579624 | L52: 0.4 | M52: =+K52*1.4 -> 139.41147 | N52: 150
B53: NESLEY | C53: NESLEY | D53: 36 | E53: 40 | F53: black 2 piece suit | G53: 50 | H53: 6066 | I53: 6015 | J53: =+G53/H53*I53 -> 49.579624 | K53: =+G53+J53 -> 99.579624 | L53: 0.4 | M53: =+K53*1.4 -> 139.41147 | N53: 140 | Q53: cash | R53: 46079
B54: NESLEY | C54: NESLEY | D54: 37 | E54: 44 | F54: black 2 piece suit | G54: 50 | H54: 6066 | I54: 6015 | J54: =+G54/H54*I54 -> 49.579624 | K54: =+G54+J54 -> 99.579624 | L54: 0.4 | M54: =+K54*1.4 -> 139.41147 | N54: 150 | Q54: mrs rev munikwa | R54: 45706
B55: NESLEY | C55: NESLEY | D55: 38 | E55: 46 | F55: black 2 piece suit | G55: 50 | H55: 6066 | I55: 6015 | J55: =+G55/H55*I55 -> 49.579624 | K55: =+G55+J55 -> 99.579624 | L55: 0.4 | M55: =+K55*1.4 -> 139.41147 | N55: 150
B56: NESLEY | C56: NESLEY | E56: 40 | F56: beige 2 pc suit former avondale | G56: 50 | H56: 6066 | I56: 6015 | J56: =+G56/H56*I56 -> 49.579624 | K56: =+G56+J56 -> 99.579624 | L56: 1.4 | M56: =+K56*1.4 -> 139.41147 | N56: 140 | Q56: cash | R56: 46079
C57: 45352
B58: NESLY | C58: NESLY | E58: 42 | F58: coffee scotch jacket & coffee pleated skirt | G58: 55 | H58: =825+725*0.045 -> 857.625 | I58: 370 | J58: =+G58/H58*I58 -> 23.728319 | K58: =+J58+G58 -> 78.728319 | L58: 0.4 | M58: =+K58*1.4 -> 110.21965 | N58: 150 | Q58: CR mrs kambarami | R58: 46052
E59: 44 | F59: coffee scotch jacket & coffee pleated skirt | G59: 55 | H59: =825+725*0.045 -> 857.625 | I59: 370 | J59: =+G59/H59*I59 -> 23.728319 | K59: =+J59+G59 -> 78.728319 | L59: 0.4 | M59: =+K59*1.4 -> 110.21965 | N59: 150
E60: 46 | F60: coffee scotch jacket & coffee pleated skirt | G60: 55 | H60: =825+725*0.045 -> 857.625 | I60: 370 | J60: =+G60/H60*I60 -> 23.728319 | K60: =+J60+G60 -> 78.728319 | L60: 0.4 | M60: =+K60*1.4 -> 110.21965 | N60: 150
C61: 45413
B62: xmeric | C62: xmeric | D62: 43 | E62: 46 | F62: brown scotch suit | G62: 42 | H62: 768 | I62: 515 | J62: =+G62/H62*I62 -> 28.164062 | K62: =+G62+J62 -> 70.164062 | M62: =+K62*1.4 -> 98.229687 | N62: 125 | Q62: dr zezai???? 10 apr
B63: xmeric | C63: xmeric | D63: 44 | E63: 48 | F63: brown scotch suit | G63: 42 | H63: 768 | I63: 515 | J63: =+G63/H63*I63 -> 28.164062 | K63: =+G63+J63 -> 70.164062 | M63: =+K63*1.4 -> 98.229687 | N63: 125
B64: xmeric | C64: xmeric | D64: 46 | E64: 44 | F64: maroon scotch suit | G64: 42 | H64: 768 | I64: 515 | J64: =+G64/H64*I64 -> 28.164062 | K64: =+G64+J64 -> 70.164062 | M64: =+K64*1.4 -> 98.229687 | N64: 125
B65: xmeric | C65: xmeric | D65: 47 | E65: 46 | F65: maroon scotch suit | G65: 42 | H65: 768 | I65: 515 | J65: =+G65/H65*I65 -> 28.164062 | K65: =+G65+J65 -> 70.164062 | M65: =+K65*1.4 -> 98.229687 | N65: 125
B66: xmeric | C66: xmeric | D66: 48 | E66: 48 | F66: maroon scotch suit | G66: 42 | H66: 768 | I66: 515 | J66: =+G66/H66*I66 -> 28.164062 | K66: =+G66+J66 -> 70.164062 | M66: =+K66*1.4 -> 98.229687 | N66: 125
B67: xmeric | C67: xmeric | D67: 49 | E67: 50 | F67: black suit | G67: 42 | H67: 768 | I67: 515 | J67: =+G67/H67*I67 -> 28.164062 | K67: =+G67+J67 -> 70.164062 | M67: =+K67*1.4 -> 98.229687 | N67: 125
B68: another | C68: no name | D68: 53 | F68: wooled 2 piece trouser | G68: 15 | M68: 45 | N68: 45
B69: woolen | D69: 54 | F69: beige trouser set | G69: 15 | H69: 4192 | I69: 3417 | J69: =+I69/H69*G69 -> 12.226861 | K69: =+G69+J69 -> 27.226861 | L69: 1.4 | M69: =+K69*L69 -> 38.117605 | N69: 45 | Q69: lilian | R69: 45804
C70: MAY 2025.
C71: NESLEY | E71: 44 | F71: BLACK SKIRT SUIT W PLEATED JACKET | G71: 60 | H71: 6149 | I71: =5832-600 -> 5232 | J71: =+G71/H71*I71 -> 51.052204 | K71: =+G71+J71 -> 111.0522 | M71: =+K71*1.4 -> 155.47309 | N71: 150 | Q71: rev muswakatira | R71: 45804
C72: NESLEY | E72: 46 | F72: BLACK SKIRT SUIT W PLEATED JACKET | G72: 60 | H72: 6149 | I72: =5832-600 -> 5232 | J72: =+G72/H72*I72 -> 51.052204 | K72: =+G72+J72 -> 111.0522 | M72: =+K72*1.4 -> 155.47309 | N72: 150 | Q72: damaris | R72: 45790
C73: NESLEY | E73: 48 | F73: BLACK SKIRT SUIT W PLEATED JACKET | G73: 60 | H73: 6149 | I73: =5832-600 -> 5232 | J73: =+G73/H73*I73 -> 51.052204 | K73: =+G73+J73 -> 111.0522 | M73: =+K73*1.4 -> 155.47309 | N73: 150 | Q73: cash rev magumise | R73: 45852
C74: NESLEY | E74: 50 | F74: BLACK SKIRT SUIT W PLEATED JACKET | G74: 60 | H74: 6149 | I74: =5832-600 -> 5232 | J74: =+G74/H74*I74 -> 51.052204 | K74: =+G74+J74 -> 111.0522 | M74: =+K74*1.4 -> 155.47309 | N74: 150 | Q74: pastor lorraine returned
C75: NESLEY | E75: 52 | F75: BLACK SKIRT SUIT W PLEATED JACKET | G75: 60 | H75: 6149 | I75: =5832-600 -> 5232 | J75: =+G75/H75*I75 -> 51.052204 | K75: =+G75+J75 -> 111.0522 | M75: =+K75*1.4 -> 155.47309 | N75: 150
C76: NESLEY | E76: 44 | F76: NAVY SKIRT SUIT W ONE BUTTON JACKET | G76: 60 | H76: 6149 | I76: =5832-600 -> 5232 | J76: =+G76/H76*I76 -> 51.052204 | K76: =+G76+J76 -> 111.0522 | M76: =+K76*1.4 -> 155.47309 | N76: 150
C77: NESLEY | E77: 46 | F77: NAVY SKIRT SUIT W ONE BUTTON JACKET | G77: 60 | H77: 6149 | I77: =5832-600 -> 5232 | J77: =+G77/H77*I77 -> 51.052204 | K77: =+G77+J77 -> 111.0522 | M77: =+K77*1.4 -> 155.47309 | N77: 150 | Q77: damaris | R77: 45790
C78: NESLEY | E78: 48 | F78: NAVY SKIRT SUIT W ONE BUTTON JACKET | G78: 60 | H78: 6149 | I78: =5832-600 -> 5232 | J78: =+G78/H78*I78 -> 51.052204 | K78: =+G78+J78 -> 111.0522 | M78: =+K78*1.4 -> 155.47309 | N78: 150
C79: NESLEY | E79: 50 | F79: NAVY SKIRT SUIT W ONE BUTTON JACKET | G79: 60 | H79: 6149 | I79: =5832-600 -> 5232 | J79: =+G79/H79*I79 -> 51.052204 | K79: =+G79+J79 -> 111.0522 | M79: =+K79*1.4 -> 155.47309 | N79: 150 | Q79: pastor lorraine | R79: 45797
C80: NESLEY | E80: 52 | F80: NAVY SKIRT SUIT W ONE BUTTON JACKET | G80: 60 | H80: 6149 | I80: =5832-600 -> 5232 | J80: =+G80/H80*I80 -> 51.052204 | K80: =+G80+J80 -> 111.0522 | M80: =+K80*1.4 -> 155.47309 | N80: 150
C81: 45901
B82: IBRAHIM HAZAR | E82: 36 | F82: black skirt suit w flared skirt | G82: 39 | H82: 5225 | I82: 3700 | J82: =+G82/H82*I82 -> 27.617225 | K82: =+G82+J82 -> 66.617225 | M82: =+K82*1.4 -> 93.264115 | N82: 150 | O82: 150
B83: IBRAHIM HAZAR | E83: 38 | F83: black skirt suit w flared skirt | G83: 39 | H83: 5225 | I83: 3700 | J83: =+G83/H83*I83 -> 27.617225 | K83: =+G83+J83 -> 66.617225 | M83: =+K83*1.4 -> 93.264115 | N83: 150 | O83: 150
B84: IBRAHIM HAZAR | E84: 40 | F84: black skirt suit w flared skirt | G84: 39 | H84: 5225 | I84: 3700 | J84: =+G84/H84*I84 -> 27.617225 | K84: =+G84+J84 -> 66.617225 | M84: =+K84*1.4 -> 93.264115 | N84: 150 | O84: 150
B85: IBRAHIM HAZAR | E85: 42 | F85: black skirt suit w flared skirt | G85: 39 | H85: 5225 | I85: 3700 | J85: =+G85/H85*I85 -> 27.617225 | K85: =+G85+J85 -> 66.617225 | M85: =+K85*1.4 -> 93.264115 | N85: 150 | O85: 150
B86: IBRAHIM HAZAR | E86: 44 | F86: black skirt suit w flared skirt | G86: 39 | H86: 5225 | I86: 3700 | J86: =+G86/H86*I86 -> 27.617225 | K86: =+G86+J86 -> 66.617225 | M86: =+K86*1.4 -> 93.264115 | N86: 125 | O86: 150 | Q86: rev mukwakwami | R86: 45939
B87: nodilife | C87: nodilife | E87: 40 | F87: black skirt suit w long flared skirt & zip jacket | G87: 39 | H87: 5225 | I87: 3700 | J87: =+G87/H87*I87 -> 27.617225 | K87: =+G87+J87 -> 66.617225 | M87: =+K87*1.4 -> 93.264115 | N87: 150 | O87: 150
B88: nodilife | C88: nodilife | E88: 44 | F88: black skirt suit w long flared skirt & zip jacket | G88: 39 | H88: 5225 | I88: 3700 | J88: =+G88/H88*I88 -> 27.617225 | K88: =+G88+J88 -> 66.617225 | M88: =+K88*1.4 -> 93.264115 | N88: 150 | O88: 150
B89: nodilife | C89: nodilife | E89: 48 | F89: black skirt suit w long flared skirt & zip jacket | G89: 39 | H89: 5225 | I89: 3700 | J89: =+G89/H89*I89 -> 27.617225 | K89: =+G89+J89 -> 66.617225 | M89: =+K89*1.4 -> 93.264115 | N89: 150 | O89: 150
B90: nodilife | C90: nodilife | E90: 50 | F90: black skirt suit w long flared skirt & zip jacket | G90: 39 | H90: 5225 | I90: 3700 | J90: =+G90/H90*I90 -> 27.617225 | K90: =+G90+J90 -> 66.617225 | M90: =+K90*1.4 -> 93.264115 | N90: 150 | O90: 150
B91: maryland | C91: maryland | E91: 44 | F91: black skirt suit w waistcoat | G91: 45 | H91: 5225 | I91: 3700 | J91: =+G91/H91*I91 -> 31.866029 | K91: =+G91+J91 -> 76.866029 | M91: =+K91*1.4 -> 107.61244 | N91: =+K91*1.5 -> 115.29904 | O91: 130
B92: maryland | C92: maryland | E92: 44 | F92: black skirt suit w waistcoat | G92: 45 | H92: 5225 | I92: 3700 | J92: =+G92/H92*I92 -> 31.866029 | K92: =+G92+J92 -> 76.866029 | M92: =+K92*1.4 -> 107.61244 | N92: =+K92*1.5 -> 115.29904 | O92: 130
B93: maryland | C93: maryland | E93: 46 | F93: black skirt suit w waistcoat | G93: 45 | H93: 5225 | I93: 3700 | J93: =+G93/H93*I93 -> 31.866029 | K93: =+G93+J93 -> 76.866029 | M93: =+K93*1.4 -> 107.61244 | N93: =+K93*1.5 -> 115.29904 | O93: 130
B94: maryland | C94: maryland | E94: 48 | F94: black skirt suit w waistcoat | G94: 45 | H94: 5225 | I94: 3700 | J94: =+G94/H94*I94 -> 31.866029 | K94: =+G94+J94 -> 76.866029 | M94: =+K94*1.4 -> 107.61244 | N94: =+K94*1.5 -> 115.29904 | O94: 130
F96: TROUSER SUITS
C97: MAY 2025.
C98: maryland | F98: beige scotch trouser suit | G98: 45 | H98: 6149 | I98: =5832-600 -> 5232 | J98: =+G98/H98*I98 -> 38.289153 | K98: =+G98+J98 -> 83.289153 | M98: =+K98*1.4 -> 116.60481 | N98: 150
C99: june 2025.
C100: nesly | E100: 38 | F100: stripped grey trouser suit | G100: 58 | H100: 870 | I100: 300 | J100: =+G100/H100*I100 -> 20 | K100: =+G100+J100 -> 78 | M100: =+K100*1.4 -> 109.2 | N100: 150 | Q100: mai abisha | R100: 45874
C101: nesly | E101: 40 | F101: stripped grey trouser suit | G101: 58 | H101: 870 | I101: 300 | J101: =+G101/H101*I101 -> 20 | K101: =+G101+J101 -> 78 | M101: =+K101*1.4 -> 109.2 | N101: 150
C102: nesly | E102: 42 | F102: stripped grey trouser suit | G102: 58 | H102: 870 | I102: 300 | J102: =+G102/H102*I102 -> 20 | K102: =+G102+J102 -> 78 | M102: =+K102*1.4 -> 109.2 | N102: 150
...

Sheet hats shoes & bags
B1: SHOP | C1: LABEL | D1: Q | E1: size | F1: Item | G1: pur price | H1: total purchase price | I1: total cost | J1: Indirect Cost / unit | K1: Total Unit Cost | L1: Multiplier | M1: recommended | N1: Actual Price | O1: SALE | P1: S/T JAN '25 | Q1: S/T JAN 2026 | R1: status | S1: date
F3: SHOES
B4: STOCK 2018
C5: life stride | D5: 1 | F5: black sandal low heel | G5: 12 | H5: 5650 | I5: 9750 | J5: =+G5/H5*I5 -> 20.707965 | K5: =+G5+J5 -> 32.707965 | L5: 1.3 | M5: =+K5*L5+K5 -> 75.228319 | N5: 65 | R5: taken home
F6: TURKEY SEPT 2019 | M6: =+K6*L6+K6 -> 0
C7: altin yak | D7: 3 | F7: nude block heel with bow on top | G7: 12 | M7: =+K7*L7+K7 -> 0 | N7: 65 | O7: 25
C8: 44044 | M8: =+K8*L8+K8 -> 0
C9: MRP | D9: 5 | E9: 5 | F9: green flat sandals w buckle | G9: 7.5882353 | M9: =+K9*L9+K9 -> 0 | N9: 25
C10: MRP | D10: 6 | E10: 5 | F10: green flat sandals w buckle | G10: 7.5882353 | M10: =+K10*L10+K10 -> 0 | N10: 25
F11: CHINA STOCK MARCH 2021 | M11: =+K11*L11+K11 -> 0
C12: zara | D12: 7 | E12: 40 | F12: nude heel slip on | G12: 8 | H12: 1050 | I12: 2585 | J12: =+G12/H12*I12 -> 19.695238 | K12: =+G12+J12 -> 27.695238 | L12: 0.3 | M12: =+K12*L12+K12 -> 36.00381 | N12: 45 | R12: taken home
C13: zara | D13: 8 | E13: 40 | F13: nude heel slip on | G13: 8 | H13: 1050 | I13: =+H13+1335+200 -> 2585 | J13: =+G13/H13*I13 -> 19.695238 | K13: =+G13+J13 -> 27.695238 | L13: 0.3 | M13: =+K13*L13+K13 -> 36.00381 | N13: 45 | R13: taken home
C14: zara | D14: 9 | E14: 41 | F14: nude heel slip on | G14: 8 | H14: 1050 | I14: =+H14+1335+200 -> 2585 | J14: =+G14/H14*I14 -> 19.695238 | K14: =+G14+J14 -> 27.695238 | L14: 0.3 | M14: =+K14*L14+K14 -> 36.00381 | N14: 45 | R14: taken home
C15: zara | D15: 10 | E15: 40 | F15: orange heel slip on | G15: 8 | H15: 1050 | I15: =+H15+1335+200 -> 2585 | J15: =+G15/H15*I15 -> 19.695238 | K15: =+G15+J15 -> 27.695238 | L15: 0.3 | M15: =+K15*L15+K15 -> 36.00381 | N15: 45 | R15: taken home
C16: zara | D16: 11 | E16: 41 | F16: gold heel strappy sandal | G16: 8 | H16: 1050 | I16: =+H16+1335+200 -> 2585 | J16: =+G16/H16*I16 -> 19.695238 | K16: =+G16+J16 -> 27.695238 | L16: 0.3 | M16: =+K16*L16+K16 -> 36.00381 | N16: 45 | R16: taken home
C17: zara | D17: 12 | E17: 39 | F17: gold heel strappy sandal | G17: 8 | H17: 1050 | I17: =+H17+1335+200 -> 2585 | J17: =+G17/H17*I17 -> 19.695238 | K17: =+G17+J17 -> 27.695238 | L17: 0.3 | M17: =+K17*L17+K17 -> 36.00381 | N17: 45 | R17: taken home
C18: zara | D18: 13 | E18: 39 | F18: pink heel strappy sandal | G18: 8 | H18: 1050 | I18: =+H18+1335+200 -> 2585 | J18: =+G18/H18*I18 -> 19.695238 | K18: =+G18+J18 -> 27.695238 | L18: 0.3 | M18: =+K18*L18+K18 -> 36.00381 | N18: 45 | R18: taken home
C19: zara | D19: 14 | E19: 40 | F19: pink heel strappy sandal | G19: 8 | H19: 1050 | I19: =+H19+1335+200 -> 2585 | J19: =+G19/H19*I19 -> 19.695238 | K19: =+G19+J19 -> 27.695238 | L19: 0.3 | M19: =+K19*L19+K19 -> 36.00381 | N19: 45 | R19: taken home
C20: zara | D20: 15 | E20: 41 | F20: pink heel strappy sandal | G20: 8 | H20: 1050 | I20: =+H20+1335+200 -> 2585 | J20: =+G20/H20*I20 -> 19.695238 | K20: =+G20+J20 -> 27.695238 | L20: 0.3 | M20: =+K20*L20+K20 -> 36.00381 | N20: 45 | R20: taken home
C21: zara | D21: 16 | E21: 37 | F21: white heeled slip on with buckle | G21: 8 | H21: 1050 | I21: =+H21+1335+200 -> 2585 | J21: =+G21/H21*I21 -> 19.695238 | K21: =+G21+J21 -> 27.695238 | L21: 0.3 | M21: =+K21*L21+K21 -> 36.00381 | N21: 45 | R21: taken home mai poly cash
F22: flat sandal | M22: =+K22*L22+K22 -> 0
C23: charles & keith | D23: 17 | E23: 39 | F23: white flat sandal | G23: 7 | H23: 1050 | I23: =+H23+1335+200 -> 2585 | J23: =+G23/H23*I23 -> 17.233333 | K23: =+G23+J23 -> 24.233333 | L23: 0.3 | M23: =+K23*L23+K23 -> 31.503333 | N23: 30 | R23: taken home
C24: LV | D24: 18 | E24: 39 | F24: brown fur flat sandal | G24: 6 | H24: 1050 | I24: =+H24+1335+200 -> 2585 | J24: =+G24/H24*I24 -> 14.771429 | K24: =+G24+J24 -> 20.771429 | L24: 0.3 | M24: =+K24*L24+K24 -> 27.002857 | N24: 25
C25: zara | D25: 20 | E25: 39 | F25: black plaited flat sandal | G25: 6 | H25: 1050 | I25: =+H25+1335+200 -> 2585 | J25: =+G25/H25*I25 -> 14.771429 | K25: =+G25+J25 -> 20.771429 | L25: 0.3 | M25: =+K25*L25+K25 -> 27.002857 | N25: 25 | O25: 15 | R25: gift rev shandu
C26: zara | D26: 21 | E26: 40 | F26: gold plaited flat sandal | G26: 6 | H26: 1050 | I26: =+H26+1335+200 -> 2585 | J26: =+G26/H26*I26 -> 14.771429 | K26: =+G26+J26 -> 20.771429 | L26: 0.3 | M26: =+K26*L26+K26 -> 27.002857 | N26: 25
C27: zara | D27: 22 | E27: 41 | F27: gold plaited flat sandal | G27: 6 | H27: 1050 | I27: =+H27+1335+200 -> 2585 | J27: =+G27/H27*I27 -> 14.771429 | K27: =+G27+J27 -> 20.771429 | L27: 0.3 | M27: =+K27*L27+K27 -> 27.002857 | N27: 25
C28: zara | D28: 23 | E28: 39 | F28: gold plaited flat sandal | G28: 6 | H28: 1050 | I28: =+H28+1335+200 -> 2585 | J28: =+G28/H28*I28 -> 14.771429 | K28: =+G28+J28 -> 20.771429 | L28: 0.3 | M28: =+K28*L28+K28 -> 27.002857 | N28: 25
C29: zara | D29: 24 | E29: 41 | F29: gold plaited flat sandal | G29: 6 | H29: 1050 | I29: =+H29+1335+200 -> 2585 | J29: =+G29/H29*I29 -> 14.771429 | K29: =+G29+J29 -> 20.771429 | L29: 0.3 | M29: =+K29*L29+K29 -> 27.002857 | N29: 25
C30: zara | D30: 25 | E30: 40 | F30: gold plaited flat sandal | G30: 6 | H30: 1050 | I30: =+H30+1335+200 -> 2585 | J30: =+G30/H30*I30 -> 14.771429 | K30: =+G30+J30 -> 20.771429 | L30: 0.3 | M30: =+K30*L30+K30 -> 27.002857 | N30: 25
C31: zara | D31: 26 | E31: 38 | F31: gold plaited flat sandal | G31: 6 | H31: 1050 | I31: =+H31+1335+200 -> 2585 | J31: =+G31/H31*I31 -> 14.771429 | K31: =+G31+J31 -> 20.771429 | L31: 0.3 | M31: =+K31*L31+K31 -> 27.002857 | N31: 25
C32: zara | D32: 27 | E32: 41 | F32: royal blue plaited flat sandal | G32: 6 | H32: 1050 | I32: =+H32+1335+200 -> 2585 | J32: =+G32/H32*I32 -> 14.771429 | K32: =+G32+J32 -> 20.771429 | L32: 0.3 | M32: =+K32*L32+K32 -> 27.002857 | N32: 25
C33: zara | D33: 28 | E33: 39 | F33: royal blue plaited flat sandal | G33: 6 | H33: 1050 | I33: =+H33+1335+200 -> 2585 | J33: =+G33/H33*I33 -> 14.771429 | K33: =+G33+J33 -> 20.771429 | L33: 0.3 | M33: =+K33*L33+K33 -> 27.002857 | N33: 25
C34: zara | D34: 29 | E34: 40 | F34: royal blue plaited flat sandal | G34: 6 | H34: 1050 | I34: =+H34+1335+200 -> 2585 | J34: =+G34/H34*I34 -> 14.771429 | K34: =+G34+J34 -> 20.771429 | L34: 0.3 | M34: =+K34*L34+K34 -> 27.002857 | N34: 25
F35: BOOTS | M35: =+K35*L35+K35 -> 0
C36: ZARA T | D36: 30 | E36: 39 | F36: Black high ankle w side mesh | G36: 12 | H36: 1050 | I36: =+H36+1335+200 -> 2585 | J36: =+G36/H36*I36 -> 29.542857 | K36: =+G36+J36 -> 41.542857 | L36: 0.3 | M36: =+K36*L36+K36 -> 54.005714 | N36: 65 | R36: taken home
C37: zara | D37: 32 | E37: 37 | F37: navy suede ankle boot | G37: 12 | H37: 1050 | I37: =+H37+1335+200 -> 2585 | J37: =+G37/H37*I37 -> 29.542857 | K37: =+G37+J37 -> 41.542857 | L37: 0.3 | M37: =+K37*L37+K37 -> 54.005714 | N37: 55 | R37: taken home
C38: bongo | D38: 3 | F38: black knee high low wedge boot | M38: =+K38*L38+K38 -> 0 | N38: 70 | R38: taken by tatenda
C39: sept 2021 stock | M39: =+K39*L39+K39 -> 0
C40: altin yak | D40: 34 | E40: 36 | F40: black block heel | G40: 13 | H40: 844 | I40: 1496 | J40: =+G40/H40*I40 -> 23.042654 | K40: =+G40+J40 -> 36.042654 | L40: 0.3 | M40: =+K40*L40+K40 -> 46.85545 | N40: 55
C41: altin yak | D41: 35 | E41: 37 | F41: black block heel | G41: 13 | H41: 844 | I41: 1496 | J41: =+G41/H41*I41 -> 23.042654 | K41: =+G41+J41 -> 36.042654 | L41: 0.3 | M41: =+K41*L41+K41 -> 46.85545 | N41: 55
C42: altin yak | D42: 36 | E42: 38 | F42: black block heel | G42: 13 | H42: 844 | I42: 1496 | J42: =+G42/H42*I42 -> 23.042654 | K42: =+G42+J42 -> 36.042654 | L42: 0.3 | M42: =+K42*L42+K42 -> 46.85545 | N42: 55
C43: altin yak | D43: 38 | E43: 38 | F43: black block heel | G43: 13 | H43: 844 | I43: 1496 | J43: =+G43/H43*I43 -> 23.042654 | K43: =+G43+J43 -> 36.042654 | L43: 0.3 | M43: =+K43*L43+K43 -> 46.85545 | N43: 55
C44: altin yak | D44: 39 | E44: 39 | F44: black block heel | G44: 13 | H44: 844 | I44: 1496 | J44: =+G44/H44*I44 -> 23.042654 | K44: =+G44+J44 -> 36.042654 | L44: 0.3 | M44: =+K44*L44+K44 -> 46.85545 | N44: 55
C45: altin yak | D45: 39 | E45: 39 | F45: black block heel | G45: 13 | H45: 844 | I45: 1496 | J45: =+G45/H45*I45 -> 23.042654 | K45: =+G45+J45 -> 36.042654 | L45: 0.3 | M45: =+K45*L45+K45 -> 46.85545 | N45: 55 | R45: cash mai poly | S45: 46064
C46: altin yak | D46: 40 | E46: 37 | F46: nude block heel | G46: 13 | H46: 844 | I46: 1496 | J46: =+G46/H46*I46 -> 23.042654 | K46: =+G46+J46 -> 36.042654 | L46: 0.3 | M46: =+K46*L46+K46 -> 46.85545 | N46: 65 | R46: taken home
C47: altin yak | D47: 41 | E47: 36 | F47: black leather tennis | G47: 13 | H47: 844 | I47: 1496 | J47: =+G47/H47*I47 -> 23.042654 | K47: =+G47+J47 -> 36.042654 | L47: 0.3 | M47: =+K47*L47+K47 -> 46.85545 | N47: 45
C48: as life | D48: 42 | E48: 40 | F48: red flat strappy sandals | G48: 38 | M48: =+K48*L48+K48 -> 0 | N48: 55
C49: as life | D49: 43 | E49: 40 | F49: black flat strappy sandals | G49: 38 | M49: =+K49*L49+K49 -> 0 | N49: 55
C50: altin yak | D50: 45 | E50: 39 | F50: black glossy medium heel | G50: 11 | H50: 6556 | I50: 9750 | J50: =+G50/H50*I50 -> 16.35906 | K50: =+G50+J50 -> 27.35906 | L50: 0.3 | M50: =+K50*L50+K50 -> 35.566779 | N50: 65 | O50: 45
C51: altin yak | D51: 46 | E51: 40 | F51: black glossy medium heel | G51: 11 | H51: 6556 | I51: 9750 | J51: =+G51/H51*I51 -> 16.35906 | K51: =+G51+J51 -> 27.35906 | L51: 0.3 | M51: =+K51*L51+K51 -> 35.566779 | N51: 65 | O51: 45
C52: altin yak | D52: 47 | E52: 41 | F52: black glossy medium heel | G52: 11 | H52: 6556 | I52: 9750 | J52: =+G52/H52*I52 -> 16.35906 | K52: =+G52+J52 -> 27.35906 | L52: 0.3 | M52: =+K52*L52+K52 -> 35.566779 | N52: 65 | O52: 45
C53: altin yak | D53: 48 | E53: 41 | F53: black glossy medium heel | G53: 11 | H53: 6556 | I53: 9750 | J53: =+G53/H53*I53 -> 16.35906 | K53: =+G53+J53 -> 27.35906 | L53: 0.3 | M53: =+K53*L53+K53 -> 35.566779 | N53: 65 | O53: 45
C54: paris | D54: 50 | E54: 36 | F54: black w elastic top | G54: 12 | H54: 6556 | I54: 9750 | J54: =+G54/H54*I54 -> 17.846248 | K54: =+G54+J54 -> 29.846248 | L54: 0.3 | M54: =+K54*L54+K54 -> 38.800122 | N54: 65 | O54: 45
C55: paris | D55: 51 | E55: 37 | F55: black w elastic top | G55: 12 | H55: 6556 | I55: 9750 | J55: =+G55/H55*I55 -> 17.846248 | K55: =+G55+J55 -> 29.846248 | L55: 0.3 | M55: =+K55*L55+K55 -> 38.800122 | N55: 65 | O55: 45
C56: paris | D56: 52 | E56: 36 | F56: black w buckle | G56: 14 | H56: 6556 | I56: 9750 | J56: =+G56/H56*I56 -> 20.820622 | K56: =+G56+J56 -> 34.820622 | L56: 0.3 | M56: =+K56*L56+K56 -> 45.266809 | N56: 65 | O56: 45
C57: paris | D57: 54 | E57: 38 | F57: black w buckle | G57: 14 | H57: 6556 | I57: 9750 | J57: =+G57/H57*I57 -> 20.820622 | K57: =+G57+J57 -> 34.820622 | L57: 0.3 | M57: =+K57*L57+K57 -> 45.266809 | N57: 65 | O57: 45
F58: feb 2021 stock
C59: PAOLO ROSSI | D59: 55 | E59: 40 | F59: black heels | G59: 35 | H59: 1079 | I59: =+H59+552 -> 1631 | J59: =+G59/H59*I59 -> 52.905468 | K59: =+G59+J59 -> 87.905468 | L59: 0.3 | M59: =+K59*L59+K59 -> 114.27711 | N59: 120 | O59: 65
C60: Paris | D60: 56 | E60: 36 | F60: maroon w black side elastic | G60: 16 | H60: 1079 | I60: =+H60+552 -> 1631 | J60: =+G60/H60*I60 -> 24.185357 | K60: =+G60+J60 -> 40.185357 | L60: 0.3 | M60: =+K60*L60+K60 -> 52.240964 | N60: 65 | O60: 25
C61: Paris | D61: 57 | E61: 37 | F61: maroon w black side elastic | G61: 16 | H61: 1079 | I61: =+H61+552 -> 1631 | J61: =+G61/H61*I61 -> 24.185357 | K61: =+G61+J61 -> 40.185357 | L61: 0.3 | M61: =+K61*L61+K61 -> 52.240964 | N61: 65 | O61: 25
C62: Paris | D62: 58 | E62: 37 | F62: maroon w black side elastic | G62: 16 | H62: 1079 | I62: =+H62+552 -> 1631 | J62: =+G62/H62*I62 -> 24.185357 | K62: =+G62+J62 -> 40.185357 | L62: 0.3 | M62: =+K62*L62+K62 -> 52.240964 | N62: 65 | O62: 25
C63: Paris | D63: 59 | E63: 39 | F63: maroon w black side elastic | G63: 16 | H63: 1079 | I63: =+H63+552 -> 1631 | J63: =+G63/H63*I63 -> 24.185357 | K63: =+G63+J63 -> 40.185357 | L63: 0.3 | M63: =+K63*L63+K63 -> 52.240964 | N63: 65 | O63: 25
C64: Paris | D64: 60 | E64: 40 | F64: black gloss court shoe | G64: 15 | H64: 1079 | I64: =+H64+552 -> 1631 | J64: =+G64/H64*I64 -> 22.673772 | K64: =+G64+J64 -> 37.673772 | L64: 0.3 | M64: =+K64*L64+K64 -> 48.975904 | N64: 70
C65: Paris | D65: 61 | E65: 44 | F65: black gloss court shoe | G65: 15 | H65: 1079 | I65: =+H65+552 -> 1631 | J65: =+G65/H65*I65 -> 22.673772 | K65: =+G65+J65 -> 37.673772 | L65: 0.3 | M65: =+K65*L65+K65 -> 48.975904 | N65: 70
F66: CHINA PUMPS FEBRUARY 16
B67: china | C67: ANGEL SHOES | D67: 63 | E67: 7 | F67: Black flat pump | G67: 7.52 | H67: 376 | I67: 864 | J67: =+G67/H67*I67 -> 17.28 | K67: =+G67+J67 -> 24.8 | L67: 0.3 | M67: =+K67*L67+K67 -> 32.24 | N67: 50
B68: china | C68: ANGEL SHOES | D68: 66 | E68: 7 | F68: maroon flat pump | G68: 7.52 | H68: 376 | I68: 864 | J68: =+G68/H68*I68 -> 17.28 | K68: =+G68+J68 -> 24.8 | L68: 0.3 | M68: =+K68*L68+K68 -> 32.24 | N68: 50
B69: china | C69: ANGEL SHOES | D69: 69 | E69: 12 | F69: maroon flat pump | G69: 7.52 | H69: 376 | I69: 864 | J69: =+G69/H69*I69 -> 17.28 | K69: =+G69+J69 -> 24.8 | L69: 0.3 | M69: =+K69*L69+K69 -> 32.24 | N69: 50
B70: china | C70: ANGEL SHOES | D70: 71 | E70: 12 | F70: grey flat pump | G70: 7.52 | H70: 376 | I70: 864 | J70: =+G70/H70*I70 -> 17.28 | K70: =+G70+J70 -> 24.8 | L70: 0.3 | M70: =+K70*L70+K70 -> 32.24 | N70: 50
B71: china | C71: ANGEL SHOES | D71: 75 | E71: 8 | F71: blue wedge | G71: 7.52 | H71: 376 | I71: 864 | J71: =+G71/H71*I71 -> 17.28 | K71: =+G71+J71 -> 24.8 | L71: 0.3 | M71: =+K71*L71+K71 -> 32.24 | N71: 60
B72: china | C72: ANGEL SHOES | D72: 76 | E72: 7 | F72: grey wedge | G72: 7.52 | H72: 376 | I72: 864 | J72: =+G72/H72*I72 -> 17.28 | K72: =+G72+J72 -> 24.8 | L72: 0.3 | M72: =+K72*L72+K72 -> 32.24 | N72: 60
B73: china | C73: ANGEL SHOES | D73: 78 | E73: 8 | F73: grey wedge | G73: 7.52 | H73: 376 | I73: 864 | J73: =+G73/H73*I73 -> 17.28 | K73: =+G73+J73 -> 24.8 | L73: 0.3 | M73: =+K73*L73+K73 -> 32.24 | N73: 60
B74: china | C74: ANGEL SHOES | D74: 79 | E74: 12 | F74: grey wedge | G74: 7.52 | H74: 376 | I74: 864 | J74: =+G74/H74*I74 -> 17.28 | K74: =+G74+J74 -> 24.8 | L74: 0.3 | M74: =+K74*L74+K74 -> 32.24 | N74: 60
C75: rumbi stock Sandals september
D76: 83 | E76: 7 | F76: yellow weave sandals | G76: 11.1875 | J76: 2.173913 | K76: =+G76+J76 -> 13.361413 | L76: 0.3 | M76: =+K76*1.3 -> 17.369837 | N76: 25 | R76: added dec stock take
C77: butterfly | D77: 84 | E77: 6 | F77: brown weave sandals | G77: 11.1875 | J77: 2.173913 | K77: =+G77+J77 -> 13.361413 | L77: 0.3 | M77: =+K77*1.3 -> 17.369837 | N77: 25 | R77: cash | S77: 46078
C78: edit | D78: 85 | E78: 7 | F78: black cross sandal | G78: 10 | J78: 2.173913 | K78: =+G78+J78 -> 12.173913 | L78: 0.3 | M78: =+K78*1.3 -> 15.826087 | N78: 25 | R78: cash | S78: 46097
F79: sept 2022 stock
B80: capone | C80: capone | D80: 89 | E80: 40 | F80: black gloss pattened medium heels | G80: 23 | H80: 6911 | I80: 4716 | J80: =+G80/H80*I80 -> 15.694979 | K80: =+G80+J80 -> 38.694979 | L80: 0.3 | M80: =+K80*L80+K80 -> 50.303473 | N80: 55 | R80: mutimodyo | S80: 46106
B81: capone | C81: capone | D81: 89 | E81: 40 | F81: black gloss pattened medium heels | G81: 23 | H81: 6911 | I81: 4716 | J81: =+G81/H81*I81 -> 15.694979 | K81: =+G81+J81 -> 38.694979 | L81: 0.3 | M81: =+K81*L81+K81 -> 50.303473 | N81: 55
F82: TURKEY TRIP NOV 2022
C83: polu collection | D83: 92 | E83: 40 | F83: cream loafers | G83: 15 | H83: 4607 | I83: =7503-H83 -> 2896 | J83: =+G83/H83*I83 -> 9.4291296 | K83: =+G83+J83 -> 24.42913 | L83: 0.3 | M83: =+K83*L83+K83 -> 31.757868 | N83: 55 | O83: 25
C84: paris order | D84: 93 | E84: 39 | F84: black flat shoes | G84: 16 | H84: 4607 | I84: =7503-H84 -> 2896 | J84: =+G84/H84*I84 -> 10.057738 | K84: =+G84+J84 -> 26.057738 | L84: 0.3 | M84: =+K84*L84+K84 -> 33.87506 | N84: 55
F85: SEPTEMBER . 2023
B86: ross | C86: report | D86: 98 | E86: 8.5 | F86: brown studded sandals | G86: 13 | H86: 1162 | I86: 2629 | J86: =+G86/H86*I86 -> 29.41222 | K86: =+G86+J86 -> 42.41222 | L86: 0.4 | M86: =+K86*1.4 -> 59.377108 | N86: 50
B87: ross | C87: report | D87: 99 | E87: 10 | F87: brown studded sandals | G87: 13 | H87: 1162 | I87: 2629 | J87: =+G87/H87*I87 -> 29.41222 | K87: =+G87+J87 -> 42.41222 | L87: 0.4 | M87: =+K87*1.4 -> 59.377108 | N87: 50
A88: china | C88: ANGEL SHOES | D88: 114 | E88: 7 | F88: pink medium heel w top design | G88: 6.8571429 | H88: 3550 | I88: 5698 | J88: =+G88/H88*I88 -> 11.006197 | K88: =+G88+J88 -> 17.86334 | M88: =+K88*1.4 -> 25.008676 | N88: 45 | R88: chidzenga | S88: 46079
A89: china | C89: ANGEL SHOES | D89: 115 | E89: 7 | F89: nude medium heel w top design | G89: 6.8571429 | H89: 3550 | I89: 5698 | J89: =+G89/H89*I89 -> 11.006197 | K89: =+G89+J89 -> 17.86334 | M89: =+K89*1.4 -> 25.008676 | N89: 45
A90: china | C90: ANGEL SHOES | D90: 136 | E90: 7 | F90: brown flat w top bluckle | G90: 6.8571429 | H90: 3550 | I90: 5698 | J90: =+G90/H90*I90 -> 11.006197 | K90: =+G90+J90 -> 17.86334 | M90: =+K90*1.4 -> 25.008676 | N90: 45
A91: china | C91: ANGEL SHOES | D91: 139 | E91: 9 | F91: maroon flat w top buckle | G91: 6.8571429 | H91: 3550 | I91: 5698 | J91: =+G91/H91*I91 -> 11.006197 | K91: =+G91+J91 -> 17.86334 | M91: =+K91*1.4 -> 25.008676 | N91: 45
A92: china | C92: ANGEL SHOES | D92: 140 | E92: 7 | F92: maroon flat w top buckle | G92: 6.8571429 | H92: 3550 | I92: 5698 | J92: =+G92/H92*I92 -> 11.006197 | K92: =+G92+J92 -> 17.86334 | M92: =+K92*1.4 -> 25.008676 | N92: 45
A93: china | C93: ANGEL SHOES | D93: 140 | E93: 7 | F93: black flat w top buckle | G93: 6.8571429 | H93: 3550 | I93: 5698 | J93: =+G93/H93*I93 -> 11.006197 | K93: =+G93+J93 -> 17.86334 | M93: =+K93*1.4 -> 25.008676 | N93: 45
C94: march
C95: angel shoes | E95: 7 | F95: nude sling back sandal | G95: 7.6 | H95: 354 | I95: 500 | J95: =+G95/H95*I95 -> 10.734463 | K95: =+G95+J95 -> 18.334463 | M95: =+K95*1.4 -> 25.668249 | N95: 40
C96: angel shoes | E96: 7 | F96: nude slingback sandal | G96: 7.6 | H96: 354 | I96: 500 | J96: =+G96/H96*I96 -> 10.734463 | K96: =+G96+J96 -> 18.334463 | M96: =+K96*1.4 -> 25.668249 | N96: 40
C97: angel shoes | E97: 7 | F97: maroon slingback sandal | G97: 7.6 | H97: 354 | I97: 500 | J97: =+G97/H97*I97 -> 10.734463 | K97: =+G97+J97 -> 18.334463 | M97: =+K97*1.4 -> 25.668249 | N97: 40 | R97: greta jere | S97: 46136
C98: angel shoes | E98: 8 | F98: maroon slingback sandal | G98: 7.6 | H98: 354 | I98: 500 | J98: =+G98/H98*I98 -> 10.734463 | K98: =+G98+J98 -> 18.334463 | M98: =+K98*1.4 -> 25.668249 | N98: 40 | R98: pastor komichi | S98: 46086
C99: angel shoes | E99: 8 | F99: maroon slingback sandal | G99: 7.6 | H99: 354 | I99: 500 | J99: =+G99/H99*I99 -> 10.734463 | K99: =+G99+J99 -> 18.334463 | M99: =+K99*1.4 -> 25.668249 | N99: 40 | R99: jere | S99: 46112
C100: angel shoes | E100: 8 | F100: maroon slingback sandal | G100: 7.6 | H100: 354 | I100: 500 | J100: =+G100/H100*I100 -> 10.734463 | K100: =+G100+J100 -> 18.334463 | M100: =+K100*1.4 -> 25.668249 | N100: 40
C101: angel shoes | E101: 10 | F101: red gloss square heel | G101: 7.6 | H101: 354 | I101: 500 | J101: =+G101/H101*I101 -> 10.734463 | K101: =+G101+J101 -> 18.334463 | M101: =+K101*1.4 -> 25.668249 | N101: 40 | R101: mrs mawango 2025 purchase reconciliation | S101: 24 dec 2025..
...

Sheet credit clients 
A1: to | C1: date of purchase | D1: inv no. | E1: amount | F1: paid to date | I1: USD Bal 2024
B2: mai chitindi | C2: 43571 | E2: 125
C3: 43597
E4: =SUM(E2:E3) -> 125 | I4: =+E4 -> 125
B6: mai jordan | E6: 65 | F6: -30
C7: 43550 | E7: 65 | F7: -40
C8: 43612 | F8: -50
C9: 43613 | E9: 200
C10: 43847 | F10: -50
E11: =SUM(E6:E10) -> 330 | F11: =SUM(F6:F10) -> -170 | I11: =+E11+F11 -> 160
B13: pauline gatsi | C13: 43546 | D13: 431 | E13: 200
C14: 43551
C15: 43551 | E15: =125+180 -> 305
E16: 175
C17: 43553
C18: 43593 | E18: 65
C19: 43602 | E19: =45+85 -> 130
C20: 43607 | E20: =70+65 -> 135
C21: 43608 | E21: 65
C22: 43616
C23: 43616 | E23: 415
C24: 43630 | E24: 90
C25: 43664
C26: 43664 | E26: 200
C27: 43679 | E27: 300
C28: 43694
C29: 43694 | E29: 100
C30: 43732 | E30: 215
C31: 43748
C32: 43748 | E32: 125
C33: 44169 | E33: 150
C34: 43820 | E34: 120
C35: 43859
C36: 43861 | E36: 280
C37: 43865 | E37: 75
C38: 43867 | E38: 55
C39: 43874 | E39: 50
C40: 43873 | E40: 125
B41: pauline Gatsi | C41: 43904
E42: =SUM(E13:E41) -> 3375 | K42: 745
B44: pauline Gatsi | E44: 745
C45: 43977 | G45: -300
C46: 43977 | E46: =80+45 -> 125
E47: =SUM(E44:E46) -> 870 | G47: =SUM(G44:G46) -> -300 | I47: =+E47+G47 -> 570
B48: Pauline Gatsi | E48: 570
B50: mavis | C50: 43698 | D50: 550 | E50: 65 | G50: 0
C51: 43732 | E51: 235
C52: 43733 | G52: -100
C53: 43733 | E53: 280
C54: 43742 | G54: -100
C55: 43742 | E55: =125+65 -> 190
C56: 43798 | E56: 68
C57: 43798 | E57: 65
C58: 44170 | E58: =125+150 -> 275
C59: 43820 | D59: 642 | E59: 115
C60: 43900 | G60: -400
G61: -65
C62: 43973 | G62: -200
E65: =SUM(E50:E62) -> 1293 | F65: =SUM(F50:F54) -> 0 | G65: =SUM(G50:G62) -> -865 | I65: =+E65+G65 -> 428
B67: bonnie musara | C67: 43907 | E67: 100
C68: 43964 | G68: -100
C69: 43964 | E69: 90 | G69: -50
C70: 43978 | E70: =125+125+90 -> 340
E73: =SUM(E67:E72) -> 530 | G73: =SUM(G68:G72) -> -150 | I73: =+E73+G73 -> 380
B75: magwizi | C75: 45476 | E75: 570 | F75: 0
C76: 45498 | F76: -500
E78: =SUM(E75:E77) -> 570 | F78: =SUM(F75:F77) -> -500 | I78: =+E78+F78 -> 70
B80: nyadzi | C80: 45504 | E80: 25 | F80: -5
C81: 46014 | F81: -15
C82: 45773 | E82: 35
E83: =SUM(E80:E82) -> 60 | F83: =SUM(F80:F82) -> -20 | I83: =+E83+F83 -> 40
B86: TOTAL BAD DEBTS | I86: =+I4+I11+I47+I65+I73+I78+I83 -> 1773
B88: 43770
A90: 11 | B90: Tatenda | C90: 43789 | D90: 401 | E90: 25
C91: 43473 | E91: 25
C92: 43495 | E92: =-(50/3.4) -> -14.705882
C93: 43552 | E93: =-50/3.4 -> -14.705882
C94: 43567 | E94: =65*0.75 -> 48.75
C95: 43619 | E95: -10
C96: 43679 | E96: -10
C97: 43680 | E97: 10
C98: 43739 | E98: -5
C99: 43801 | E99: -5
C100: 43812 | E100: =125*0.75 -> 93.75
C101: 44258 | E101: 60
C102: 44348 | E102: -8
C103: 44382 | E103: -10
C104: 44509 | E104: 25
C105: 44531 | E105: -10
C106: 10 dc | E106: -10
C107: 44594 | E107: -10
C108: 44621 | E108: -10
C109: 44650 | E109: -10
C110: 44693 | E110: 70
C111: 44713 | E111: -10
C112: 44743 | E112: -10
C113: 44838 | E113: -14
C114: 44872 | E114: -15
C115: 45238 | E115: 15
C116: 44919 | E116: -20
...

Sheet layby clients
A1: to | B1: date of purchase | C1: inst dates | D1: name | E1: inv no | F1: invoice total | G1: deposit | H1: inst | J1: layby bal
B4: 45742 | D4: zezai | F4: 150 | H4: -100
F6: =SUM(F4:F5) -> 150 | G6: =SUM(G4:G5) -> 0 | H6: =SUM(H4:H5) -> -100 | J6: =+F6+H6 -> 50
B9: 45859 | D9: memory mugake | F9: 45 | H9: -20 | M9: 1302
M10: 1212
F11: =SUM(F9:F10) -> 45 | G11: =SUM(G9:G10) -> 0 | H11: =SUM(H9:H10) -> -20 | J11: =SUM(F11:I11) -> 25 | M11: =+M9-M10 -> 90
B14: 45969 | D14: wendy munjemu | F14: 150 | H14: -80
C15: 46030 | H15: -70
F16: =SUM(F14:F15) -> 150 | G16: =SUM(G14:G15) -> 0 | H16: =SUM(H14:H15) -> -150 | J16: =+F16+H16 -> 0
B18: 45972 | D18: mai poly | F18: 150 | H18: -25
C19: 46043 | H19: -125
F20: =SUM(F18:F19) -> 150 | G20: =SUM(G18:G19) -> 0 | H20: =SUM(H18:H19) -> -150 | J20: =+F20+H20 -> 0
B22: 45973 | D22: mahufe | F22: 125 | H22: -50
C23: 45992 | H23: -40
C24: 45995
C25: 46092 | H25: -100
F26: =SUM(F22:F24) -> 125 | G26: =SUM(G22:G23) -> 0 | H26: =SUM(H22:H25) -> -190 | J26: =+F26+H26 -> -65
B29: 45990 | D29: chamisa | F29: 65 | H29: -20
D31: RETURNED | F31: =SUM(F29:F30) -> 65 | G31: =SUM(G29:G30) -> 0 | H31: =SUM(H29:H30) -> -20 | J31: =SUM(F31:I31) -> 45
B33: 45993 | D33: chidzenga | F33: 70 | H33: -20
C34: 45995 | F34: 5 | H34: -24
C35: 46041 | H35: -26
F36: =SUM(F33:F34) -> 75 | G36: =SUM(G33:G34) -> 0 | H36: =SUM(H33:H35) -> -70 | J36: =SUM(F36:I36) -> 5
B39: 46003 | D39: manyumwa | F39: 125 | H39: -60
C40: 46024 | H40: -65
F41: =SUM(F39:F40) -> 125 | G41: =SUM(G39:G40) -> 0 | H41: =SUM(H39:H40) -> -125 | J41: =SUM(F41:I41) -> 0
B43: 46003 | D43: tsopotsa | F43: 480 | H43: -20 | I43: disc
H44: -140
C45: 46004 | H45: -160
C46: 46010 | H46: -70
F47: =SUM(F43:F46) -> 480 | G47: =SUM(G43:G46) -> 0 | H47: =SUM(H43:H46) -> -390 | J47: =SUM(F47:I47) -> 90
B49: 46003 | D49: irene | F49: 65 | H49: -30
C50: 46039 | H50: -35
F51: =SUM(F49:F50) -> 65 | G51: =SUM(G49:G50) -> 0 | H51: =SUM(H49:H50) -> -65 | J51: =SUM(F51:I51) -> 0
D53: JANUARY 2026..
B55: 46024 | D55: Eve Mutsvangwa | F55: 235 | H55: -90
C56: 46028 | H56: -145
F57: =SUM(F55:F56) -> 235 | G57: =SUM(G55:G56) -> 0 | H57: =SUM(H55:H56) -> -235 | J57: =SUM(F57:I57) -> 0
B58: 46038 | D58: mr banda | F58: 65 | H58: -30
C59: 46046 | H59: -35
F60: =SUM(F58:F59) -> 65 | G60: =SUM(G58:G59) -> 0 | H60: =SUM(H58:H59) -> -65 | J60: =+F60+H60 -> 0
B62: 46042 | D62: mapotsa | F62: 180 | H62: -100
F63: 15
C64: 46044 | H64: -95
F65: =SUM(F62:F64) -> 195 | G65: =SUM(G62:G64) -> 0 | H65: =SUM(H62:H64) -> -195 | J65: =SUM(F65:I65) -> 0
B66: 46046 | D66: shambira | F66: 65 | H66: -35
C67: 46052 | H67: -30
F68: =SUM(F66:F67) -> 65 | G68: =SUM(G66:G67) -> 0 | H68: =SUM(H66:H67) -> -65 | J68: =SUM(F68:I68) -> 0
D69: tivavenge
B70: 46052 | F70: 190 | H70: -90
C71: 46057 | H71: -100
F72: =SUM(F70:F71) -> 190 | G72: =SUM(G70:G71) -> 0 | H72: =SUM(H70:H71) -> -190 | J72: =+F72+H72 -> 0
B74: 46057 | D74: Tivavenge | F74: 95 | H74: -40
C75: 46085 | H75: -55
F76: =SUM(F74:F75) -> 95 | G76: =SUM(G74:G75) -> 0 | H76: =SUM(H74:H75) -> -95 | J76: =SUM(F76:I76) -> 0
B78: 46072 | D78: kanjere | F78: 75 | H78: -30
C79: 46093 | H79: -45
F80: =SUM(F78:F79) -> 75 | G80: =SUM(G78:G79) -> 0 | H80: =SUM(H78:H79) -> -75 | J80: =SUM(F80:I80) -> 0
B82: 46078 | D82: shambira | F82: 125 | H82: -80
C83: march | H83: -45
F84: =SUM(F82:F83) -> 125 | G84: =SUM(G82:G83) -> 0 | H84: =SUM(H82:H83) -> -125 | J84: =SUM(F84:I84) -> 0
B86: 46079 | D86: chidzenga | F86: 80 | H86: -5
C87: 46116 | H87: -75
F88: =SUM(F86:F87) -> 80 | G88: =SUM(G86:G87) -> 0 | H88: =SUM(H86:H87) -> -80 | J88: =SUM(F88:I88) -> 0
B90: 46079 | D90: ndachi | F90: 25 | H90: -10
C91: 46086 | H91: -15
F92: =SUM(F90:F91) -> 25 | G92: =SUM(G90:G91) -> 0 | H92: =SUM(H90:H91) -> -25 | J92: =SUM(F92:I92) -> 0
B94: 46081 | D94: mrs njagu | F94: 195 | H94: -100
C95: 46084 | H95: -95
F96: =SUM(F94:F95) -> 195 | G96: =SUM(G94:G95) -> 0 | H96: =SUM(H94:H95) -> -195 | J96: =SUM(F96:I96) -> 0
B98: 46085 | D98: murembeni | F98: 65 | H98: -20
F100: =SUM(F98:F99) -> 65 | G100: =SUM(G98:G99) -> 0 | H100: =SUM(H98:H99) -> -20 | J100: =SUM(F100:I100) -> 45
B102: 46094 | D102: jaricha | F102: 150 | H102: -75
C103: 46101 | H103: -75
F104: =SUM(F102:F103) -> 150 | G104: =SUM(G102:G103) -> 0 | H104: =SUM(H102:H103) -> -150 | J104: =SUM(F104:I104) -> 0
B106: 46102 | D106: matumhu | F106: 65 | H106: -20
F108: =SUM(F106:F107) -> 65 | G108: =SUM(G106:G107) -> 0 | H108: =SUM(H106:H107) -> -20 | J108: =SUM(F108:I108) -> 45
B110: 46112 | D110: Greta Jere | F110: 25 | H110: -10
C111: 46132 | H111: -10
C112: 46135 | F112: 25 | H112: -10
F113: =SUM(F110:F112) -> 50 | G113: =SUM(G110:G111) -> 0 | H113: =SUM(H110:H112) -> -30 | J113: =SUM(F113:I113) -> 20
B116: 46139 | D116: magutsa | F116: 125 | H116: -25
F118: =SUM(F116:F117) -> 125 | G118: =SUM(G116:G117) -> 0 | H118: =SUM(H116:H117) -> -25 | J118: =SUM(F118:I118) -> 100
D121: TOTAL | J121: =SUM(J2:J120) -> 360

Sheet sales analysis
A1: to
C2: INITIAL ESTABLISHMENT | D2: GROWTH | E2: NORMAL | F2: NORMAL | G2: COVID | H2: COVID/EASTGATE | I2: COVID | J2: RECOVERY | K2: NORMAL/ AVONDALE/CAR | L2: RECOVERY | M2: normal
K3: avondale/car | L3: CAR/baby shop | M3: ceteris paribus wedding/ uk university
B4: month | C4: year 1 (sept-dec) 2015 | D4: year 2 ( 2016) | E4: year 3 ( 2017) | F4: year 4 (2018) | G4: year 5 (2019) | H4: year 6 2020 | I4: year 7 2021 | J4: year 8 2022 | K4: year 9 2023 | L4: yr 10 2024 | M4: yr 11 2025 | N4: yr 12 2026
B5: jan | D5: 3811 | E5: 5584 | F5: 8183 | G5: 2814 | H5: 4180 | I5: 1485 | J5: 6068 | K5: 4140 | L5: 3230 | M5: 5024 | N5: =+'daily sales'!B195 -> 5642
B6: feb | D6: 4126 | E6: 5317 | F6: 5000 | G6: 2883 | H6: 3413 | I6: 1570 | J6: 5403 | K6: 6376 | L6: 3380 | M6: 5030 | N6: =+'daily sales'!B378 -> 6915
B7: mar | D7: 5742 | E7: 6635 | F7: 6500 | G7: 6262 | H7: 6532 | I7: 6010 | J7: 6778 | K7: 8031 | L7: 5258 | M7: 6741 | N7: =+'daily sales'!B597 -> 9315
B8: apr | D8: 12651 | E8: 7539 | F8: 7200 | G8: 2162 | H8: 128 | I8: 4066 | J8: 8490 | K8: 11232 | L8: 7090 | M8: 7345 | N8: =+'daily sales'!B810 -> 6284
B9: may | D9: 5651 | E9: 6359 | F9: 9000 | G9: 6517 | H9: 3594 | I9: 6722 | J9: 8879 | K9: 10926 | L9: 7471 | M9: 10118
B10: jun | D10: 8161 | E10: 11905 | F10: 10000 | G10: 1498 | H10: 3961 | I10: 7798 | J10: 9362 | K10: 7742 | L10: 8907 | M10: 9778
B11: jul | D11: 6484 | E11: 6736 | F11: 8000 | G11: 6873 | H11: 5060 | I11: 4364 | J11: 6653 | K11: 9525 | L11: 6370 | M11: 6612
B12: aug | D12: 8230 | E12: 10761 | F12: 7000 | G12: 5505 | H12: 3150 | I12: 6270 | J12: 8335 | K12: 10015 | L12: 7479 | M12: 7650
B13: sept | C13: 6540 | D13: 11580 | E13: 6736 | F13: 12000 | G13: 6114 | H13: 5083 | I13: 8932 | J13: 6658 | K13: 8403 | L13: 6808 | M13: 4785
B14: oct | C14: 11157 | D14: 10088 | E14: 18642.6 | F14: 15000 | G14: 6691 | H14: 3875 | I14: 6199 | J14: 9675 | K14: 7623 | L14: 8649 | M14: 9160
B15: nov | C15: 6993 | D15: 6191 | E15: 9327 | F15: 10000 | G15: 6841 | H15: 4706 | I15: 7739 | J15: 6915 | K15: 8747 | L15: 6038 | M15: 5325
B16: dec | C16: 9405 | D16: 8897 | E16: 8279 | F16: 8000 | G16: 7148 | H16: 6947 | I16: 11255 | J16: 8645 | K16: 13002 | L16: 6840 | M16: 10621
B17: total | C17: =SUM(C5:C16) -> 34095 | D17: =SUM(D5:D16) -> 91612 | E17: =SUM(E5:E16) -> 103820.6 | F17: =SUM(F5:F16) -> 105883 | G17: =SUM(G5:G16) -> 61308 | H17: =SUM(H5:H16) -> 50629 | I17: =SUM(I5:I16) -> 72410 | J17: =SUM(J5:J16) -> 91861 | ... N17: =SUM(N5:N16) -> 28156
B19: av monthly | C19: =+C17/4 -> 8523.75 | D19: =+D17/12 -> 7634.3333 | E19: =+E17/12 -> 8651.7167 | F19: =+F17/12 -> 8823.5833 | G19: =+G17/12 -> 5109 | H19: =+H17/12 -> 4219.0833 | I19: =+I17/12 -> 6034.1667 | J19: =+J17/12 -> 7655.0833 | K19: =+K17/12 -> 8813.5 | ... N19: =+N17/12 -> 2346.3333
B21: quarterly analysis
B22: 1st | D22: =+D5+D6+D7 -> 13679 | E22: =+E5+E6+E7 -> 17536 | F22: =+F5+F6+F7 -> 19683 | G22: =+G5+G6+G7 -> 11959 | H22: =+H5+H6+H7 -> 14125 | I22: =+I5+I6+I7 -> 9065 | J22: =+J5+J6+J7 -> 18249 | K22: =+K5+K6+K7 -> 18547 | ... N22: =+N5+N6+N7 -> 21872
B23: 2nd | D23: =+D8+D9+D10 -> 26463 | E23: =+E8+E9+E10 -> 25803 | F23: =+F8+F9+F10 -> 26200 | G23: =+G8+G9+G10 -> 10177 | H23: =+H8+H9+H10 -> 7683 | I23: =+I8+I9+I10 -> 18586 | J23: =+J8+J9+J10 -> 26731 | K23: =+K8+K9+K10 -> 29900 | ... N23: =+N8+N9+N10 -> 6284
B24: 3rd | D24: =+D11+D12+D13 -> 26294 | E24: =+E11+E12+E13 -> 24233 | F24: =+F11+F12+F13 -> 27000 | G24: =+G11+G12+G13 -> 18492 | H24: =+H11+H12+H13 -> 13293 | I24: =+I11+I12+I13 -> 19566 | J24: =+J11+J12+J13 -> 21646 | K24: =+K11+K12+K13 -> 27943 | ... N24: =+N11+N12+N13 -> 0
B25: 4th | D25: =+D14+D15+D16 -> 25176 | E25: =+E14+E15+E16 -> 36248.6 | F25: =+F14+F15+F16 -> 33000 | G25: =+G14+G15+G16 -> 20680 | H25: =+H14+H15+H16 -> 15528 | I25: =+I14+I15+I16 -> 25193 | J25: =+J14+J15+J16 -> 25235 | K25: =+K14+K15+K16 -> 29372 | ... N25: =+N14+N15+N16 -> 0
D27: =SUM(D22:D26) -> 91612 | E27: =SUM(E22:E26) -> 103820.6 | F27: =SUM(F22:F26) -> 105883 | G27: =SUM(G22:G26) -> 61308 | H27: =SUM(H22:H26) -> 50629 | I27: =SUM(I22:I26) -> 72410 | J27: =SUM(J22:J26) -> 91861 | K27: =SUM(K22:K26) -> 105762 | ... N27: =SUM(N22:N26) -> 28156
B29: average quarterly | D29: =+D27/4 -> 22903 | E29: =+E27/4 -> 25955.15 | F29: =+F27/4 -> 26470.75 | G29: =+G27/4 -> 15327 | H29: =+H27/4 -> 12657.25 | I29: =+I27/4 -> 18102.5 | J29: =+J27/4 -> 22965.25 | K29: =+K27/4 -> 26440.5 | ... M29: =+M27/4 -> 22047.25
D33: month | E33: stock purchase outflow 2024 | F33: inflows - 2024 | G33: stock purchase outflow 2025 | H33: inflows - 2025
D34: jan | F34: =+'daily sales'!#REF! -> #REF! | G34: =+'stock purchase 2026'!I1158 -> 3538.2857 | H34: =+'daily sales'!#REF! -> #REF! | P34: =+'daily sales'!#REF! -> #REF!
D35: feb | E35: =+'stock purchase 2026'!I19 -> 300 | F35: =+'daily sales'!#REF! -> #REF! | G35: =+'stock purchase 2026'!I1169 -> 252 | H35: =+'daily sales'!#REF! -> #REF! | P35: =+'daily sales'!#REF! -> #REF!
D36: mar | E36: =+'stock purchase 2026'!I255 -> 4191.88 | F36: =+'daily sales'!#REF! -> #REF! | G36: =+'stock purchase 2026'!I1222 -> 364.8 | H36: =+'daily sales'!#REF! -> #REF!
B37: =+H46-F34-F35-F36-F37 -> #REF! | D37: apr | E37: =+'stock purchase 2026'!I379 -> 4087 | F37: =+'daily sales'!#REF! -> #REF! | G37: =+'stock purchase 2026'!I1248 -> 41 | H37: =+'daily sales'!#REF! -> #REF!
D38: may | F38: =+'daily sales'!#REF! -> #REF! | G38: =+'stock purchase 2026'!I1863 -> 9628.95 | H38: =+'daily sales'!#REF! -> #REF!
D39: jun | E39: =+'stock purchase 2026'!I458 -> 1960 | F39: =+'daily sales'!#REF! -> #REF! | G39: =+'stock purchase 2026'!I1958 -> 2734.75 | H39: =+'daily sales'!#REF! -> #REF!
D40: jul | E40: =+'stock purchase 2026'!I477 -> 683.5 | F40: =+'daily sales'!#REF! -> #REF! | G40: =+'stock purchase 2026'!I2009 -> 1892 | H40: =+'daily sales'!#REF! -> #REF!
D41: aug | E41: =+'stock purchase 2026'!I650 -> 5598.5 | F41: =+'daily sales'!#REF! -> #REF! | G41: =+'stock purchase 2026'!I2045 -> 832 | H41: =+'daily sales'!#REF! -> #REF!
D42: sept | E42: =+'stock purchase 2026'!I691 -> 824 | F42: =+'daily sales'!#REF! -> #REF! | G42: =+'stock purchase 2026'!I2413 -> 5225.2 | H42: =+'daily sales'!#REF! -> #REF!
D43: oct | E43: =+'stock purchase 2026'!I778 -> 4046.8 | F43: =+'daily sales'!#REF! -> #REF! | G43: =+'stock purchase 2026'!I2466 -> 6497.2 | H43: =+'daily sales'!#REF!+'daily sales'!#REF! -> #REF!
D44: nov | E44: =+'stock purchase 2026'!I853 -> 2300 | F44: =+'daily sales'!#REF! -> #REF! | G44: =+'stock purchase 2026'!I2846 -> 4523.2857 | H44: =+M15 -> 5325
D45: dec | E45: =+'stock purchase 2026'!I871 -> 343 | F45: =+'daily sales'!#REF! -> #REF! | G45: =+'stock purchase 2026'!I2875 -> 489.27536 | H45: =+M16 -> 10621
D46: total | E46: =SUM(E34:E45) -> 24334.68 | F46: =SUM(F34:F45) -> #REF! | G46: =SUM(G34:G45) -> 36018.747 | H46: =SUM(H34:H45) -> #REF! | I46: =SUM(I34:I45) -> 0 | J46: =SUM(J34:J45) -> 0 | K46: =SUM(K34:K45) -> 0 | L46: =SUM(L34:L45) -> 0 | ... P46: =SUM(P34:P45) -> #REF!
B47: cargo | E47: =+cashbook!#REF!+cashbook!#REF!+cashbook!#REF!+cashbook!#REF!+cashbook!#REF!+cashbook!#REF!+cashbook!#REF!+cashbook!#REF!+cashbook!#REF!+cashbook!#REF!+cashbook!#REF!+cashbook!#REF!+cashbook!#REF!+cashbook!#REF!+cashbook!#REF!+cashbook!#REF!+cashbook!#REF!+cashbook!#REF!+cashbook!#REF!+cashbook!#REF! -> #REF! | G47: =+cashbook!#REF!+cashbook!#REF!+cashbook!#REF!+cashbook!#REF!+cashbook!#REF!+cashbook!#REF!+cashbook!#REF!+cashbook!#REF!+cashbook!#REF!+cashbook!#REF!+cashbook!#REF!+cashbook!#REF!+cashbook!#REF!+cashbook!#REF!+cashbook!#REF!+cashbook!#REF!+cashbook!#REF!+cashbook!#REF!+cashbook!#REF!+cashbook!#REF!+cashbook!#REF!+cashbook!#REF!+cashbook!#REF!+cashbook!#REF!+cashbook!#REF!+cashbook!#REF!+cashbook!#REF!+cashbook!#REF!+cashbook!#REF!+cashbook!#REF!+cashbook!#REF!+cashbook!#REF!+cashbook!#REF!+cashbook!#REF!+cashbook!#REF!+cashbook!#REF!+cashbook!#REF!+cashbook!#REF!+cashbook!#REF!+cashbook!#REF! -> #REF!
B49: GROSS ANNUAL PROFIT | F49: =+F46-E46-E47 -> #REF! | G49: =+H46-G46-G47 -> #REF!

Sheet stock purchase 2026
A1: SHOP | B1: shop | C1: label | E1: qnty | F1: size | G1: Item | I1: purchase price / unit $ | J1: total purchase price | K1: total cost excl stock | L1: Indirect Cost / unit | M1: Total Unit Cost | N1: Multiplier | O1: Rec Price | P1: Actual Price | Q1: reduced 4 sale | R1: stock take 4 | T1: date | U1: sales
C2: 45323
B3: white moon | C3: wioma | F3: 44 | G3: brown beige winter dress | I3: 25 | O3: 90 | P3: 90 | S3: macy tagwirei | T3: 45359 | U3: =+P3*18000 -> 1620000
B4: white moon | C4: wioma | F4: 46 | G4: brown beige winter dress | I4: 25 | O4: 90 | P4: 90 | S4: layby zezai | T4: 45377 | U4: =+P4*20000 -> 1800000
B5: white moon | C5: wioma | F5: 48 | G5: brown beige winter dress | I5: 25 | O5: 90 | P5: 90 | S5: cash, | T5: 45369 | U5: =+P5*18000 -> 1620000
B6: white moon | C6: wioma | F6: 50 | G6: brown beige winter dress | I6: 25 | O6: 90 | P6: 90 | S6: cash mai prudence | T6: 45358 | U6: =+P6*18000 -> 1620000
B7: white moon | C7: wioma | F7: 52 | G7: brown winter dress w beige sleeves | I7: 25 | O7: 90 | P7: 90 | S7: cash | T7: 45384 | U7: =+P7*35000 -> 3150000
B8: white moon | C8: wioma | F8: 54 | G8: brown winter dress w beige sleeves | I8: 25 | O8: 90 | P8: 90
B9: white moon | C9: wioma | F9: 56 | G9: brown winter dress w beige sleeves | I9: 25 | O9: 90 | P9: 90
B10: white moon | C10: wioma | F10: 58 | G10: brown winter dress w beige sleeves | I10: 25 | O10: 90 | P10: 90
B11: white moon | C11: wioma | F11: 44 | G11: black/white scotch w bottom pleats | I11: 25 | O11: 90 | P11: 90 | S11: cash | T11: 45372 | U11: =+P11*20000 -> 1800000
B12: white moon | C12: wioma | F12: 46 | G12: black/white scotch w bottom pleats | I12: 25 | O12: 90 | P12: 90 | S12: macy tagwirei | T12: 45359 | U12: =+P12*18000 -> 1620000
B13: white moon | C13: wioma | F13: 48 | G13: black/white scotch w bottom pleats | I13: 25 | O13: 90 | P13: 90 | S13: cash | T13: 45378 | U13: =+P13*30000 -> 2700000
B14: white moon | C14: wioma | F14: 50 | G14: black/white scotch w bottom pleats | I14: 25 | O14: 90 | P14: 90 | S14: cash | T14: 45384 | U14: =+P14*35000 -> 3150000
C15: wioma | F15: 44 | G15: beige / brown w front slit design | P15: 90
C16: wioma | F16: 46 | G16: beige / brown w front slit design | P16: 90
C17: wioma | F17: 48 | G17: beige / brown w front slit design | P17: 90
C18: wioma | F18: 50 | G18: beige / brown w front slit design | P18: 90
G19: FEBRUARY TOTAL | I19: =SUM(I3:I14) -> 300 | O19: =SUM(O3:O14) -> 1080
B21: GOWNS | G21: MARCH .2024
B22: Tango | C22: calino | F22: 42 | G22: green satin wrap over w sheer sleeves | I22: 45 | J22: 4192 | K22: 3417 | L22: =+K22/J22*I22 -> 36.680582 | M22: =+I22+L22 -> 81.680582 | N22: 1.4 | O22: =+M22*N22 -> 114.35281 | P22: 150
B23: Tango | C23: calino | F23: 44 | G23: green satin wrap over w sheer sleeves | I23: 45 | J23: 4192 | K23: 3417 | L23: =+K23/J23*I23 -> 36.680582 | M23: =+I23+L23 -> 81.680582 | N23: 1.4 | O23: =+M23*N23 -> 114.35281 | P23: 150
B24: Tango | C24: calino | F24: 46 | G24: green satin wrap over w sheer sleeves | I24: 45 | J24: 4192 | K24: 3417 | L24: =+K24/J24*I24 -> 36.680582 | M24: =+I24+L24 -> 81.680582 | N24: 1.4 | O24: =+M24*N24 -> 114.35281 | P24: 150 | S24: cash emilia | T24: 45386 | U24: =+P24*35000 -> 5250000
B25: Tango | C25: calino | F25: 48 | G25: green satin wrap over w sheer sleeves | I25: 45 | J25: 4192 | K25: 3417 | L25: =+K25/J25*I25 -> 36.680582 | M25: =+I25+L25 -> 81.680582 | N25: 1.4 | O25: =+M25*N25 -> 114.35281 | P25: 150 | S25: mandidzinga | T25: 45379 | U25: =+P25*30000 -> 4500000
B26: Tango | C26: calino | F26: 36 | G26: gold satin wrap over w sheer sleeves | I26: 45 | J26: 4192 | K26: 3417 | L26: =+K26/J26*I26 -> 36.680582 | M26: =+I26+L26 -> 81.680582 | N26: 1.4 | O26: =+M26*N26 -> 114.35281 | P26: 150
B27: Tango | C27: calino | F27: 38 | G27: gold satin wrap over w sheer sleeves | I27: 45 | J27: 4192 | K27: 3417 | L27: =+K27/J27*I27 -> 36.680582 | M27: =+I27+L27 -> 81.680582 | N27: 1.4 | O27: =+M27*N27 -> 114.35281 | P27: 150
B28: Tango | C28: calino | F28: 40 | G28: gold satin wrap over w sheer sleeves | I28: 45 | J28: 4192 | K28: 3417 | L28: =+K28/J28*I28 -> 36.680582 | M28: =+I28+L28 -> 81.680582 | N28: 1.4 | O28: =+M28*N28 -> 114.35281 | P28: 150
B29: Tango | C29: calino | F29: 42 | G29: gold satin wrap over w sheer sleeves | I29: 45 | J29: 4192 | K29: 3417 | L29: =+K29/J29*I29 -> 36.680582 | M29: =+I29+L29 -> 81.680582 | N29: 1.4 | O29: =+M29*N29 -> 114.35281 | P29: 150 | S29: cash | T29: 45378 | U29: =+P29*30000 -> 4500000
B30: fervente | C30: fervente | F30: 38 | G30: gold gown | I30: 38 | J30: 4192 | K30: 3417 | L30: =+K30/J30*I30 -> 30.974714 | M30: =+I30+L30 -> 68.974714 | N30: 1.4 | O30: =+M30*N30 -> 96.564599 | P30: 125
B31: fervente | C31: fervente | F31: 40 | G31: gold gown | I31: 38 | J31: 4192 | K31: 3417 | L31: =+K31/J31*I31 -> 30.974714 | M31: =+I31+L31 -> 68.974714 | N31: 1.4 | O31: =+M31*N31 -> 96.564599 | P31: 125
B32: fervente | C32: fervente | F32: 42 | G32: gold gown | I32: 38 | J32: 4192 | K32: 3417 | L32: =+K32/J32*I32 -> 30.974714 | M32: =+I32+L32 -> 68.974714 | N32: 1.4 | O32: =+M32*N32 -> 96.564599 | P32: 125
B33: fervente | C33: fervente | F33: 38 | G33: rose gold gown | I33: 29 | J33: 4192 | K33: 3417 | L33: =+K33/J33*I33 -> 23.638597 | M33: =+I33+L33 -> 52.638597 | N33: 1.4 | O33: =+M33*N33 -> 73.694036 | P33: 125
B34: fervente | C34: fervente | F34: 40 | G34: rose gold gown | I34: 29 | J34: 4192 | K34: 3417 | L34: =+K34/J34*I34 -> 23.638597 | M34: =+I34+L34 -> 52.638597 | N34: 1.4 | O34: =+M34*N34 -> 73.694036 | P34: 125
B35: fervente | C35: fervente | F35: 42 | G35: rose gold gown | I35: 29 | J35: 4192 | K35: 3417 | L35: =+K35/J35*I35 -> 23.638597 | M35: =+I35+L35 -> 52.638597 | N35: 1.4 | O35: =+M35*N35 -> 73.694036 | P35: 125
B36: fiero | C36: ladonatella | F36: 44 | G36: black /white sheer one arm gown | I36: 68 | J36: 4192 | K36: 3417 | L36: =+K36/J36*I36 -> 55.428435 | M36: =+I36+L36 -> 123.42844 | N36: 1.4 | O36: =+M36*N36 -> 172.79981 | P36: 200
B37: fiero | C37: ladonatella | F37: crew | G37: black /white sheer one arm gown | I37: 68 | J37: 4192 | K37: 3417 | L37: =+K37/J37*I37 -> 55.428435 | M37: =+I37+L37 -> 123.42844 | N37: 1.4 | O37: =+M37*N37 -> 172.79981 | P37: 200
B38: fiero | C38: ladonatella | F38: 48 | G38: black /white sheer one arm gown | I38: 68 | J38: 4192 | K38: 3417 | L38: =+K38/J38*I38 -> 55.428435 | M38: =+I38+L38 -> 123.42844 | N38: 1.4 | O38: =+M38*N38 -> 172.79981 | P38: 200 | S38: cash emilia | T38: 45386 | U38: =+P38*35000 -> 7000000
B39: fiero | C39: fiero | F39: 52 | G39: rose gold gown w front slit & sheer sleeve | I39: 68 | J39: 4192 | K39: 3417 | L39: =+K39/J39*I39 -> 55.428435 | M39: =+I39+L39 -> 123.42844 | N39: 1.4 | O39: =+M39*N39 -> 172.79981 | P39: 200
B40: fiero | C40: fiero | F40: 54 | G40: rose gold gown w front slit & sheer sleeve | I40: 68 | J40: 4192 | K40: 3417 | L40: =+K40/J40*I40 -> 55.428435 | M40: =+I40+L40 -> 123.42844 | N40: 1.4 | O40: =+M40*N40 -> 172.79981 | P40: 200
B41: fiero | C41: fiero | F41: 56 | G41: rose gold gown w front slit & sheer sleeve | I41: 68 | J41: 4192 | K41: 3417 | L41: =+K41/J41*I41 -> 55.428435 | M41: =+I41+L41 -> 123.42844 | N41: 1.4 | O41: =+M41*N41 -> 172.79981 | P41: 200
B42: fiero | C42: fiero | F42: 52 | G42: gold short gown | I42: 39 | J42: 4192 | K42: 3417 | L42: =+K42/J42*I42 -> 31.789838 | M42: =+I42+L42 -> 70.789838 | N42: 1.4 | O42: =+M42*N42 -> 99.105773
B43: fiero | C43: fiero | F43: 54 | G43: gold short gown | I43: 39 | J43: 4192 | K43: 3417 | L43: =+K43/J43*I43 -> 31.789838 | M43: =+I43+L43 -> 70.789838 | N43: 1.4 | O43: =+M43*N43 -> 99.105773 | P43: 125
B44: fiero | C44: fiero | F44: 56 | G44: gold short gown | I44: 39 | J44: 4192 | K44: 3417 | L44: =+K44/J44*I44 -> 31.789838 | M44: =+I44+L44 -> 70.789838 | N44: 1.4 | O44: =+M44*N44 -> 99.105773 | P44: 125
B46: DRESSES
B47: White pepper | C47: moda milla | F47: 42 | G47: black dress w white stripe | I47: 33 | J47: 4192 | K47: 3417 | L47: =+K47/J47*I47 -> 26.899094 | M47: =+I47+L47 -> 59.899094 | N47: 1.4 | O47: =+M47*N47 -> 83.858731 | P47: 110
B48: White pepper | C48: moda milla | F48: 44 | G48: black dress w white stripe | I48: 33 | J48: 4192 | K48: 3417 | L48: =+K48/J48*I48 -> 26.899094 | M48: =+I48+L48 -> 59.899094 | N48: 1.4 | O48: =+M48*N48 -> 83.858731 | P48: 110 | S48: cash | T48: 45378 | U48: =+P48*30000 -> 3300000
B49: White pepper | C49: moda milla | F49: 46 | G49: black dress w white stripe | I49: 33 | J49: 4192 | K49: 3417 | L49: =+K49/J49*I49 -> 26.899094 | M49: =+I49+L49 -> 59.899094 | N49: 1.4 | O49: =+M49*N49 -> 83.858731 | P49: 110
B50: White pepper | C50: moda milla | F50: 48 | G50: black dress w white stripe | I50: 33 | J50: 4192 | K50: 3417 | L50: =+K50/J50*I50 -> 26.899094 | M50: =+I50+L50 -> 59.899094 | N50: 1.4 | O50: =+M50*N50 -> 83.858731 | P50: 110
B51: black rose volonte | C51: black rose | F51: 38 | G51: green pleated skirt & blouse | I51: 40 | J51: 4192 | K51: 3417 | L51: =+K51/J51*I51 -> 32.604962 | M51: =+I51+L51 -> 72.604962 | N51: 1.4 | O51: =+M51*N51 -> 101.64695 | P51: 125
B52: black rose volonte | C52: black rose | F52: 40 | G52: green pleated skirt & blouse | I52: 40 | J52: 4192 | K52: 3417 | L52: =+K52/J52*I52 -> 32.604962 | M52: =+I52+L52 -> 72.604962 | N52: 1.4 | O52: =+M52*N52 -> 101.64695 | P52: 125
B53: black rose volonte | C53: black rose | F53: 42 | G53: green pleated skirt & blouse | I53: 40 | J53: 4192 | K53: 3417 | L53: =+K53/J53*I53 -> 32.604962 | M53: =+I53+L53 -> 72.604962 | N53: 1.4 | O53: =+M53*N53 -> 101.64695 | P53: 110 | S53: tete chipo | T53: 45379 | U53: =+P53*30000 -> 3300000
B54: black rose volonte | C54: black rose | F54: 44 | G54: green pleated skirt & blouse | I54: 40 | J54: 4192 | K54: 3417 | L54: =+K54/J54*I54 -> 32.604962 | M54: =+I54+L54 -> 72.604962 | N54: 1.4 | O54: =+M54*N54 -> 101.64695 | P54: 110
B55: black rose volonte | C55: black rose | F55: 44 | G55: coffee pleated skirt & blouse | I55: 42 | J55: 4192 | K55: 3417 | L55: =+K55/J55*I55 -> 34.23521 | M55: =+I55+L55 -> 76.23521 | N55: 1.4 | O55: =+M55*N55 -> 106.72929 | P55: 110
B56: black rose volonte | C56: black rose | F56: 46 | G56: coffee pleated skirt & blouse | I56: 42 | J56: 4192 | K56: 3417 | L56: =+K56/J56*I56 -> 34.23521 | M56: =+I56+L56 -> 76.23521 | N56: 1.4 | O56: =+M56*N56 -> 106.72929 | P56: 110
B57: black rose volonte | C57: black rose | F57: 48 | G57: coffee pleated skirt & blouse | I57: 42 | J57: 4192 | K57: 3417 | L57: =+K57/J57*I57 -> 34.23521 | M57: =+I57+L57 -> 76.23521 | N57: 1.4 | O57: =+M57*N57 -> 106.72929 | P57: 110
B58: black rose volonte | C58: black rose | F58: 50 | G58: coffee pleated skirt & blouse | I58: 42 | J58: 4192 | K58: 3417 | L58: =+K58/J58*I58 -> 34.23521 | M58: =+I58+L58 -> 76.23521 | N58: 1.4 | O58: =+M58*N58 -> 106.72929 | P58: 110
B59: black rose volonte | C59: black rose | F59: 44 | G59: orange pleated skirt & blouse | I59: 37 | J59: 4192 | K59: 3417 | L59: =+K59/J59*I59 -> 30.15959 | M59: =+I59+L59 -> 67.15959 | N59: 1.4 | O59: =+M59*N59 -> 94.023426 | P59: 125 | S59: tete chipo | T59: 45379 | U59: =+P59*30000 -> 3750000
B60: black rose volonte | C60: black rose | F60: 46 | G60: orange pleated skirt & blouse | I60: 37 | J60: 4192 | K60: 3417 | L60: =+K60/J60*I60 -> 30.15959 | M60: =+I60+L60 -> 67.15959 | N60: 1.4 | O60: =+M60*N60 -> 94.023426 | P60: 125 | S60: cash | T60: 45378 | U60: =+P60*30000 -> 3750000
B61: black rose volonte | C61: black rose | F61: 48 | G61: orange pleated skirt & blouse | I61: 37 | J61: 4192 | K61: 3417 | L61: =+K61/J61*I61 -> 30.15959 | M61: =+I61+L61 -> 67.15959 | N61: 1.4 | O61: =+M61*N61 -> 94.023426 | P61: 125
B62: black rose volonte | C62: black rose | F62: 50 | G62: orange pleated skirt & blouse | I62: 37 | J62: 4192 | K62: 3417 | L62: =+K62/J62*I62 -> 30.15959 | M62: =+I62+L62 -> 67.15959 | N62: 1.4 | O62: =+M62*N62 -> 94.023426 | P62: 125
B63: IDEAL | C63: mast fashion | F63: 42 | G63: green/white dress net material w white belt | I63: 27 | J63: 4192 | K63: 3417 | L63: =+K63/J63*I63 -> 22.008349 | M63: =+I63+L63 -> 49.008349 | N63: 1.4 | O63: =+M63*N63 -> 68.611689 | P63: 110
B64: IDEAL | C64: mast fashion | F64: 44 | G64: green/white dress net material w white belt | I64: 27 | J64: 4192 | K64: 3417 | L64: =+K64/J64*I64 -> 22.008349 | M64: =+I64+L64 -> 49.008349 | N64: 1.4 | O64: =+M64*N64 -> 68.611689 | P64: 110
B65: IDEAL | C65: mast fashion | F65: 46 | G65: green/white dress net material w white belt | I65: 27 | J65: 4192 | K65: 3417 | L65: =+K65/J65*I65 -> 22.008349 | M65: =+I65+L65 -> 49.008349 | N65: 1.4 | O65: =+M65*N65 -> 68.611689 | P65: 110
B66: IDEAL | C66: mast fashion | F66: 48 | G66: green/white dress net material w white belt | I66: 27 | J66: 4192 | K66: 3417 | L66: =+K66/J66*I66 -> 22.008349 | M66: =+I66+L66 -> 49.008349 | N66: 1.4 | O66: =+M66*N66 -> 68.611689 | P66: 110 | S66: cash | T66: 45371 | U66: =+P66*20000 -> 2200000
B67: IDEAL | C67: my tenim | F67: 42 | G67: denim shirt dress w white tie/dye design | I67: 35 | J67: 4192 | K67: 3417 | L67: =+K67/J67*I67 -> 28.529342 | M67: =+I67+L67 -> 63.529342 | N67: 1.4 | O67: =+M67*N67 -> 88.941078 | P67: 110
B68: IDEAL | C68: my tenim | F68: 44 | G68: denim shirt dress w white tie/dye design | I68: 35 | J68: 4192 | K68: 3417 | L68: =+K68/J68*I68 -> 28.529342 | M68: =+I68+L68 -> 63.529342 | N68: 1.4 | O68: =+M68*N68 -> 88.941078 | P68: 110
B69: IDEAL | C69: my tenim | F69: 46 | G69: denim shirt dress w white tie/dye design | I69: 35 | J69: 4192 | K69: 3417 | L69: =+K69/J69*I69 -> 28.529342 | M69: =+I69+L69 -> 63.529342 | N69: 1.4 | O69: =+M69*N69 -> 88.941078 | P69: 110
B70: IDEAL | C70: my tenim | F70: 48 | G70: denim shirt dress w white tie/dye design | I70: 35 | J70: 4192 | K70: 3417 | L70: =+K70/J70*I70 -> 28.529342 | M70: =+I70+L70 -> 63.529342 | N70: 1.4 | O70: =+M70*N70 -> 88.941078 | P70: 110
B71: IDEAL | C71: M | F71: 42 | G71: beige dress w black frill | I71: 36 | J71: 4192 | K71: 3417 | L71: =+K71/J71*I71 -> 29.344466 | M71: =+I71+L71 -> 65.344466 | N71: 1.4 | O71: =+M71*N71 -> 91.482252 | P71: 125
B72: IDEAL | C72: M | F72: 44 | G72: beige dress w black frill | I72: 36 | J72: 4192 | K72: 3417 | L72: =+K72/J72*I72 -> 29.344466 | M72: =+I72+L72 -> 65.344466 | N72: 1.4 | O72: =+M72*N72 -> 91.482252 | P72: 125
B73: IDEAL | C73: M | F73: 46 | G73: beige dress w black frill | I73: 36 | J73: 4192 | K73: 3417 | L73: =+K73/J73*I73 -> 29.344466 | M73: =+I73+L73 -> 65.344466 | N73: 1.4 | O73: =+M73*N73 -> 91.482252 | P73: 125
B74: IDEAL | C74: M | F74: 48 | G74: beige dress w black frill | I74: 36 | J74: 4192 | K74: 3417 | L74: =+K74/J74*I74 -> 29.344466 | M74: =+I74+L74 -> 65.344466 | N74: 1.4 | O74: =+M74*N74 -> 91.482252 | P74: 125
B75: IDEAL | C75: F & B girls | F75: 50 | G75: black/gold denim shirt dress w belt | I75: 42 | J75: 4192 | K75: 3417 | L75: =+K75/J75*I75 -> 34.23521 | M75: =+I75+L75 -> 76.23521 | N75: 1.4 | O75: =+M75*N75 -> 106.72929 | P75: 125
B76: IDEAL | C76: F & B girls | F76: 52 | G76: black/gold denim shirt dress w belt | I76: 42 | J76: 4192 | K76: 3417 | L76: =+K76/J76*I76 -> 34.23521 | M76: =+I76+L76 -> 76.23521 | N76: 1.4 | O76: =+M76*N76 -> 106.72929 | P76: 125
B77: IDEAL | C77: F & B girls | F77: 54 | G77: black/gold denim shirt dress w belt | I77: 42 | J77: 4192 | K77: 3417 | L77: =+K77/J77*I77 -> 34.23521 | M77: =+I77+L77 -> 76.23521 | N77: 1.4 | O77: =+M77*N77 -> 106.72929 | P77: 125
B78: IDEAL | C78: F & B girls | F78: 56 | G78: black/gold denim shirt dress w belt | I78: 42 | J78: 4192 | K78: 3417 | L78: =+K78/J78*I78 -> 34.23521 | M78: =+I78+L78 -> 76.23521 | N78: 1.4 | O78: =+M78*N78 -> 106.72929 | P78: 125 | S78: cash mazanhi | T78: 45379 | U78: =+P78*30000 -> 3750000
B79: fervente | C79: fervente | F79: 38 | G79: hot pink pleated dress w waist design | I79: 22 | J79: 4192 | K79: 3417 | L79: =+K79/J79*I79 -> 17.932729 | M79: =+I79+L79 -> 39.932729 | N79: 1.4 | O79: =+M79*N79 -> 55.905821 | P79: 110
B80: fervente | C80: fervente | F80: 40 | G80: hot pink pleated dress w waist design | I80: 22 | J80: 4192 | K80: 3417 | L80: =+K80/J80*I80 -> 17.932729 | M80: =+I80+L80 -> 39.932729 | N80: 1.4 | O80: =+M80*N80 -> 55.905821 | P80: 110
B81: fervente | C81: fervente | F81: 42 | G81: hot pink pleated dress w waist design | I81: 22 | J81: 4192 | K81: 3417 | L81: =+K81/J81*I81 -> 17.932729 | M81: =+I81+L81 -> 39.932729 | N81: 1.4 | O81: =+M81*N81 -> 55.905821 | P81: 110
B82: fervente | C82: fervente | F82: 38 | G82: cream pleated dress w waist design | I82: 22 | J82: 4192 | K82: 3417 | L82: =+K82/J82*I82 -> 17.932729 | M82: =+I82+L82 -> 39.932729 | N82: 1.4 | O82: =+M82*N82 -> 55.905821 | P82: 110
B83: fervente | C83: fervente | F83: 40 | G83: cream pleated dress w waist design | I83: 22 | J83: 4192 | K83: 3417 | L83: =+K83/J83*I83 -> 17.932729 | M83: =+I83+L83 -> 39.932729 | N83: 1.4 | O83: =+M83*N83 -> 55.905821 | P83: 110
B84: fervente | C84: fervente | F84: 42 | G84: cream pleated dress w waist design | I84: 22 | J84: 4192 | K84: 3417 | L84: =+K84/J84*I84 -> 17.932729 | M84: =+I84+L84 -> 39.932729 | N84: 1.4 | O84: =+M84*N84 -> 55.905821 | P84: 110
B85: darkmen | C85: darkmen | F85: 1 | G85: green/black polka dot cotton dress | I85: 24 | J85: 4192 | K85: 3417 | L85: =+K85/J85*I85 -> 19.562977 | M85: =+I85+L85 -> 43.562977 | N85: 1.4 | O85: =+M85*N85 -> 60.988168 | P85: 110
B86: darkmen | C86: darkmen | F86: 2 | G86: green/black polka dot cotton dress | I86: 24 | J86: 4192 | K86: 3417 | L86: =+K86/J86*I86 -> 19.562977 | M86: =+I86+L86 -> 43.562977 | N86: 1.4 | O86: =+M86*N86 -> 60.988168 | P86: 110 | S86: cash mazanhi | T86: 45374 | U86: =+P86*20000 -> 2200000
B87: darkmen | C87: darkmen | F87: 1 | G87: beige/black cotton dress | I87: 24 | J87: 4192 | K87: 3417 | L87: =+K87/J87*I87 -> 19.562977 | M87: =+I87+L87 -> 43.562977 | N87: 1.4 | O87: =+M87*N87 -> 60.988168 | P87: 110
B88: darkmen | C88: darkmen | F88: 2 | G88: beige/black cotton dress | I88: 24 | J88: 4192 | K88: 3417 | L88: =+K88/J88*I88 -> 19.562977 | M88: =+I88+L88 -> 43.562977 | N88: 1.4 | O88: =+M88*N88 -> 60.988168 | P88: 110 | S88: cash mazanhi | T88: 45374 | U88: =+P88*20000 -> 2200000
B89: darkmen | C89: darkmen | F89: 1 | G89: denim look midi sleeveless dress | I89: 23 | J89: 4192 | K89: 3417 | L89: =+K89/J89*I89 -> 18.747853 | M89: =+I89+L89 -> 41.747853 | N89: 1.4 | O89: =+M89*N89 -> 58.446994 | P89: 110
B90: darkmen | C90: darkmen | F90: 2 | G90: denim look midi sleeveless dress | I90: 23 | J90: 4192 | K90: 3417 | L90: =+K90/J90*I90 -> 18.747853 | M90: =+I90+L90 -> 41.747853 | N90: 1.4 | O90: =+M90*N90 -> 58.446994 | P90: 110
B91: modagun | C91: modagun | F91: 50 | G91: green chiffon short dress | I91: 25 | J91: 4192 | K91: 3417 | L91: =+K91/J91*I91 -> 20.378101 | M91: =+I91+L91 -> 45.378101 | N91: 1.4 | O91: =+M91*N91 -> 63.529342 | P91: 110
B92: modagun | C92: modagun | F92: 52 | G92: green chiffon short dress | I92: 25 | J92: 4192 | K92: 3417 | L92: =+K92/J92*I92 -> 20.378101 | M92: =+I92+L92 -> 45.378101 | N92: 1.4 | O92: =+M92*N92 -> 63.529342 | P92: 110
B93: modagun | C93: modagun | F93: 54 | G93: green chiffon short dress | I93: 25 | J93: 4192 | K93: 3417 | L93: =+K93/J93*I93 -> 20.378101 | M93: =+I93+L93 -> 45.378101 | N93: 1.4 | O93: =+M93*N93 -> 63.529342 | P93: 110
B94: modagun | C94: modagun | F94: 56 | G94: green chiffon short dress | I94: 25 | J94: 4192 | K94: 3417 | L94: =+K94/J94*I94 -> 20.378101 | M94: =+I94+L94 -> 45.378101 | N94: 1.4 | O94: =+M94*N94 -> 63.529342 | P94: 110
B95: modagun | C95: modagun | F95: 50 | G95: cream/hot pink chiffon dress | I95: 25 | J95: 4192 | K95: 3417 | L95: =+K95/J95*I95 -> 20.378101 | M95: =+I95+L95 -> 45.378101 | N95: 1.4 | O95: =+M95*N95 -> 63.529342 | P95: 110
B96: modagun | C96: modagun | F96: 52 | G96: cream/hot pink chiffon dress | I96: 25 | J96: 4192 | K96: 3417 | L96: =+K96/J96*I96 -> 20.378101 | M96: =+I96+L96 -> 45.378101 | N96: 1.4 | O96: =+M96*N96 -> 63.529342 | P96: 110
B97: modagun | C97: modagun | F97: 54 | G97: cream/hot pink chiffon dress | I97: 25 | J97: 4192 | K97: 3417 | L97: =+K97/J97*I97 -> 20.378101 | M97: =+I97+L97 -> 45.378101 | N97: 1.4 | O97: =+M97*N97 -> 63.529342 | P97: 110
B98: modagun | C98: modagun | F98: 56 | G98: cream/hot pink chiffon dress | I98: 25 | J98: 4192 | K98: 3417 | L98: =+K98/J98*I98 -> 20.378101 | M98: =+I98+L98 -> 45.378101 | N98: 1.4 | O98: =+M98*N98 -> 63.529342 | P98: 110
B99: white moon | C99: fimas | F99: 44 | G99: army green flared chiffon dress w flower design | I99: 25 | J99: 4192 | K99: 3417 | L99: =+K99/J99*I99 -> 20.378101 | M99: =+I99+L99 -> 45.378101 | N99: 1.4 | O99: =+M99*N99 -> 63.529342 | P99: 110 | S99: layby manhambara | T99: 45384 | U99: =+P99*35000 -> 3850000
B100: white moon | C100: fimas | F100: 46 | G100: army green flared chiffon dress w flower design | I100: 25 | J100: 4192 | K100: 3417 | L100: =+K100/J100*I100 -> 20.378101 | M100: =+I100+L100 -> 45.378101 | N100: 1.4 | O100: =+M100*N100 -> 63.529342 | P100: 110
B101: white moon | C101: fimas | F101: 48 | G101: army green flared chiffon dress w flower design | I101: 25 | J101: 4192 | K101: 3417 | L101: =+K101/J101*I101 -> 20.378101 | M101: =+I101+L101 -> 45.378101 | N101: 1.4 | O101: =+M101*N101 -> 63.529342 | P101: 110 | S101: credit mukuruva | T101: 45384 | U101: =+P101*35000 -> 3850000
B102: white moon | C102: fimas | F102: 50 | G102: army green flared chiffon dress w flower design | I102: 25 | J102: 4192 | K102: 3417 | L102: =+K102/J102*I102 -> 20.378101 | M102: =+I102+L102 -> 45.378101 | N102: 1.4 | O102: =+M102*N102 -> 63.529342 | P102: 110
...

Sheet sops
A1: to
B2: all layby & credit sales instalments to be updated on invoice for audit purposes
B3: daily analysis to be completed daily & check all transactions against receipts, invoices, pos & zimra machine
B5: DAILY SALES TO BE RECORDED AND RECONCILED DAILY
B7: REGULAR STOCK SPOT CHECK ESP ON NEW STOCK
B9: stock taken by clients home for fitting | G9: double check labels and quanity when returned
G10: double check labels and quanity when going out
G11: record in the stock out diary when stock leaves the shop
G12: tick and cancell returned stock
G13: record stock taken by client on the daily analysis and cash/credit invoice
G14: end of every week cross check if there is stock that went out which has not been returned
B16: discounts | G16: only given on cash purchases
G17: have a cash discount receipt stating discount amount and signed by the client
G18: max discount discretion is $5
B20: cash received allocation
G21: weekly $100 savings | L21: 100
G22: weekly $ 50 education fund savings | L22: 50
F23: balance to | G23: stock procurement | L23: 0.5
G24: investment | L24: 0.1
G25: home improvement | L25: 0.1
G26: working capital | L26: 0.3

Sheet salaries
A1: to
C2: Jan | D2: Feb | E2: Mar | F2: Apr | G2: May | H2: Jun | I2: Jul | J2: Aug | K2: Sep | L2: Oct | M2: Nov | N2: Dec
B3: sales USD
B5: salary
B6: Pauline
B7: Tatenda
B9: Transport ZWD
B10: Pauline
B11: WEEK 1
B12: WEEK 2
B13: WEEK 3
B14: WEEK 4
B15: Tatenda
B16: WEEK 1
... B26: STAFF LEAVE DAYS
C27: PAU # of days | D27: dates | G27: TATENDA # of days | H27: dates | K27: nyadzi # of days | L27: dates | O27: angelica | P27: dates
C28: 1 | D28: 1./01/25 | G28: 7 | H28: 20.-26 JAN | K28: 7 | L28: 6-.12 JAN | O28: 1 | P28: 14-15 april | Q28: 2 days but she covered for 1 day on easter Friday
C29: 1 | D29: 4/23/2025. | G29: 6 | H29: 30 june-5 july | K29: 1 | L29: 1 april 2025. | M29: child sick
C30: 6 | D30: 16-21 june 2025 | G30: 7 | H30: 6-12 october | K30: 5 | L30: 6-10. apr
C31: 1 | D31: 45836
C32: 8 | D32: 16-22 aug
B33: TOTAL | C33: =SUM(C28:C32) -> 17 | G33: =SUM(G28:G32) -> 20 | K33: =SUM(K28:K32) -> 13 | O33: =SUM(O28:O32) -> 1
B36: salary advances | D36: sept | E36: October | F36: Nov | G36: Dec | I36: jan | J36: feb | K36: mar | L36: april | M36: may | N36: june
B37: Pauline | C37: 100 | D37: -25 | E37: -25 | F37: -25 | G37: -25 | L37: 80 | N37: 50 | O37: -25
B38: nyadzi nov | C38: 20 | F38: -20 | L38: 20
B40: Angelica | I40: 20
B43: monthly salary confirmation | F43: jan | G43: feb | H43: mar | I43: apr | J43: may | K43: june | L43: july
B45: Pauline | C45: salary | F45: 200 | G45: 200 | H45: 200 | I45: 200 | J45: 200
C46: transport | F46: 80 | G46: 80 | H46: 100 | I46: 100 | J46: 100
C47: comm
C48: advance | D48: 80 | J48: -20
C49: actual paid | F49: =SUM(F45:F48) -> 280 | G49: =SUM(G45:G48) -> 280 | H49: =SUM(H45:H48) -> 300 | I49: =SUM(I45:I48) -> 300 | J49: =SUM(J45:J48) -> 280
B52: tatenda | C52: salary | F52: 200 | G52: 200 | H52: 200 | I52: 200 | J52: 200 | K52: 200 | L52: 400
C53: transport | F53: 80 | G53: 80 | H53: 100
C54: comm | H54: 20
C55: advance | H55: 50
C56: actual paid | F56: =SUM(F52:F55) -> 280 | G56: =SUM(G52:G55) -> 280 | H56: =SUM(H52:H55) -> 370 | I56: =SUM(I52:I55) -> 200 | J56: =SUM(J52:J55) -> 200 | K56: =SUM(K52:K55) -> 200 | L56: =SUM(L52:L55) -> 400
B59: Rufaro | C59: salary | F59: 200 | G59: 200 | H59: 200 | I59: 200 | J59: 200 | K59: 200 | L59: 220
F60: 80 | G60: 80 | H60: 100
C61: comm | G61: 0 | L61: 9
C62: advance
C63: actual paid | F63: =SUM(F59:F62) -> 280 | G63: =SUM(G59:G62) -> 280 | H63: =SUM(H59:H62) -> 300 | I63: =SUM(I59:I62) -> 200 | J63: =SUM(J59:J62) -> 200 | K63: =SUM(K59:K62) -> 200 | L63: =SUM(L59:L62) -> 229
B66: angelica | C66: salary | F66: 150 | G66: 150 | H66: 150 | I66: 150 | J66: 150 | K66: 150 | L66: 150
C67: advance | F67: 0 | G67: 0
C68: actual paid | F68: =SUM(F66:F67) -> 150 | G68: =SUM(G66:G67) -> 150 | H68: =SUM(H66:H67) -> 150 | I68: =SUM(I66:I67) -> 150 | J68: =SUM(J66:J67) -> 150 | K68: =SUM(K66:K67) -> 150 | L68: =SUM(L66:L67) -> 150

Sheet stock movement
B36: stock type | C36: opening level | D36: adds in the year | E36: closing level | F36: amnt sold during the year | G36: % sale
A38: 2 | B38: panties | C38: 209 | E38: 69 | F38: =+C38-E38 -> 140 | G38: =+F38/C38*100 -> 66.985646
A39: 3 | B39: clutch bags | C39: 72 | E39: 28 | F39: =+C39-E39 -> 44 | G39: =+F39/C39*100 -> 61.111111
A40: 4 | B40: jerseys | C40: 82 | E40: 32 | F40: =+C40-E40 -> 50 | G40: =+F40/C40*100 -> 60.97561
A41: 5 | B41: scarfs | C41: 24 | E41: 10 | F41: =+C41-E41 -> 14 | G41: =+F41/C41*100 -> 58.333333
A42: 6 | B42: dresses | C42: 912 | E42: 381 | F42: =+C42-E42 -> 531 | G42: =+F42/C42*100 -> 58.223684
A43: 7 | B43: coserts | C43: 19 | E43: 8 | F43: =+C43-E43 -> 11 | G43: =+F43/C43*100 -> 57.894737
A44: 8 | B44: handbags | C44: 57 | E44: 25 | F44: =+C44-E44 -> 32 | G44: =+F44/C44*100 -> 56.140351
A45: 9 | B45: jackets | C45: 48 | E45: 22 | F45: =+C45-E45 -> 26 | G45: =+F45/C45*100 -> 54.166667
A46: 10 | B46: pantyhose | C46: 49 | E46: 25 | F46: =+C46-E46 -> 24 | G46: =+F46/C46*100 -> 48.979592
A47: 11 | B47: tops & blouses | C47: 271 | E47: 139 | F47: =+C47-E47 -> 132 | G47: =+F47/C47*100 -> 48.708487
A48: 12 | B48: dress outfits | C48: 64 | E48: 36 | F48: =+C48-E48 -> 28 | G48: =+F48/C48*100 -> 43.75
A49: 13 | B49: skirts | C49: 169 | E49: 100 | F49: =+C49-E49 -> 69 | G49: =+F49/C49*100 -> 40.828402
... A57: 21 | B57: pajamas | C57: 4 | E57: 3 | F57: =+C57-E57 -> 1 | G57: =+F57/C57*100 -> 25
